Workbook
Name OLE_LINK1: Carátula!$A$1

Sheet Carátula

Sheet Indice
B1: Índice Boletin Anual de Empresas por Provincias (a 2 dígitos)
B3: Partidos de GBA | C3: Formosa | D3: Salta
CE4: 4° Trim 2015 | CF4: 1° Trim 2016
B5: Capital Federal | C5: Jujuy | D5: San Juan
B7: Resto de Bueno Aires | C7: La Pampa | D7: San Luis
B9: Catamarca | C9: La Rioja | D9: Santa Cruz
B11: Córdoba | C11: Mendoza | D11: Santa Fe
B13: Corrientes | C13: Misiones | D13: Santiago del Estero
B15: Chaco | C15: Neuquén | D15: Tucumán
B17: Chubut | C17: Río Negro | D17: Tierra del Fuego
B19: Entre Ríos

Sheet Metodología
A1: Nota metodológica
A4: ESTADÍSTICAS SOBRE EMPRESAS Y EMPLEO ASALARIADO REGISTRADO PORPROVINCIA
A6: El Boletín Provincial recopila una serie de tablas estadísticas elaboradas por el Observatorio de Empleo y Dinámica Empresarial[1] del Ministerio de Trabajo, Empleo y Seguridad Social.
A8: Tiene como fuente los registros administrativos del Sistema Integrado Previsional Argentino (SIPA) que contienen las declaraciones mensuales que realizan las empresas sobre el personal que tienen en relación de dependencia para el pago de los aportes y contribuciones patronales. La unidad de análisis es la empresa, definida como una unidad legal independiente[2] y está identificada por su Código Único de Identificación Tributaria (CUIT). Los indicadores se refieren al empleo asalariado registrado y a las empresas privadas de industria, comercio y servicios radicadas en todo el país.
A10: Las empresas se encuentran clasificadas según las provincias donde declaran sus ocupados. Es decir, las empresas que informan sobre sus trabajadores en diferentes provincias se contabilizan en cada una de las provincias donde declararon ocupados, por ello, la suma de las empresas desagregadas por provincia supera al total de empresas que operan efectivamente en el país. Asimismo, el empleo se encuentra clasificado por provincia de acuerdo a las zonas donde las empresas declaran que trabajan sus empleados.
A12: CONSTRUCCIÓN DE LA BASE LONGITUDINAL
A14: El grado de desagregación alcanzado y la frecuencia con que se actualiza la información permiten el tratamiento de series longitudinales que registran la evolución del empleo al nivel de cada empresa. Esto posibilita calcular por un lado el empleo creado por las empresas que expanden sus dotaciones de personal y el creado por empresas nuevas; y por otro lado, el empleo destruido por las empresas que contraen sus dotaciones y el destruido por las empresas que cierran[3].
A16: La construcción de esta base longitudinal involucra varios procesos cuyo objetivo final es el de consolidar, a partir del registro administrativo, un sistema de información estadístico. Una de las principales dificultades estadísticas que presenta el registro, y que se deben resolver es la discontinuidad de la información.
A18: Es frecuente encontrar en un registro administrativo vacíos de información producidos por distintas causas (declaraciones tardías, errores de carga, etc.) y que no reflejan cambios reales en la información. Podría citarse como ejemplo el caso de empresas que aparecen en el registro con meses de falta de declaración seguidos y antecedidos por meses de declaración positiva de empleo. En estos casos, los valores nulos se completan utilizando la información de los períodos anterior y posterior. Sin embargo, cuando el período sin declaraciones de una firma es prolongado, se respetan los datos consignados porque se entiende que reflejan discontinuidades reales en el empleo[4]
A20: TOTAL DE FIRMAS Y FIRMAS LOCALES
A22: Se considera que son “firmas locales” a aquellas firmas que declaran una mayor proporción de su empleo en la provincia de referencia. Es decir, una misma firma diversificada en el territorio nacional será “firma local” en la provincia donde declara más empleo y “firma no local” en el resto de las provincias donde declare la otra parte del empleo.
A24: Esta distinción es particularmente importante para analizar demografía de empresas. La entrada y salida de las firmas no locales es muy volátil, mientras que la movilidad de las firmas locales suele ser más estable reflejando de mejor manera los procesos de expansión del tejido productivo en las regiones.
... A30: Quedan excluidos del registro:
A31: O | B31: Trabajadores del sector público.
A32: O | B32: Trabajadores en casas particulares.
A33: O | B33: Asalariados no registrados.
A34: O | B34: Trabajadores por cuenta propia, patrones y trabajo familiar.
A38: DEFINICIONES
A40: A continuación se presentan las definiciones que se utilizaron para el análisis de la demografía (movilidad) de las empresas:
A42: Empresas que abren: Son empresas que inician actividades durante el período de referencia. Se identifica el inicio de actividades de una firma, a partir de la fecha de las primeras declaraciones de personal ocupado de las nuevas firmas. Para el análisis de la antigüedad de las firmas se toma en cuenta también la fecha de ingreso al padrón de empleadores de AFIP.
A44: Empresas que cierran: Se definen a partir de un criterio empírico que considera como cerrada (dada de baja) a toda empresa que no declara personal ocupado a lo largo de un año (4 trimestres) [5]. Para poder medir el impacto de los cierres en los flujos de empleo, se considera que el momento en que se produce el cierre de la empresa es el primer período de empleo nulo[6]
A46: Cambio neto de empresas: Es la diferencia entre las aperturas y los cierres de empresas.
A48: Tasas de entrada y tasa de salida de empresas: Es la cantidad de empresas creadas/destruidas en el período dividido por el total de empresas existentes a lo largo del período. Es decir, en el denominador se incluyen a las empresas activas (aperturas, sobrevivientes de periodos anteriores) así como a los cierres del periodo.
A50: Tasa de cambio neto: Es la diferencia entre la tasa de entrada y de salida de empresas.
A54: RAMA DE ACTIVIDAD ECONOMICA
A56: Es la rama de actividad principal, codificada con la revisión 3 del código CIIU. La información original de rama surge del padrón de contribuyentes de AFIP y se mejora incorporando información de otras fuentes: principalmente la Encuesta de Indicadores Laborales (EIL), guías de empresas, consultas a Cámaras y Organismos Reguladores, y otras bases de registros de empresas.
A58: ESTRATIFICACION DE LAS EMPRESAS POR TAMAÑO
A60: La estratificación por tamaño para una empresa en determinado trimestre se realiza a partir del empleo promedio declarado por la firma durante los últimos cuatro trimestres. Por ejemplo: para calcular el tamaño de una empresa en el 4to trimestre del año 2015, se toma en cuenta el promedio del empleo declarardo por la misma en cada trimestre del año 2015.
A62: Los rangos de empleo utilizados en cada estrato de tamaño varían según rama de actividad, atendiendo a diferencias sectoriales en la productividad media del trabajo y a las pautas establecidas por el país para la aplicación de políticas orientadas a la pequeña y mediana empresa. Estos tramos se determinaron a partir del nivel de ventas de las empresas definido por la SEPyME en la Resolución 24/2001 que establece el nivel máximo de ventas para cada categoría de empresa (micro, pequeña, mediana y gran empresa) según el sector en el que desarrollan su actividad.
... A67: CORTES POR TAMAÑO ($)
B68: Agropecuario | C68: Industria y Minería | D68: Comercio | E68: Servicios
A69: Micro | B69: 150000 | C69: 500000 | D69: 1000000 | E69: 250000
A70: Pequeña | B70: 1000000 | C70: 3000000 | D70: 6000000 | E70: 1800000
A71: Mediana | B71: 6000000 | C71: 24000000 | D71: 48000000 | E71: 12000000
A72: Fuente: Resolución SEPyME N° 24/01
A74: A partir de las estimaciones realizadas se definieron tramos ocupacionales, que ponen en evidencia las fuertes diferencias entre los distintos sectores (industria, comercio y servicios) y entre las distintas ramas de actividad al interior de cada sector. Se presentan a continuación los resultados que surgieron de las estimaciones realizadas para definir los tramos de empleo que permiten clasificar a las firmas según su tamaño económico.
A76: Se enuncian los topes máximos para cada categoría, con una desagregación de dos dígitos de la CIIU Revisión 3.
A78: TOPES MÁXIMOS PARA CADA CATEGORÍA: INDUSTRIA MANUFACTURERA
A79: Rama de actividad | C79: Micro | D79: Pequeña | E79: Mediana
A80: 15 | B80: Elaboración de productos alimenticios y bebidas | C80: 6 | D80: 34 | E80: 128
A81: 16 | B81: Elaboración de productos de tabaco | C81: 5 | D81: 30 | E81: 118
A82: 17 | B82: Fabricación de productos textiles | C82: 5 | D82: 25 | E82: 122
A83: 18 | B83: Fabricación de prendas de vestir; terminación y teñido de pieles | C83: 5 | D83: 21 | E83: 202
A84: 19 | B84: Curtido y terminación de cueros; fabricación de maletas, bolsos de mano. Artículos de talabartería y guarnicioneria, y calzado | C84: 4 | D84: 31 | E84: 125
A85: 20 | B85: Producción de madera y fabricación de productos de madera y corcho excepto muebles; fabricación de artículos de paja y de materiales trenzables | C85: 5 | D85: 19 | E85: 108
A86: 21 | B86: Fabricación de papel y de productos de papel | C86: 5 | D86: 26 | E86: 74
A87: 22 | B87: Actividades de edición e impresión y de reproducción de grabaciones | C87: 4 | D87: 20 | E87: 69
A88: 23 | B88: Fabricación de productos del petróleo | C88: 3 | D88: 28 | E88: 68
A89: 24 | B89: Fabricación de sustancias y productos químicos | C89: 5 | D89: 23 | E89: 100
A90: 25 | B90: Fabricación de productos de caucho y plástico | C90: 5 | D90: 22 | E90: 82
A91: 26 | B91: Fabricación de otros productos minerales no metálicos | C91: 7 | D91: 28 | E91: 96
... A102: 37 | B102: Reciclamiento de desperdicios y desechos | C102: 5 | D102: 27 | E102: 108
A103: Total Industria – Promedio simple | C103: 5 | D103: 24 | E103: 96
A104: Fuente: Observatorio de Empleo y Dinámica Empresarial - DGIyEL - SSPEyEL - en base a SIPA
A106: TOPES MÁXIMOS PARA CADA CATEGORÍA: COMERCIO
A107: Rama de actividad | C107: Micro | D107: Pequeña | E107: Mediana
A108: 50 | B108: Venta mantenimiento y reparación de vehículos,motocicletas y de sus partes, piezas y accesorios. Venta al por menor de combustible | C108: 4 | D108: 26 | E108: 60
A109: 51 | B109: Comercio al por mayor | C109: 4 | D109: 17 | E109: 40
A110: 52 | B110: Comercio al por menor y reparación de efectos personales y enseres domésticos | C110: 5 | D110: 26 | E110: 100
A111: Total Comercio – Promedio simple | C111: 5 | D111: 23 | E111: 67
A112: Fuente: Observatorio de Empleo y Dinámica Empresarial - DGIyEL - SSPEyEL - en base a SIPA
A114: [1] El Observatorio de Empleo y Dinámica Empresarial, en Argentina, fue creado por la Resolución Nº 135 de mayo de 2003, de la Secretaría de Empleo – MTEySS.
A116: [2] En algunos casos corresponde a un grupo de plantas o de unidades de negocio, bajo un mismo control. Puede ser, según los casos, una persona física o una persona jurídica, constituida con el objeto de ejercer en uno o varios lugares actividades de producción.
A118: [3]En el enfoque tradicional de estática comparada, se calcula solamente el crecimiento promedio como la diferencia del empleo total registrado en dos momentos; no se identifican comportamientos diferentes de la media (empresas que expanden y contraen sus dotaciones); no siempre se identifican los cambios en la composición de las empresas (entrada y salida de firmas). Estos problemas se resuelven en el análisis de series longitudinales
A120: [4] La situación más clara corresponde a las Personas físicas que conservan un mismo CUIT a lo largo de su vida activa y que efectivamente pueden discontinuar su actividad de empleador por períodos prolongados. También sucede en los casos de actividades estacionales.
A122: [5] El criterio se corresponde con el aplicado por el Bureau of Labor Statistics de los Estados Unidos.
A124: [6]Este criterio coincide con los estudios de dinámica del empleo y difiere del que habitualmente se utiliza en demografía de empresas, particularmente en los estudios de OECD, que consideran el momento del cierre con el último período de empleo positivo.
A126: [7] Las estadísticas tradicionales de Argentina no siempre pueden agrupar el empleo de todos los “locales” de las empresas, por ello solamente suelen clasificar por estratos a los locales. Esta forma de clasificación de las estadísticas tradicionales lleva a subestimar la importancia del empleo en las grandes empresas (generalmente multiplanta), lo que queda contemplado clasificando a las empresas a partir de su empleo total y no a cada local por separado.

Sheet Partidos de GBA
D1: Volver al índice
A2: PARTIDOS DE GBA
A3: Empresas del sector privado por rama de actividad - Activas en cada año
B4: Ramas de actividad | C4: 1996 | D4: 1997 | E4: 1998 | F4: 1999 | G4: 2000 | H4: 2001 | I4: 2002 | J4: 2003 | K4: 2004 | L4: 2005 | M4: 2006 | N4: 2007 | O4: 2008 | P4: 2009 | Q4: 2010 | R4: 2011 | S4: 2012 | T4: 2013 | U4: 2014 | V4: 2015 | W4: 2016 | X4: 2017 | Y4: 2018 | Z4: 2019 | AA4: 2020 | AB4: 2021 | AC4: 2022 | AD4: 2023 | AE4: 2024
D5: 2º Trim 1996 | F5: 3º Trim 1996 | H5: 4º Trim 1996 | J5: 1º Trim 1997 | L5: 2º Trim 1997 | N5: 3º Trim 1997 | P5: 4º Trim 1997 | R5: 1º Trim 1998
A6: A | B6: AGRICULTURA, GANADERIA, CAZA Y SILVICULTURA | C6: 1271 | D6: 1270 | E6: 1264 | F6: 1328 | G6: 1006 | H6: 1009 | I6: 993 | J6: 1108 | K6: 1261 | L6: 1344 | M6: 1436 | N6: 1538 | O6: 1511 | P6: 1487 | Q6: 1468 | R6: 1478 | S6: 1434 | T6: 1381 | U6: 1355 | V6: 1377 | W6: 1394 | X6: 1412 | Y6: 1432 | Z6: 1447 | AA6: 1470 | AB6: 1546 | AC6: 2156 | AD6: 2318 | AE6: 2285
A7: 1 | B7: Agricultura y ganaderia | C7: 1238 | D7: 1232 | E7: 1230 | F7: 1290 | G7: 971 | H7: 976 | I7: 963 | J7: 1076 | K7: 1226 | L7: 1305 | M7: 1399 | N7: 1496 | O7: 1470 | P7: 1440 | Q7: 1421 | R7: 1434 | S7: 1391 | T7: 1335 | U7: 1310 | V7: 1332 | W7: 1351 | X7: 1370 | Y7: 1389 | Z7: 1408 | AA7: 1431 | AB7: 1502 | AC7: 2106 | AD7: 2256 | AE7: 2227
A8: 2 | B8: Silvicultura, extracción de madera | C8: 33 | D8: 38 | E8: 34 | F8: 38 | G8: 35 | H8: 33 | I8: 30 | J8: 32 | K8: 35 | L8: 39 | M8: 37 | N8: 42 | O8: 41 | P8: 47 | Q8: 47 | R8: 44 | S8: 43 | T8: 46 | U8: 45 | V8: 45 | W8: 43 | X8: 42 | Y8: 43 | Z8: 39 | AA8: 39 | AB8: 44 | AC8: 50 | AD8: 62 | AE8: 58
A9: B | B9: PESCA Y SERVICIOS CONEXOS | C9: 4 | D9: 6 | E9: 8 | F9: 11 | G9: s.d. | H9: s.d. | I9: 5 | J9: s.d. | K9: 7 | L9: 9 | M9: 11 | N9: 11 | O9: 9 | P9: 9 | Q9: 7 | R9: 8 | S9: 9 | T9: 14 | U9: 10 | V9: 11 | W9: 11 | X9: 9 | Y9: 10 | Z9: 13 | AA9: 12 | AB9: 15 | AC9: 8 | AD9: 18 | AE9: 21
A10: 5 | B10: Pesca y actividades relacionadas con la pesca | C10: 4 | D10: 6 | E10: 8 | F10: 11 | G10: s.d. | H10: s.d. | I10: 5 | J10: s.d. | K10: 7 | L10: 9 | M10: 11 | N10: 11 | O10: 9 | P10: 9 | Q10: 7 | R10: 8 | S10: 9 | T10: 14 | U10: 10 | V10: 11 | W10: 11 | X10: 9 | Y10: 10 | Z10: 13 | AA10: 12 | AB10: 15 | AC10: 8 | AD10: 18 | AE10: 21
A11: C | B11: EXPLOTACION DE MINAS Y CANTERAS | C11: 52 | D11: 53 | E11: 56 | F11: 58 | G11: 56 | H11: 53 | I11: 46 | J11: 51 | K11: 54 | L11: 58 | M11: 64 | N11: 74 | O11: 70 | P11: 71 | Q11: 72 | R11: 66 | S11: 63 | T11: 74 | U11: 71 | V11: 69 | W11: 65 | X11: 61 | Y11: 65 | Z11: 67 | AA11: 70 | AB11: 72 | AC11: 92 | AD11: 94 | AE11: 92
A12: 11 | B12: Extraccion de petroleo crudo y gas natural | C12: 19 | D12: 17 | E12: 18 | F12: 18 | G12: 19 | H12: 16 | I12: 14 | J12: 18 | K12: s.d. | L12: s.d. | M12: s.d. | N12: 21 | O12: 23 | P12: s.d. | Q12: s.d. | R12: s.d. | S12: s.d. | T12: s.d. | U12: s.d. | V12: s.d. | W12: s.d. | X12: s.d. | Y12: 23 | Z12: 26 | AA12: 28 | AB12: 28 | AC12: 33 | AD12: 33 | AE12: 36
A13: 13 | B13: Extraccion de minerales metaliferos | C13: 4 | D13: 4 | E13: s.d. | F13: s.d. | G13: s.d. | H13: s.d. | I13: s.d. | J13: s.d. | K13: s.d. | L13: s.d. | M13: s.d. | N13: 4 | O13: s.d. | P13: s.d. | Q13: s.d. | R13: s.d. | S13: s.d. | T13: s.d. | U13: s.d. | V13: s.d. | W13: s.d. | X13: s.d. | Y13: s.d. | Z13: s.d. | AA13: s.d. | AB13: s.d. | AC13: 4 | AD13: 4 | AE13: s.d.
A14: 14 | B14: Explotacion de otras minas y canteras | C14: 29 | D14: 32 | E14: s.d. | F14: s.d. | G14: s.d. | H14: s.d. | I14: s.d. | J14: s.d. | K14: 37 | L14: 39 | M14: 42 | N14: 49 | O14: s.d. | P14: 44 | Q14: 48 | R14: 44 | S14: 40 | T14: 44 | U14: 44 | V14: 43 | W14: 41 | X14: 37 | Y14: s.d. | Z14: s.d. | AA14: s.d. | AB14: s.d. | AC14: 55 | AD14: 57 | AE14: s.d.
A15: D | B15: INDUSTRIA MANUFACTURERA | C15: 15570 | D15: 15445 | E15: 15019 | F15: 15544 | G15: 14185 | H15: 13219 | I15: 12399 | J15: 13334 | K15: 14894 | L15: 15955 | M15: 16910 | N15: 17669 | O15: 17992 | P15: 17919 | Q15: 18014 | R15: 18186 | S15: 18233 | T15: 18198 | U15: 18113 | V15: 18239 | W15: 18061 | X15: 17791 | Y15: 17219 | Z15: 16632 | AA15: 16313 | AB15: 16483 | AC15: 17402 | AD15: 17490 | AE15: 17226
A16: 15 | B16: Alimentos | C16: 2270 | D16: 2220 | E16: 2077 | F16: 2104 | G16: 1873 | H16: 1787 | I16: 1692 | J16: 1797 | K16: 2065 | L16: 2127 | M16: 2230 | N16: 2301 | O16: 2372 | P16: 2403 | Q16: 2406 | R16: 2453 | S16: 2489 | T16: 2514 | U16: 2522 | V16: 2534 | W16: 2539 | X16: 2561 | Y16: 2536 | Z16: 2517 | AA16: 2468 | AB16: 2536 | AC16: 2817 | AD16: 2915 | AE16: 2922
A17: 16 | B17: Tabaco | C17: s.d. | D17: s.d. | E17: s.d. | F17: s.d. | G17: s.d. | H17: s.d. | I17: 6 | J17: 6 | K17: 7 | L17: 6 | M17: 5 | N17: 5 | O17: 4 | P17: 5 | Q17: 5 | R17: 5 | S17: 5 | T17: 4 | U17: 4 | V17: 4 | W17: 4 | X17: 5 | Y17: 5 | Z17: 6 | AA17: 6 | AB17: 7 | AC17: 7 | AD17: 7 | AE17: 7
A18: 17 | B18: Productos textiles | C18: 954 | D18: 948 | E18: 929 | F18: 953 | G18: 818 | H18: 795 | I18: 724 | J18: 791 | K18: 876 | L18: 947 | M18: 1008 | N18: 1080 | O18: 1078 | P18: 1060 | Q18: 1079 | R18: 1088 | S18: 1102 | T18: 1110 | U18: 1111 | V18: 1111 | W18: 1118 | X18: 1096 | Y18: 1045 | Z18: 1004 | AA18: 991 | AB18: 1002 | AC18: 1071 | AD18: 1075 | AE18: 1072
A19: 18 | B19: Confecciones | C19: 642 | D19: 600 | E19: 615 | F19: 608 | G19: 536 | H19: 457 | I19: 395 | J19: 443 | K19: 547 | L19: 609 | M19: 710 | N19: 759 | O19: 782 | P19: 775 | Q19: 785 | R19: 806 | S19: 780 | T19: 778 | U19: 803 | V19: 816 | W19: 795 | X19: 759 | Y19: 716 | Z19: 649 | AA19: 602 | AB19: 581 | AC19: 709 | AD19: 723 | AE19: 728
A20: 19 | B20: Calzado y cuero | C20: 703 | D20: 671 | E20: 616 | F20: 626 | G20: 567 | H20: 504 | I20: 472 | J20: 552 | K20: 654 | L20: 717 | M20: 779 | N20: 840 | O20: 852 | P20: 858 | Q20: 884 | R20: 919 | S20: 942 | T20: 955 | U20: 940 | V20: 960 | W20: 949 | X20: 909 | Y20: 835 | Z20: 732 | AA20: 700 | AB20: 678 | AC20: 697 | AD20: 690 | AE20: 649
A21: 20 | B21: Madera | C21: 641 | D21: 625 | E21: 596 | F21: 613 | G21: 568 | H21: 506 | I21: 448 | J21: 474 | K21: 545 | L21: 588 | M21: 630 | N21: 654 | O21: 666 | P21: 642 | Q21: 628 | R21: 625 | S21: 612 | T21: 596 | U21: 590 | V21: 567 | W21: 536 | X21: 512 | Y21: 494 | Z21: 471 | AA21: 463 | AB21: 477 | AC21: 492 | AD21: 505 | AE21: 482
A22: 21 | B22: Papel | C22: 340 | D22: 346 | E22: 338 | F22: 359 | G22: 328 | H22: 306 | I22: 305 | J22: 338 | K22: 363 | L22: 383 | M22: 406 | N22: 416 | O22: 431 | P22: 434 | Q22: 437 | R22: 439 | S22: 440 | T22: 439 | U22: 435 | V22: 445 | W22: 453 | X22: 443 | Y22: 431 | Z22: 416 | AA22: 405 | AB22: 414 | AC22: 428 | AD22: 430 | AE22: 419
A23: 22 | B23: Edición e impresión | C23: 633 | D23: 645 | E23: 688 | F23: 724 | G23: 670 | H23: 637 | I23: 597 | J23: 622 | K23: 694 | L23: 767 | M23: 822 | N23: 862 | O23: 883 | P23: 906 | Q23: 905 | R23: 886 | S23: 860 | T23: 862 | U23: 852 | V23: 842 | W23: 838 | X23: 798 | Y23: 756 | Z23: 732 | AA23: 695 | AB23: 681 | AC23: 721 | AD23: 719 | AE23: 686
A24: 23 | B24: Productos de petróleo | C24: 48 | D24: 43 | E24: 41 | F24: 43 | G24: 36 | H24: 34 | I24: 28 | J24: 31 | K24: 33 | L24: 34 | M24: 31 | N24: 31 | O24: 30 | P24: 30 | Q24: 31 | R24: 32 | S24: 32 | T24: 33 | U24: 34 | V24: 35 | W24: 34 | X24: 31 | Y24: 31 | Z24: 30 | AA24: 29 | AB24: 30 | AC24: 31 | AD24: 32 | AE24: 32
A25: 24 | B25: Productos químicos | C25: 912 | D25: 919 | E25: 912 | F25: 987 | G25: 913 | H25: 898 | I25: 886 | J25: 942 | K25: 1001 | L25: 1044 | M25: 1060 | N25: 1049 | O25: 1046 | P25: 1045 | Q25: 1046 | R25: 1042 | S25: 1050 | T25: 1049 | U25: 1054 | V25: 1067 | W25: 1045 | X25: 1054 | Y25: 1041 | Z25: 1052 | AA25: 1058 | AB25: 1073 | AC25: 1138 | AD25: 1150 | AE25: 1134
A26: 25 | B26: Productos de caucho y plástico | C26: 1312 | D26: 1307 | E26: 1303 | F26: 1401 | G26: 1337 | H26: 1254 | I26: 1195 | J26: 1270 | K26: 1348 | L26: 1433 | M26: 1494 | N26: 1525 | O26: 1552 | P26: 1558 | Q26: 1543 | R26: 1568 | S26: 1575 | T26: 1581 | U26: 1577 | V26: 1622 | W26: 1618 | X26: 1602 | Y26: 1560 | Z26: 1532 | AA26: 1532 | AB26: 1559 | AC26: 1585 | AD26: 1580 | AE26: 1555
A27: 26 | B27: Otros minerales no metálicos | C27: 491 | D27: 460 | E27: 437 | F27: 456 | G27: 422 | H27: 378 | I27: 357 | J27: 367 | K27: 399 | L27: 416 | M27: 431 | N27: 466 | O27: 460 | P27: 454 | Q27: 454 | R27: 460 | S27: 461 | T27: 459 | U27: 447 | V27: 454 | W27: 450 | X27: 441 | Y27: 439 | Z27: 427 | AA27: 424 | AB27: 438 | AC27: 466 | AD27: 468 | AE27: 461
A28: 27 | B28: Metales comunes | C28: 475 | D28: 477 | E28: 438 | F28: 459 | G28: 434 | H28: 397 | I28: 379 | J28: 399 | K28: 447 | L28: 483 | M28: 496 | N28: 513 | O28: 524 | P28: 510 | Q28: 513 | R28: 528 | S28: 523 | T28: 511 | U28: 511 | V28: 503 | W28: 483 | X28: 468 | Y28: 448 | Z28: 442 | AA28: 442 | AB28: 454 | AC28: 452 | AD28: 439 | AE28: 431
A29: 28 | B29: Otros productos de metal | C29: 2628 | D29: 2651 | E29: 2589 | F29: 2705 | G29: 2464 | H29: 2299 | I29: 2148 | J29: 2319 | K29: 2599 | L29: 2804 | M29: 2995 | N29: 3154 | O29: 3228 | P29: 3203 | Q29: 3206 | R29: 3229 | S29: 3251 | T29: 3262 | U29: 3220 | V29: 3252 | W29: 3223 | X29: 3188 | Y29: 3088 | Z29: 2961 | AA29: 2896 | AB29: 2903 | AC29: 2991 | AD29: 2966 | AE29: 2898
A30: 29 | B30: Maquinaria y equipo | C30: 932 | D30: 952 | E30: 951 | F30: 998 | G30: 933 | H30: 856 | I30: 799 | J30: 881 | K30: 965 | L30: 1056 | M30: 1097 | N30: 1146 | O30: 1149 | P30: 1127 | Q30: 1137 | R30: 1136 | S30: 1147 | T30: 1125 | U30: 1113 | V30: 1115 | W30: 1081 | X30: 1061 | Y30: 1042 | Z30: 1028 | AA30: 1014 | AB30: 1003 | AC30: 1022 | AD30: 1017 | AE30: 1017
A31: 30 | B31: Maquinaria de oficina | C31: s.d. | D31: s.d. | E31: s.d. | F31: s.d. | G31: s.d. | H31: s.d. | I31: 11 | J31: 12 | K31: 14 | L31: 15 | M31: 20 | N31: 21 | O31: 20 | P31: 20 | Q31: 19 | R31: 20 | S31: 18 | T31: 19 | U31: 20 | V31: 25 | W31: 23 | X31: 20 | Y31: 21 | Z31: 16 | AA31: 18 | AB31: 23 | AC31: 30 | AD31: 32 | AE31: 29
A32: 31 | B32: Aparatos eléctricos | C32: 397 | D32: 401 | E32: 372 | F32: 389 | G32: 351 | H32: 324 | I32: 301 | J32: 324 | K32: 359 | L32: 379 | M32: 398 | N32: 419 | O32: 427 | P32: 441 | Q32: 453 | R32: 468 | S32: 480 | T32: 466 | U32: 473 | V32: 493 | W32: 484 | X32: 479 | Y32: 470 | Z32: 463 | AA32: 456 | AB32: 469 | AC32: 494 | AD32: 500 | AE32: 492
A33: 32 | B33: Radio y televisión | C33: 54 | D33: 53 | E33: 48 | F33: 48 | G33: 42 | H33: 37 | I33: 34 | J33: 36 | K33: 40 | L33: 42 | M33: 42 | N33: 46 | O33: 47 | P33: 48 | Q33: 49 | R33: 52 | S33: 58 | T33: 56 | U33: 58 | V33: 55 | W33: 54 | X33: 56 | Y33: 56 | Z33: 51 | AA33: 53 | AB33: 52 | AC33: 50 | AD33: 51 | AE33: 50
A34: 33 | B34: Instrumentos médicos | C34: 118 | D34: 125 | E34: 125 | F34: 137 | G34: 120 | H34: 115 | I34: 116 | J34: 134 | K34: 146 | L34: 152 | M34: 158 | N34: 165 | O34: 182 | P34: 180 | Q34: 191 | R34: 188 | S34: 182 | T34: 191 | U34: 184 | V34: 184 | W34: 187 | X34: 189 | Y34: 182 | Z34: 183 | AA34: 183 | AB34: 190 | AC34: 206 | AD34: 206 | AE34: 209
A35: 34 | B35: Automotores | C35: 574 | D35: 585 | E35: 556 | F35: 566 | G35: 534 | H35: 518 | I35: 497 | J35: 526 | K35: 575 | L35: 614 | M35: 634 | N35: 655 | O35: 655 | P35: 636 | Q35: 640 | R35: 638 | S35: 631 | T35: 610 | U35: 601 | V35: 600 | W35: 592 | X35: 583 | Y35: 554 | Z35: 518 | AA35: 514 | AB35: 524 | AC35: 522 | AD35: 514 | AE35: 507
A36: 35 | B36: Otros equipo de transporte | C36: 162 | D36: 156 | E36: 156 | F36: 151 | G36: 149 | H36: 131 | I36: 124 | J36: 131 | K36: 163 | L36: 177 | M36: 202 | N36: 224 | O36: 234 | P36: 228 | Q36: 229 | R36: 227 | S36: 221 | T36: 209 | U36: 194 | V36: 192 | W36: 195 | X36: 178 | Y36: 174 | Z36: 170 | AA36: 164 | AB36: 168 | AC36: 179 | AD36: 176 | AE36: 164
A37: 36 | B37: Muebles | C37: 1240 | D37: 1215 | E37: 1191 | F37: 1173 | G37: 1047 | H37: 943 | I37: 851 | J37: 900 | K37: 1015 | L37: 1115 | M37: 1207 | N37: 1263 | O37: 1286 | P37: 1278 | Q37: 1296 | R37: 1302 | S37: 1292 | T37: 1287 | U37: 1290 | V37: 1279 | W37: 1281 | X37: 1285 | Y37: 1223 | Z37: 1161 | AA37: 1129 | AB37: 1145 | AC37: 1208 | AD37: 1210 | AE37: 1200
A38: 37 | B38: Reciclamiento de desperdicios y desechos | C38: 26 | D38: 29 | E38: 27 | F38: 29 | G38: 31 | H38: 30 | I38: 34 | J38: 39 | K38: 39 | L38: 47 | M38: 55 | N38: 75 | O38: 84 | P38: 78 | Q38: 78 | R38: 75 | S38: 82 | T38: 82 | U38: 80 | V38: 84 | W38: 79 | X38: 73 | Y38: 72 | Z38: 71 | AA38: 71 | AB38: 76 | AC38: 86 | AD38: 85 | AE38: 82
A39: E | B39: ELECTRICIDAD, GAS Y AGUA | C39: 33 | D39: 27 | E39: 27 | F39: 34 | G39: 35 | H39: 34 | I39: 31 | J39: 30 | K39: 31 | L39: 34 | M39: 34 | N39: 35 | O39: 33 | P39: 33 | Q39: 35 | R39: 35 | S39: 40 | T39: 39 | U39: 36 | V39: 40 | W39: 38 | X39: 43 | Y39: 49 | Z39: 44 | AA39: 41 | AB39: 48 | AC39: 66 | AD39: 54 | AE39: 64
A40: 40 | B40: Electricidad, gas y agua | C40: 21 | D40: 14 | E40: 16 | F40: 21 | G40: 22 | H40: 20 | I40: 18 | J40: 18 | K40: 18 | L40: 20 | M40: 18 | N40: 20 | O40: 19 | P40: 20 | Q40: 23 | R40: 23 | S40: 28 | T40: 27 | U40: 24 | V40: 27 | W40: 25 | X40: 31 | Y40: 36 | Z40: 31 | AA40: 28 | AB40: 34 | AC40: 45 | AD40: 35 | AE40: 46
A41: 41 | B41: Captación, depuración y distribución de agua | C41: 12 | D41: 13 | E41: 11 | F41: 13 | G41: 13 | H41: 14 | I41: 13 | J41: 12 | K41: 13 | L41: 14 | M41: 16 | N41: 15 | O41: 14 | P41: 13 | Q41: 12 | R41: 12 | S41: 12 | T41: 12 | U41: 12 | V41: 13 | W41: 13 | X41: 12 | Y41: 13 | Z41: 13 | AA41: 13 | AB41: 14 | AC41: 21 | AD41: 19 | AE41: 18
A42: F | B42: CONSTRUCCION | C42: 2916 | D42: 3073 | E42: 3261 | F42: 3359 | G42: 3039 | H42: 2539 | I42: 2079 | J42: 2487 | K42: 3079 | L42: 3622 | M42: 4213 | N42: 4732 | O42: 4992 | P42: 4898 | Q42: 5018 | R42: 5261 | S42: 5243 | T42: 5300 | U42: 5218 | V42: 5279 | W42: 5192 | X42: 5197 | Y42: 5173 | Z42: 5206 | AA42: 4795 | AB42: 4910 | AC42: 5404 | AD42: 5316 | AE42: 4958
A43: 45 | B43: Construccion | C43: 2916 | D43: 3073 | E43: 3261 | F43: 3359 | G43: 3039 | H43: 2539 | I43: 2079 | J43: 2487 | K43: 3079 | L43: 3622 | M43: 4213 | N43: 4732 | O43: 4992 | P43: 4898 | Q43: 5018 | R43: 5261 | S43: 5243 | T43: 5300 | U43: 5218 | V43: 5279 | W43: 5192 | X43: 5197 | Y43: 5173 | Z43: 5206 | AA43: 4795 | AB43: 4910 | AC43: 5404 | AD43: 5316 | AE43: 4958
A44: G | B44: COMERCIO AL POR MAYOR Y AL POR MENOR | C44: 16547 | D44: 16463 | E44: 16158 | F44: 16367 | G44: 15421 | H44: 14717 | I44: 13715 | J44: 14873 | K44: 18619 | L44: 20620 | M44: 23178 | N44: 24668 | O44: 26188 | P44: 27170 | Q44: 28105 | R44: 28671 | S44: 28970 | T44: 29507 | U44: 29590 | V44: 30139 | W44: 30545 | X44: 31170 | Y44: 30682 | Z44: 30127 | AA44: 28832 | AB44: 29068 | AC44: 32908 | AD44: 33852 | AE44: 34017
A45: 50 | B45: Vta y reparación de vehículos. vta por menor de combustible | C45: 2819 | D45: 2843 | E45: 2777 | F45: 2771 | G45: 2547 | H45: 2433 | I45: 2267 | J45: 2443 | K45: 2946 | L45: 3164 | M45: 3430 | N45: 3607 | O45: 3754 | P45: 3824 | Q45: 3884 | R45: 3887 | S45: 3886 | T45: 3911 | U45: 3888 | V45: 3923 | W45: 3908 | X45: 3928 | Y45: 3885 | Z45: 3844 | AA45: 3724 | AB45: 3774 | AC45: 4090 | AD45: 4140 | AE45: 4149
A46: 51 | B46: Comercio al por mayor | C46: 4063 | D46: 4065 | E46: 3964 | F46: 4264 | G46: 3882 | H46: 3684 | I46: 3458 | J46: 3680 | K46: 4143 | L46: 4520 | M46: 4951 | N46: 5158 | O46: 5421 | P46: 5572 | Q46: 5711 | R46: 5835 | S46: 5952 | T46: 6126 | U46: 6147 | V46: 6250 | W46: 6279 | X46: 6362 | Y46: 6335 | Z46: 6338 | AA46: 6355 | AB46: 6571 | AC46: 7264 | AD46: 7480 | AE46: 7510
A47: 52 | B47: Comercio al por menor | C47: 9665 | D47: 9555 | E47: 9417 | F47: 9332 | G47: 8992 | H47: 8600 | I47: 7990 | J47: 8750 | K47: 11530 | L47: 12936 | M47: 14797 | N47: 15903 | O47: 17013 | P47: 17774 | Q47: 18510 | R47: 18949 | S47: 19132 | T47: 19470 | U47: 19555 | V47: 19966 | W47: 20358 | X47: 20880 | Y47: 20462 | Z47: 19945 | AA47: 18753 | AB47: 18723 | AC47: 21554 | AD47: 22232 | AE47: 22358
A48: H | B48: HOTELERIA Y RESTAURANTES | C48: 1754 | D48: 1734 | E48: 1783 | F48: 1653 | G48: 1371 | H48: 1280 | I48: 1178 | J48: 1311 | K48: 1789 | L48: 2039 | M48: 2337 | N48: 2580 | O48: 2822 | P48: 3005 | Q48: 3073 | R48: 3201 | S48: 3298 | T48: 3397 | U48: 3431 | V48: 3602 | W48: 3732 | X48: 3968 | Y48: 4033 | Z48: 3961 | AA48: 3501 | AB48: 3623 | AC48: 4599 | AD48: 4873 | AE48: 4877
A49: 55 | B49: Servicios de hoteleria y restaurantes | C49: 1754 | D49: 1734 | E49: 1783 | F49: 1653 | G49: 1371 | H49: 1280 | I49: 1178 | J49: 1311 | K49: 1789 | L49: 2039 | M49: 2337 | N49: 2580 | O49: 2822 | P49: 3005 | Q49: 3073 | R49: 3201 | S49: 3298 | T49: 3397 | U49: 3431 | V49: 3602 | W49: 3732 | X49: 3968 | Y49: 4033 | Z49: 3961 | AA49: 3501 | AB49: 3623 | AC49: 4599 | AD49: 4873 | AE49: 4877
A50: I | B50: SERVICIOS DE TRANSPORTE, DE ALMACENAMIENTO Y DE COMUNICACIONES | C50: 3264 | D50: 3145 | E50: 3313 | F50: 3599 | G50: 3264 | H50: 3048 | I50: 2817 | J50: 3057 | K50: 3848 | L50: 4349 | M50: 4998 | N50: 5436 | O50: 5795 | P50: 5826 | Q50: 6049 | R50: 6284 | S50: 6356 | T50: 6437 | U50: 6376 | V50: 6446 | W50: 6412 | X50: 6394 | Y50: 6213 | Z50: 5872 | AA50: 5575 | AB50: 5522 | AC50: 6116 | AD50: 6129 | AE50: 6061
A51: 60 | B51: Transporte ferroviario y automotor y por tuberias | C51: 2472 | D51: 2302 | E51: 2387 | F51: 2637 | G51: 2436 | H51: 2225 | I51: 2071 | J51: 2245 | K51: 2804 | L51: 3252 | M51: 3821 | N51: 4199 | O51: 4504 | P51: 4510 | Q51: 4689 | R51: 4871 | S51: 4920 | T51: 4979 | U51: 4888 | V51: 4897 | W51: 4829 | X51: 4779 | Y51: 4635 | Z51: 4300 | AA51: 4059 | AB51: 4023 | AC51: 4332 | AD51: 4324 | AE51: 4243
A52: 61 | B52: Transporte marítimo y fluvial | C52: 30 | D52: 31 | E52: 31 | F52: 31 | G52: 31 | H52: 28 | I52: 27 | J52: 29 | K52: 40 | L52: 46 | M52: 46 | N52: 44 | O52: 50 | P52: 58 | Q52: 62 | R52: 67 | S52: 66 | T52: 62 | U52: 60 | V52: 61 | W52: 60 | X52: 61 | Y52: 59 | Z52: 59 | AA52: 58 | AB52: 53 | AC52: 56 | AD52: 62 | AE52: 55
A53: 62 | B53: Transporte aéreo de cargas y de pasajeros | C53: 16 | D53: 20 | E53: 22 | F53: 23 | G53: 18 | H53: 18 | I53: 18 | J53: 21 | K53: 24 | L53: 22 | M53: 23 | N53: 28 | O53: 29 | P53: 28 | Q53: 28 | R53: 33 | S53: 34 | T53: 34 | U53: 35 | V53: 34 | W53: 37 | X53: 39 | Y53: 46 | Z53: 45 | AA53: 47 | AB53: 44 | AC53: 47 | AD53: 46 | AE53: 42
A54: 63 | B54: Manipulación de carga, almacenamiento y depósito | C54: 546 | D54: 581 | E54: 653 | F54: 638 | G54: 534 | H54: 518 | I54: 473 | J54: 508 | K54: 684 | L54: 742 | M54: 813 | N54: 880 | O54: 932 | P54: 960 | Q54: 992 | R54: 1032 | S54: 1051 | T54: 1084 | U54: 1108 | V54: 1167 | W54: 1201 | X54: 1240 | Y54: 1209 | Z54: 1205 | AA54: 1165 | AB54: 1154 | AC54: 1393 | AD54: 1415 | AE54: 1431
A55: 64 | B55: Telecomunicaciones y correos | C55: 200 | D55: 211 | E55: 220 | F55: 270 | G55: 245 | H55: 259 | I55: 228 | J55: 254 | K55: 296 | L55: 287 | M55: 295 | N55: 285 | O55: 280 | P55: 270 | Q55: 278 | R55: 281 | S55: 285 | T55: 278 | U55: 285 | V55: 287 | W55: 285 | X55: 275 | Y55: 264 | Z55: 263 | AA55: 246 | AB55: 248 | AC55: 288 | AD55: 282 | AE55: 290
A56: J | B56: INTERMEDIACION FINANCIERA Y OTROS SERVICIOS FINANCIEROS | C56: 521 | D56: 549 | E56: 567 | F56: 574 | G56: 499 | H56: 490 | I56: 452 | J56: 466 | K56: 573 | L56: 623 | M56: 683 | N56: 730 | O56: 770 | P56: 788 | Q56: 821 | R56: 850 | S56: 865 | T56: 877 | U56: 877 | V56: 918 | W56: 947 | X56: 954 | Y56: 954 | Z56: 932 | AA56: 907 | AB56: 898 | AC56: 954 | AD56: 974 | AE56: 947
A57: 65 | B57: Intermediacion financiera y otros servicios financieros | C57: 189 | D57: 194 | E57: 213 | F57: 231 | G57: 195 | H57: 199 | I57: 179 | J57: 175 | K57: 183 | L57: 190 | M57: 203 | N57: 206 | O57: 211 | P57: 219 | Q57: 220 | R57: 229 | S57: 223 | T57: 223 | U57: 219 | V57: 206 | W57: 203 | X57: 211 | Y57: 204 | Z57: 201 | AA57: 196 | AB57: 198 | AC57: 193 | AD57: 195 | AE57: 183
A58: 66 | B58: Seguros | C58: 89 | D58: 93 | E58: 97 | F58: 94 | G58: 82 | H58: 76 | I58: 70 | J58: 78 | K58: 83 | L58: 91 | M58: 98 | N58: 104 | O58: 102 | P58: 94 | Q58: 101 | R58: 96 | S58: 99 | T58: 93 | U58: 94 | V58: 98 | W58: 97 | X58: 99 | Y58: 96 | Z58: 96 | AA58: 92 | AB58: 94 | AC58: 96 | AD58: 98 | AE58: 95
A59: 67 | B59: Servicios auxiliares a la actividad financiera | C59: 243 | D59: 262 | E59: 257 | F59: 249 | G59: 222 | H59: 215 | I59: 203 | J59: 213 | K59: 307 | L59: 342 | M59: 382 | N59: 420 | O59: 457 | P59: 475 | Q59: 500 | R59: 525 | S59: 543 | T59: 561 | U59: 564 | V59: 614 | W59: 647 | X59: 644 | Y59: 654 | Z59: 635 | AA59: 619 | AB59: 606 | AC59: 665 | AD59: 681 | AE59: 669
A60: K | B60: SERVICIOS INMOBILIARIOS, EMPRESARIALES Y DE ALQUILER | C60: 11153 | D60: 11370 | E60: 11824 | F60: 12324 | G60: 11315 | H60: 10946 | I60: 10452 | J60: 11152 | K60: 12969 | L60: 13787 | M60: 14573 | N60: 15143 | O60: 15402 | P60: 15396 | Q60: 15482 | R60: 15535 | S60: 15285 | T60: 15165 | U60: 15060 | V60: 15034 | W60: 14973 | X60: 15030 | Y60: 14812 | Z60: 14451 | AA60: 13824 | AB60: 13547 | AC60: 14350 | AD60: 14243 | AE60: 14017
A61: 70 | B61: Servicios inmobiliarios | C61: 5617 | D61: 5628 | E61: 5815 | F61: 6033 | G61: 5658 | H61: 5497 | I61: 5378 | J61: 5577 | K61: 6306 | L61: 6568 | M61: 6773 | N61: 6901 | O61: 7038 | P61: 7144 | Q61: 7268 | R61: 7267 | S61: 7221 | T61: 7208 | U61: 7253 | V61: 7314 | W61: 7260 | X61: 7247 | Y61: 7264 | Z61: 7085 | AA61: 6854 | AB61: 6690 | AC61: 6736 | AD61: 6601 | AE61: 6591
A62: 71 | B62: Alquiler de equipo de transporte y de maquinaria | C62: 156 | D62: 151 | E62: 156 | F62: 154 | G62: 131 | H62: 125 | I62: 115 | J62: 134 | K62: 162 | L62: 185 | M62: 200 | N62: 225 | O62: 235 | P62: 236 | Q62: 242 | R62: 246 | S62: 233 | T62: 229 | U62: 228 | V62: 224 | W62: 232 | X62: 242 | Y62: 232 | Z62: 231 | AA62: 213 | AB62: 204 | AC62: 237 | AD62: 257 | AE62: 247
A63: 72 | B63: Actividades de informática | C63: 121 | D63: 155 | E63: 188 | F63: 207 | G63: 186 | H63: 177 | I63: 150 | J63: 187 | K63: 248 | L63: 288 | M63: 339 | N63: 395 | O63: 418 | P63: 409 | Q63: 421 | R63: 469 | S63: 468 | T63: 490 | U63: 514 | V63: 543 | W63: 575 | X63: 603 | Y63: 627 | Z63: 652 | AA63: 654 | AB63: 697 | AC63: 880 | AD63: 899 | AE63: 909
A64: 73 | B64: Investigación y desarrollo | C64: 6 | D64: 6 | E64: 9 | F64: 11 | G64: 14 | H64: 10 | I64: 11 | J64: 13 | K64: 18 | L64: 23 | M64: 29 | N64: 33 | O64: 32 | P64: 34 | Q64: 31 | R64: 32 | S64: 26 | T64: 30 | U64: 35 | V64: 35 | W64: 30 | X64: 33 | Y64: 28 | Z64: 26 | AA64: 26 | AB64: 32 | AC64: 47 | AD64: 55 | AE64: 54
A65: 74 | B65: Servicios jurídicos, contables y otros servicios a empresas | C65: 5214 | D65: 5385 | E65: 5610 | F65: 5869 | G65: 5276 | H65: 5091 | I65: 4750 | J65: 5193 | K65: 6189 | L65: 6680 | M65: 7187 | N65: 7538 | O65: 7628 | P65: 7517 | Q65: 7469 | R65: 7476 | S65: 7296 | T65: 7170 | U65: 6993 | V65: 6882 | W65: 6839 | X65: 6869 | Y65: 6628 | Z65: 6428 | AA65: 6049 | AB65: 5896 | AC65: 6423 | AD65: 6404 | AE65: 6189
A66: 75 | B66: Agencias de empleo eventual | C66: 39 | D66: 45 | E66: 46 | F66: 50 | G66: 50 | H66: 46 | I66: 48 | J66: 48 | K66: 46 | L66: 43 | M66: 45 | N66: 51 | O66: 51 | P66: 56 | Q66: 51 | R66: 45 | S66: 41 | T66: 38 | U66: 37 | V66: 36 | W66: 37 | X66: 36 | Y66: 33 | Z66: 29 | AA66: 28 | AB66: 28 | AC66: 27 | AD66: 27 | AE66: 27
A67: M | B67: ENSEÑANZA | C67: 1504 | D67: 1658 | E67: 1718 | F67: 1777 | G67: 1748 | H67: 1738 | I67: 1683 | J67: 1725 | K67: 1854 | L67: 1928 | M67: 2037 | N67: 2073 | O67: 2136 | P67: 2177 | Q67: 2183 | R67: 2209 | S67: 2191 | T67: 2171 | U67: 2174 | V67: 2177 | W67: 2172 | X67: 2191 | Y67: 2198 | Z67: 2185 | AA67: 2077 | AB67: 2012 | AC67: 2007 | AD67: 2061 | AE67: 1935
A68: 80 | B68: Enseñanza | C68: 1504 | D68: 1658 | E68: 1718 | F68: 1777 | G68: 1748 | H68: 1738 | I68: 1683 | J68: 1725 | K68: 1854 | L68: 1928 | M68: 2037 | N68: 2073 | O68: 2136 | P68: 2177 | Q68: 2183 | R68: 2209 | S68: 2191 | T68: 2171 | U68: 2174 | V68: 2177 | W68: 2172 | X68: 2191 | Y68: 2198 | Z68: 2185 | AA68: 2077 | AB68: 2012 | AC68: 2007 | AD68: 2061 | AE68: 1935
A69: N | B69: SERVICIOS SOCIALES Y DE SALUD | C69: 2473 | D69: 2481 | E69: 2512 | F69: 2639 | G69: 2438 | H69: 2424 | I69: 2310 | J69: 2403 | K69: 2718 | L69: 2877 | M69: 3041 | N69: 3195 | O69: 3327 | P69: 3446 | Q69: 3554 | R69: 3625 | S69: 3746 | T69: 3805 | U69: 3783 | V69: 3859 | W69: 3929 | X69: 3993 | Y69: 4046 | Z69: 4021 | AA69: 3814 | AB69: 3752 | AC69: 4106 | AD69: 4153 | AE69: 4024
A70: 85 | B70: Servicios sociales y de salud | C70: 2473 | D70: 2481 | E70: 2512 | F70: 2639 | G70: 2438 | H70: 2424 | I70: 2310 | J70: 2403 | K70: 2718 | L70: 2877 | M70: 3041 | N70: 3195 | O70: 3327 | P70: 3446 | Q70: 3554 | R70: 3625 | S70: 3746 | T70: 3805 | U70: 3783 | V70: 3859 | W70: 3929 | X70: 3993 | Y70: 4046 | Z70: 4021 | AA70: 3814 | AB70: 3752 | AC70: 4106 | AD70: 4153 | AE70: 4024
A71: O | B71: SERVICIOS COMUNITARIOS, SOCIALES Y PERSONALES N.C.P. | C71: 4970 | D71: 4961 | E71: 4932 | F71: 4908 | G71: 4587 | H71: 4386 | I71: 4091 | J71: 4382 | K71: 6209 | L71: 6819 | M71: 7296 | N71: 7355 | O71: 7244 | P71: 7309 | Q71: 7225 | R71: 7232 | S71: 7036 | T71: 6850 | U71: 6686 | V71: 6730 | W71: 6657 | X71: 6585 | Y71: 6305 | Z71: 6046 | AA71: 5458 | AB71: 5196 | AC71: 5698 | AD71: 5778 | AE71: 5476
A72: 90 | B72: Eliminación de desperdicios | C72: 128 | D72: 139 | E72: 134 | F72: 134 | G72: 113 | H72: 104 | I72: 92 | J72: 86 | K72: 115 | L72: 112 | M72: 130 | N72: 132 | O72: 124 | P72: 135 | Q72: 131 | R72: 135 | S72: 131 | T72: 138 | U72: 147 | V72: 149 | W72: 156 | X72: 153 | Y72: 155 | Z72: 155 | AA72: 155 | AB72: 157 | AC72: 175 | AD72: 178 | AE72: 175
A73: 91 | B73: Servicios de organizaciones empresariales | C73: 1160 | D73: 1211 | E73: 1234 | F73: 1348 | G73: 1294 | H73: 1293 | I73: 1296 | J73: 1358 | K73: 1420 | L73: 1456 | M73: 1484 | N73: 1513 | O73: 1508 | P73: 1530 | Q73: 1551 | R73: 1578 | S73: 1603 | T73: 1594 | U73: 1585 | V73: 1595 | W73: 1614 | X73: 1626 | Y73: 1613 | Z73: 1623 | AA73: 1586 | AB73: 1548 | AC73: 1710 | AD73: 1716 | AE73: 1699
A74: 92 | B74: Servicios culturales, deportivos y de esparcimiento | C74: 742 | D74: 765 | E74: 793 | F74: 817 | G74: 776 | H74: 767 | I74: 725 | J74: 782 | K74: 1003 | L74: 1203 | M74: 1332 | N74: 1437 | O74: 1557 | P74: 1675 | Q74: 1745 | R74: 1809 | S74: 1834 | T74: 1844 | U74: 1866 | V74: 1914 | W74: 1938 | X74: 1961 | Y74: 1938 | Z74: 1914 | AA74: 1747 | AB74: 1719 | AC74: 1920 | AD74: 1982 | AE74: 1883
A75: 93 | B75: Servicios n.c.p. | C75: 2940 | D75: 2846 | E75: 2771 | F75: 2609 | G75: 2404 | H75: 2222 | I75: 1978 | J75: 2156 | K75: 3671 | L75: 4048 | M75: 4350 | N75: 4273 | O75: 4055 | P75: 3969 | Q75: 3798 | R75: 3710 | S75: 3468 | T75: 3274 | U75: 3088 | V75: 3072 | W75: 2949 | X75: 2845 | Y75: 2599 | Z75: 2354 | AA75: 1970 | AB75: 1772 | AC75: 1893 | AD75: 1902 | AE75: 1719
B76: TOTAL | C76: 62032 | D76: 62235 | E76: 62442 | F76: 64175 | G76: 58964 | H76: 55883 | I76: 52251 | J76: 56379 | K76: 67905 | L76: 74064 | M76: 80811 | N76: 85239 | O76: 88291 | P76: 89534 | Q76: 91106 | R76: 92641 | S76: 92769 | T76: 93215 | U76: 92780 | V76: 93920 | W76: 94128 | X76: 94798 | Y76: 93191 | Z76: 91004 | AA76: 86689 | AB76: 86692 | AC76: 95866 | AD76: 97353 | AE76: 96000
A78: Notas:
A79: 1 - Las empresas se encuentran clasificadas por provincia según las zonas donde declaran que trabajan las personas.
A80: 2 - Las firmas con participación accionaria privada y estatal se incluye dentro del sector privado
A81: 3 - s/d : Dato no publicado para resguardar el secreto estadístico de las firmas
A82: Fuente: STEySS - Dirección Nacional de Estudios y Estadísticas Laborales - Observatorio de Empleo y Dinámica Empresarial, en base a SIPA.

Sheet Capital Federal
D1: Volver al índice
A2: CAPITAL FEDERAL
A3: Empresas del sector privado por rama de actividad - Activas en cada año
B4: Ramas de actividad | C4: 1996 | D4: 1997 | E4: 1998 | F4: 1999 | G4: 2000 | H4: 2001 | I4: 2002 | J4: 2003 | K4: 2004 | L4: 2005 | M4: 2006 | N4: 2007 | O4: 2008 | P4: 2009 | Q4: 2010 | R4: 2011 | S4: 2012 | T4: 2013 | U4: 2014 | V4: 2015 | W4: 2016 | X4: 2017 | Y4: 2018 | Z4: 2019 | AA4: 2020 | AB4: 2021 | AC4: 2022 | AD4: 2023 | AE4: 2024
D5: 2º Trim 1996 | F5: 3º Trim 1996 | H5: 4º Trim 1996 | J5: 1º Trim 1997 | L5: 2º Trim 1997 | N5: 3º Trim 1997 | P5: 4º Trim 1997 | R5: 1º Trim 1998
A6: A | B6: AGRICULTURA, GANADERIA, CAZA Y SILVICULTURA | C6: 2417 | D6: 2401 | E6: 2239 | F6: 2175 | G6: 1443 | H6: 1443 | I6: 1445 | J6: 1510 | K6: 1687 | L6: 1799 | M6: 1909 | N6: 1984 | O6: 1967 | P6: 1913 | Q6: 1931 | R6: 1959 | S6: 1969 | T6: 1956 | U6: 1933 | V6: 1950 | W6: 1934 | X6: 1937 | Y6: 1923 | Z6: 1900 | AA6: 1896 | AB6: 1958 | AC6: 2410 | AD6: 2501 | AE6: 2487
A7: 1 | B7: Agricultura y ganaderia | C7: 2373 | D7: 2363 | E7: 2197 | F7: 2130 | G7: 1411 | H7: 1410 | I7: 1409 | J7: 1473 | K7: 1649 | L7: 1759 | M7: 1868 | N7: 1941 | O7: 1928 | P7: 1868 | Q7: 1888 | R7: 1921 | S7: 1932 | T7: 1919 | U7: 1893 | V7: 1908 | W7: 1888 | X7: 1894 | Y7: 1883 | Z7: 1862 | AA7: 1860 | AB7: 1920 | AC7: 2360 | AD7: 2454 | AE7: 2447
A8: 2 | B8: Silvicultura, extracción de madera | C8: 44 | D8: 38 | E8: 42 | F8: 45 | G8: 32 | H8: 33 | I8: 36 | J8: 37 | K8: 38 | L8: 40 | M8: 41 | N8: 43 | O8: 39 | P8: 45 | Q8: 43 | R8: 38 | S8: 37 | T8: 37 | U8: 40 | V8: 42 | W8: 46 | X8: 43 | Y8: 40 | Z8: 38 | AA8: 36 | AB8: 38 | AC8: 50 | AD8: 47 | AE8: 40
A9: B | B9: PESCA Y SERVICIOS CONEXOS | C9: 74 | D9: 78 | E9: 75 | F9: 61 | G9: 49 | H9: 50 | I9: 57 | J9: 61 | K9: 63 | L9: 59 | M9: 62 | N9: 61 | O9: 56 | P9: 54 | Q9: 52 | R9: 48 | S9: 45 | T9: 41 | U9: 38 | V9: 37 | W9: 41 | X9: 40 | Y9: 42 | Z9: 43 | AA9: 41 | AB9: 40 | AC9: 39 | AD9: 42 | AE9: 45
A10: 5 | B10: Pesca y actividades relacionadas con la pesca | C10: 74 | D10: 78 | E10: 75 | F10: 61 | G10: 49 | H10: 50 | I10: 57 | J10: 61 | K10: 63 | L10: 59 | M10: 62 | N10: 61 | O10: 56 | P10: 54 | Q10: 52 | R10: 48 | S10: 45 | T10: 41 | U10: 38 | V10: 37 | W10: 41 | X10: 40 | Y10: 42 | Z10: 43 | AA10: 41 | AB10: 40 | AC10: 39 | AD10: 42 | AE10: 45
A11: C | B11: EXPLOTACION DE MINAS Y CANTERAS | C11: 159 | D11: 175 | E11: 163 | F11: 163 | G11: 139 | H11: 136 | I11: 116 | J11: 125 | K11: 137 | L11: 144 | M11: 164 | N11: 176 | O11: 187 | P11: 194 | Q11: 199 | R11: 206 | S11: 210 | T11: 201 | U11: 196 | V11: 195 | W11: 199 | X11: 196 | Y11: 202 | Z11: 199 | AA11: 196 | AB11: 207 | AC11: 203 | AD11: 192 | AE11: 191
A12: 11 | B12: Extraccion de petroleo crudo y gas natural | C12: 88 | D12: 100 | E12: 85 | F12: 89 | G12: 88 | H12: 86 | I12: 72 | J12: 75 | K12: 78 | L12: 85 | M12: 97 | N12: 110 | O12: 121 | P12: 126 | Q12: 126 | R12: 131 | S12: 130 | T12: 123 | U12: 122 | V12: 122 | W12: 123 | X12: 118 | Y12: 123 | Z12: 118 | AA12: 117 | AB12: 118 | AC12: 107 | AD12: 103 | AE12: 103
A13: 13 | B13: Extraccion de minerales metaliferos | C13: 10 | D13: 10 | E13: 11 | F13: 10 | G13: 7 | H13: 7 | I13: 5 | J13: 5 | K13: 6 | L13: 7 | M13: 12 | N13: 14 | O13: 15 | P13: 16 | Q13: 17 | R13: 18 | S13: 19 | T13: 16 | U13: 14 | V13: 16 | W13: 14 | X13: 13 | Y13: 15 | Z13: 15 | AA13: 13 | AB13: 15 | AC13: 15 | AD13: 17 | AE13: 15
A14: 14 | B14: Explotacion de otras minas y canteras | C14: 61 | D14: 65 | E14: 67 | F14: 64 | G14: 44 | H14: 43 | I14: 39 | J14: 45 | K14: 53 | L14: 52 | M14: 55 | N14: 52 | O14: 51 | P14: 52 | Q14: 56 | R14: 57 | S14: 61 | T14: 62 | U14: 60 | V14: 57 | W14: 62 | X14: 65 | Y14: 64 | Z14: 66 | AA14: 66 | AB14: 74 | AC14: 81 | AD14: 72 | AE14: 73
A15: D | B15: INDUSTRIA MANUFACTURERA | C15: 13269 | D15: 13381 | E15: 13293 | F15: 13034 | G15: 10941 | H15: 10178 | I15: 9474 | J15: 10109 | K15: 11119 | L15: 11645 | M15: 12459 | N15: 12951 | O15: 13073 | P15: 12831 | Q15: 12749 | R15: 12720 | S15: 12501 | T15: 12416 | U15: 12287 | V15: 12319 | W15: 12013 | X15: 11750 | Y15: 11314 | Z15: 10856 | AA15: 10656 | AB15: 10648 | AC15: 11150 | AD15: 10995 | AE15: 10891
A16: 15 | B16: Alimentos | C16: 1992 | D16: 1992 | E16: 1956 | F16: 1811 | G16: 1536 | H16: 1435 | I16: 1383 | J16: 1427 | K16: 1605 | L16: 1622 | M16: 1654 | N16: 1719 | O16: 1728 | P16: 1719 | Q16: 1745 | R16: 1767 | S16: 1738 | T16: 1727 | U16: 1731 | V16: 1737 | W16: 1734 | X16: 1750 | Y16: 1742 | Z16: 1713 | AA16: 1747 | AB16: 1787 | AC16: 1970 | AD16: 1990 | AE16: 2053
A17: 16 | B17: Tabaco | C17: 6 | D17: 6 | E17: 7 | F17: 6 | G17: 6 | H17: 6 | I17: 7 | J17: 8 | K17: 9 | L17: 9 | M17: 7 | N17: 7 | O17: 6 | P17: 6 | Q17: 7 | R17: 10 | S17: 9 | T17: 8 | U17: 11 | V17: 9 | W17: 9 | X17: 9 | Y17: 10 | Z17: 11 | AA17: 9 | AB17: 9 | AC17: 9 | AD17: 10 | AE17: 10
A18: 17 | B18: Productos textiles | C18: 1089 | D18: 1156 | E18: 1117 | F18: 1106 | G18: 972 | H18: 866 | I18: 813 | J18: 876 | K18: 983 | L18: 1030 | M18: 1134 | N18: 1175 | O18: 1208 | P18: 1198 | Q18: 1190 | R18: 1230 | S18: 1224 | T18: 1215 | U18: 1186 | V18: 1211 | W18: 1178 | X18: 1141 | Y18: 1092 | Z18: 1043 | AA18: 1036 | AB18: 1056 | AC18: 1087 | AD18: 1074 | AE18: 1063
A19: 18 | B19: Confecciones | C19: 1613 | D19: 1589 | E19: 1555 | F19: 1535 | G19: 1439 | H19: 1317 | I19: 1196 | J19: 1381 | K19: 1575 | L19: 1663 | M19: 1933 | N19: 2030 | O19: 2095 | P19: 2069 | Q19: 2037 | R19: 2004 | S19: 1975 | T19: 1959 | U19: 1985 | V19: 2013 | W19: 1947 | X19: 1884 | Y19: 1758 | Z19: 1639 | AA19: 1525 | AB19: 1482 | AC19: 1603 | AD19: 1596 | AE19: 1535
A20: 19 | B20: Calzado y productos de cuero | C20: 529 | D20: 521 | E20: 500 | F20: 481 | G20: 376 | H20: 343 | I20: 319 | J20: 370 | K20: 421 | L20: 454 | M20: 503 | N20: 529 | O20: 528 | P20: 506 | Q20: 516 | R20: 507 | S20: 492 | T20: 485 | U20: 483 | V20: 478 | W20: 456 | X20: 424 | Y20: 381 | Z20: 355 | AA20: 348 | AB20: 335 | AC20: 359 | AD20: 354 | AE20: 348
A21: 20 | B21: Madera | C21: 247 | D21: 251 | E21: 241 | F21: 246 | G21: 183 | H21: 174 | I21: 156 | J21: 163 | K21: 185 | L21: 201 | M21: 210 | N21: 208 | O21: 215 | P21: 196 | Q21: 194 | R21: 180 | S21: 172 | T21: 155 | U21: 147 | V21: 152 | W21: 145 | X21: 142 | Y21: 136 | Z21: 138 | AA21: 128 | AB21: 131 | AC21: 146 | AD21: 146 | AE21: 154
A22: 21 | B22: Papel | C22: 306 | D22: 318 | E22: 306 | F22: 311 | G22: 272 | H22: 262 | I22: 256 | J22: 271 | K22: 283 | L22: 299 | M22: 296 | N22: 301 | O22: 298 | P22: 288 | Q22: 285 | R22: 277 | S22: 275 | T22: 281 | U22: 278 | V22: 269 | W22: 257 | X22: 247 | Y22: 237 | Z22: 234 | AA22: 228 | AB22: 230 | AC22: 229 | AD22: 217 | AE22: 226
A23: 22 | B23: Edición | C23: 1544 | D23: 1592 | E23: 1646 | F23: 1639 | G23: 1509 | H23: 1424 | I23: 1285 | J23: 1321 | K23: 1408 | L23: 1496 | M23: 1578 | N23: 1644 | O23: 1650 | P23: 1628 | Q23: 1579 | R23: 1581 | S23: 1540 | T23: 1503 | U23: 1465 | V23: 1444 | W23: 1392 | X23: 1336 | Y23: 1276 | Z23: 1200 | AA23: 1145 | AB23: 1080 | AC23: 1060 | AD23: 1020 | AE23: 980
A24: 23 | B24: Productos de petróleo | C24: 35 | D24: 33 | E24: 32 | F24: 33 | G24: 30 | H24: 27 | I24: 25 | J24: 26 | K24: 28 | L24: 26 | M24: 27 | N24: 29 | O24: 28 | P24: 28 | Q24: 28 | R24: 26 | S24: 29 | T24: 29 | U24: 29 | V24: 31 | W24: 27 | X24: 24 | Y24: 25 | Z24: 24 | AA24: 23 | AB24: 24 | AC24: 28 | AD24: 25 | AE24: 26
A25: 24 | B25: Productos químicos | C25: 822 | D25: 850 | E25: 834 | F25: 839 | G25: 711 | H25: 692 | I25: 679 | J25: 712 | K25: 776 | L25: 811 | M25: 814 | N25: 823 | O25: 805 | P25: 806 | Q25: 807 | R25: 793 | S25: 788 | T25: 803 | U25: 793 | V25: 803 | W25: 802 | X25: 787 | Y25: 754 | Z25: 730 | AA25: 732 | AB25: 733 | AC25: 726 | AD25: 710 | AE25: 694
A26: 25 | B26: Productos de caucho y plástico | C26: 717 | D26: 731 | E26: 734 | F26: 719 | G26: 546 | H26: 511 | I26: 486 | J26: 511 | K26: 553 | L26: 587 | M26: 610 | N26: 635 | O26: 633 | P26: 629 | Q26: 634 | R26: 624 | S26: 596 | T26: 609 | U26: 593 | V26: 593 | W26: 575 | X26: 579 | Y26: 556 | Z26: 535 | AA26: 524 | AB26: 544 | AC26: 572 | AD26: 561 | AE26: 565
A27: 26 | B27: Otros minerales no metálicos | C27: 272 | D27: 281 | E27: 274 | F27: 262 | G27: 200 | H27: 202 | I27: 190 | J27: 207 | K27: 209 | L27: 228 | M27: 223 | N27: 239 | O27: 238 | P27: 231 | Q27: 230 | R27: 226 | S27: 225 | T27: 223 | U27: 222 | V27: 220 | W27: 217 | X27: 217 | Y27: 212 | Z27: 215 | AA27: 206 | AB27: 206 | AC27: 206 | AD27: 205 | AE27: 204
... A38: 37 | B38: Reciclamiento de desperdicios y desechos | C38: 17 | D38: 17 | E38: 12 | F38: 13 | G38: 10 | H38: 8 | I38: 10 | J38: 15 | K38: 20 | L38: 21 | M38: 28 | N38: 37 | O38: 33 | P38: 32 | Q38: 41 | R38: 35 | S38: 35 | T38: 32 | U38: 34 | V38: 34 | W38: 31 | X38: 29 | Y38: 29 | Z38: 30 | AA38: 29 | AB38: 33 | AC38: 39 | AD38: 39 | AE38: 41
A39: E | B39: ELECTRICIDAD, GAS Y AGUA | C39: 67 | D39: 68 | E39: 61 | F39: 64 | G39: 52 | H39: 56 | I39: 54 | J39: 52 | K39: 57 | L39: 51 | M39: 52 | N39: 57 | O39: 61 | P39: 63 | Q39: 67 | R39: 69 | S39: 79 | T39: 82 | U39: 75 | V39: 79 | W39: 77 | X39: 91 | Y39: 90 | Z39: 96 | AA39: 100 | AB39: 103 | AC39: 112 | AD39: 108 | AE39: 109
A40: 40 | B40: Electricidad, gas y agua | C40: 55 | D40: 55 | E40: 49 | F40: 52 | G40: 45 | H40: 46 | I40: 46 | J40: 44 | K40: 51 | L40: 46 | M40: 46 | N40: 50 | O40: 54 | P40: 58 | Q40: 61 | R40: 61 | S40: 73 | T40: 76 | U40: 71 | V40: 74 | W40: 72 | X40: 86 | Y40: 86 | Z40: s.d. | AA40: s.d. | AB40: s.d. | AC40: 105 | AD40: 101 | AE40: 102
A41: 41 | B41: Captación, depuración y distribución de agua | C41: 12 | D41: 13 | E41: 12 | F41: 12 | G41: 7 | H41: 10 | I41: 8 | J41: 8 | K41: 6 | L41: 5 | M41: 6 | N41: 7 | O41: 7 | P41: 5 | Q41: 6 | R41: 8 | S41: 6 | T41: 6 | U41: 4 | V41: 5 | W41: 5 | X41: 5 | Y41: 4 | Z41: s.d. | AA41: s.d. | AB41: s.d. | AC41: 7 | AD41: 7 | AE41: 7
A42: F | B42: CONSTRUCCION | C42: 3514 | D42: 3748 | E42: 3798 | F42: 3909 | G42: 3526 | H42: 3130 | I42: 2622 | J42: 3031 | K42: 3576 | L42: 4132 | M42: 4625 | N42: 5066 | O42: 5306 | P42: 5112 | Q42: 5331 | R42: 5463 | S42: 5546 | T42: 5585 | U42: 5533 | V42: 5506 | W42: 5508 | X42: 5658 | Y42: 5753 | Z42: 5634 | AA42: 5249 | AB42: 5298 | AC42: 5562 | AD42: 5635 | AE42: 5436
A43: 45 | B43: Construccion | C43: 3514 | D43: 3748 | E43: 3798 | F43: 3909 | G43: 3526 | H43: 3130 | I43: 2622 | J43: 3031 | K43: 3576 | L43: 4132 | M43: 4625 | N43: 5066 | O43: 5306 | P43: 5112 | Q43: 5331 | R43: 5463 | S43: 5546 | T43: 5585 | U43: 5533 | V43: 5506 | W43: 5508 | X43: 5658 | Y43: 5753 | Z43: 5634 | AA43: 5249 | AB43: 5298 | AC43: 5562 | AD43: 5635 | AE43: 5436
A44: G | B44: COMERCIO AL POR MAYOR Y AL POR MENOR | C44: 20403 | D44: 20608 | E44: 20282 | F44: 19261 | G44: 17242 | H44: 16272 | I44: 15272 | J44: 16971 | K44: 20743 | L44: 22307 | M44: 23791 | N44: 24663 | O44: 25389 | P44: 25566 | Q44: 26170 | R44: 26644 | S44: 26648 | T44: 26709 | U44: 26683 | V44: 27021 | W44: 27570 | X44: 27889 | Y44: 27403 | Z44: 26462 | AA44: 25283 | AB44: 25441 | AC44: 28355 | AD44: 28592 | AE44: 29236
A45: 50 | B45: Vta y reparación de vehículos. vta por menor de combustible | C45: 2657 | D45: 2675 | E45: 2653 | F45: 2519 | G45: 2106 | H45: 2043 | I45: 1937 | J45: 2053 | K45: 2338 | L45: 2441 | M45: 2525 | N45: 2586 | O45: 2635 | P45: 2612 | Q45: 2647 | R45: 2638 | S45: 2635 | T45: 2582 | U45: 2520 | V45: 2545 | W45: 2539 | X45: 2556 | Y45: 2565 | Z45: 2488 | AA45: 2408 | AB45: 2448 | AC45: 2633 | AD45: 2644 | AE45: 2646
A46: 51 | B46: Comercio al por mayor | C46: 6748 | D46: 6845 | E46: 6833 | F46: 6794 | G46: 6264 | H46: 5946 | I46: 5625 | J46: 6265 | K46: 6989 | L46: 7478 | M46: 7900 | N46: 8230 | O46: 8451 | P46: 8537 | Q46: 8739 | R46: 9025 | S46: 9191 | T46: 9290 | U46: 9288 | V46: 9475 | W46: 9617 | X46: 9721 | Y46: 9559 | Z46: 9376 | AA46: 9243 | AB46: 9425 | AC46: 9983 | AD46: 9977 | AE46: 10129
A47: 52 | B47: Comercio al por menor | C47: 10998 | D47: 11088 | E47: 10796 | F47: 9948 | G47: 8872 | H47: 8283 | I47: 7710 | J47: 8653 | K47: 11416 | L47: 12388 | M47: 13366 | N47: 13847 | O47: 14303 | P47: 14417 | Q47: 14784 | R47: 14981 | S47: 14822 | T47: 14837 | U47: 14875 | V47: 15001 | W47: 15414 | X47: 15612 | Y47: 15279 | Z47: 14598 | AA47: 13632 | AB47: 13568 | AC47: 15739 | AD47: 15971 | AE47: 16461
A48: H | B48: HOTELERIA Y RESTAURANTES | C48: 4913 | D48: 4939 | E48: 4680 | F48: 4100 | G48: 3799 | H48: 3606 | I48: 3427 | J48: 3630 | K48: 4825 | L48: 5156 | M48: 5478 | N48: 5768 | O48: 5951 | P48: 6104 | Q48: 6212 | R48: 6375 | S48: 6423 | T48: 6494 | U48: 6508 | V48: 6584 | W48: 6637 | X48: 6772 | Y48: 6835 | Z48: 6731 | AA48: 6031 | AB48: 5981 | AC48: 6954 | AD48: 7224 | AE48: 7372
A49: 55 | B49: Servicios de hoteleria y restaurantes | C49: 4913 | D49: 4939 | E49: 4680 | F49: 4100 | G49: 3799 | H49: 3606 | I49: 3427 | J49: 3630 | K49: 4825 | L49: 5156 | M49: 5478 | N49: 5768 | O49: 5951 | P49: 6104 | Q49: 6212 | R49: 6375 | S49: 6423 | T49: 6494 | U49: 6508 | V49: 6584 | W49: 6637 | X49: 6772 | Y49: 6835 | Z49: 6731 | AA49: 6031 | AB49: 5981 | AC49: 6954 | AD49: 7224 | AE49: 7372
A50: I | B50: SERVICIOS DE TRANSPORTE, DE ALMACENAMIENTO Y DE COMUNICACIONES | C50: 11200 | D50: 13265 | E50: 13735 | F50: 13845 | G50: 13123 | H50: 12264 | I50: 10971 | J50: 10963 | K50: 12092 | L50: 12492 | M50: 12592 | N50: 12850 | O50: 13038 | P50: 12988 | Q50: 12887 | R50: 12858 | S50: 12763 | T50: 12728 | U50: 12510 | V50: 12467 | W50: 12111 | X50: 11818 | Y50: 11240 | Z50: 10388 | AA50: 9113 | AB50: 8421 | AC50: 8396 | AD50: 7986 | AE50: 7609
A51: 60 | B51: Transporte ferroviario y automotor y por tuberias | C51: 8128 | D51: 9981 | E51: 10368 | F51: 10541 | G51: 9843 | H51: 9098 | I51: 7967 | J51: 7765 | K51: 8145 | L51: 8344 | M51: 8285 | N51: 8374 | O51: 8412 | P51: 8360 | Q51: 8204 | R51: 8121 | S51: 8002 | T51: 7959 | U51: 7704 | V51: 7616 | W51: 7338 | X51: 7045 | Y51: 6515 | Z51: 5745 | AA51: 4626 | AB51: 4014 | AC51: 3900 | AD51: 3571 | AE51: 3164
A52: 61 | B52: Transporte marítimo y fluvial | C52: 84 | D52: 86 | E52: 90 | F52: 93 | G52: 97 | H52: 96 | I52: 90 | J52: 95 | K52: 108 | L52: 109 | M52: 107 | N52: 113 | O52: 116 | P52: 109 | Q52: 107 | R52: 107 | S52: 105 | T52: 104 | U52: 104 | V52: 93 | W52: 89 | X52: 83 | Y52: 87 | Z52: 85 | AA52: 87 | AB52: 83 | AC52: 84 | AD52: 83 | AE52: 85
A53: 62 | B53: Transporte aéreo de cargas y de pasajeros | C53: 98 | D53: 108 | E53: 101 | F53: 105 | G53: 106 | H53: 102 | I53: 100 | J53: 101 | K53: 99 | L53: 100 | M53: 101 | N53: 102 | O53: 108 | P53: 112 | Q53: 114 | R53: 116 | S53: 107 | T53: 107 | U53: 106 | V53: 109 | W53: 112 | X53: 112 | Y53: 111 | Z53: 108 | AA53: 101 | AB53: 99 | AC53: 103 | AD53: 92 | AE53: 88
A54: 63 | B54: Manipulación de carga, almacenamiento y depósito | C54: 2501 | D54: 2646 | E54: 2662 | F54: 2460 | G54: 2350 | H54: 2265 | I54: 2158 | J54: 2262 | K54: 2907 | L54: 3125 | M54: 3319 | N54: 3523 | O54: 3693 | P54: 3751 | Q54: 3839 | R54: 3894 | S54: 3938 | T54: 3976 | U54: 4020 | V54: 4081 | W54: 4028 | X54: 4036 | Y54: 4004 | Z54: 3969 | AA54: 3842 | AB54: 3770 | AC54: 3848 | AD54: 3818 | AE54: 3853
A55: 64 | B55: Telecomunicaciones y correos | C55: 389 | D55: 444 | E55: 514 | F55: 646 | G55: 727 | H55: 703 | I55: 656 | J55: 740 | K55: 833 | L55: 814 | M55: 780 | N55: 738 | O55: 709 | P55: 656 | Q55: 623 | R55: 620 | S55: 611 | T55: 582 | U55: 576 | V55: 568 | W55: 544 | X55: 542 | Y55: 523 | Z55: 481 | AA55: 457 | AB55: 455 | AC55: 461 | AD55: 422 | AE55: 419
A56: J | B56: INTERMEDIACION FINANCIERA Y OTROS SERVICIOS FINANCIEROS | C56: 1571 | D56: 1604 | E56: 1581 | F56: 1564 | G56: 1498 | H56: 1440 | I56: 1403 | J56: 1472 | K56: 1648 | L56: 1709 | M56: 1763 | N56: 1841 | O56: 1871 | P56: 1885 | Q56: 1914 | R56: 1969 | S56: 1986 | T56: 1993 | U56: 1949 | V56: 1971 | W56: 1985 | X56: 1995 | Y56: 2022 | Z56: 2016 | AA56: 1956 | AB56: 1961 | AC56: 1939 | AD56: 1920 | AE56: 1943
A57: 65 | B57: Intermediacion financiera y otros servicios financieros | C57: 628 | D57: 658 | E57: 663 | F57: 668 | G57: 649 | H57: 635 | I57: 622 | J57: 648 | K57: 699 | L57: 729 | M57: 749 | N57: 780 | O57: 783 | P57: 786 | Q57: 778 | R57: 799 | S57: 808 | T57: 796 | U57: 763 | V57: 764 | W57: 728 | X57: 740 | Y57: 745 | Z57: 715 | AA57: 685 | AB57: 692 | AC57: 652 | AD57: 627 | AE57: 598
A58: 66 | B58: Seguros | C58: 294 | D58: 278 | E58: 274 | F58: 273 | G58: 267 | H58: 250 | I58: 240 | J58: 236 | K58: 242 | L58: 243 | M58: 235 | N58: 232 | O58: 228 | P58: 223 | Q58: 223 | R58: 222 | S58: 223 | T58: 226 | U58: 230 | V58: 235 | W58: 234 | X58: 230 | Y58: 230 | Z58: 226 | AA58: 227 | AB58: 224 | AC58: 223 | AD58: 225 | AE58: 222
A59: 67 | B59: Servicios auxiliares a la actividad financiera | C59: 649 | D59: 668 | E59: 644 | F59: 623 | G59: 582 | H59: 555 | I59: 541 | J59: 588 | K59: 707 | L59: 737 | M59: 779 | N59: 829 | O59: 860 | P59: 876 | Q59: 913 | R59: 948 | S59: 955 | T59: 971 | U59: 956 | V59: 972 | W59: 1023 | X59: 1025 | Y59: 1047 | Z59: 1075 | AA59: 1044 | AB59: 1045 | AC59: 1064 | AD59: 1068 | AE59: 1123
A60: K | B60: SERVICIOS INMOBILIARIOS, EMPRESARIALES Y DE ALQUILER | C60: 42673 | D60: 44062 | E60: 44843 | F60: 45659 | G60: 44915 | H60: 45032 | I60: 44230 | J60: 45733 | K60: 49260 | L60: 51136 | M60: 52737 | N60: 54381 | O60: 55447 | P60: 55815 | Q60: 56650 | R60: 57155 | S60: 57498 | T60: 57847 | U60: 58098 | V60: 58610 | W60: 58581 | X60: 58775 | Y60: 58684 | Z60: 58287 | AA60: 57253 | AB60: 56862 | AC60: 57653 | AD60: 56453 | AE60: 55553
A61: 70 | B61: Servicios inmobiliarios | C61: 30104 | D61: 30802 | E61: 31281 | F61: 31659 | G61: 31354 | H61: 31732 | I61: 31704 | J61: 32265 | K61: 33470 | L61: 34168 | M61: 34773 | N61: 35407 | O61: 35962 | P61: 36401 | Q61: 36897 | R61: 37351 | S61: 37717 | T61: 38130 | U61: 38600 | V61: 39011 | W61: 39087 | X61: 39163 | Y61: 39290 | Z61: 39252 | AA61: 38877 | AB61: 38715 | AC61: 39195 | AD61: 38360 | AE61: 37727
A62: 71 | B62: Alquiler de equipo de transporte y de maquinaria | C62: 236 | D62: 226 | E62: 231 | F62: 220 | G62: 200 | H62: 184 | I62: 166 | J62: 178 | K62: 213 | L62: 234 | M62: 258 | N62: 282 | O62: 307 | P62: 307 | Q62: 321 | R62: 328 | S62: 321 | T62: 335 | U62: 340 | V62: 337 | W62: 341 | X62: 330 | Y62: 342 | Z62: 349 | AA62: 329 | AB62: 335 | AC62: 349 | AD62: 350 | AE62: 351
A63: 72 | B63: Actividades de informática | C63: 858 | D63: 961 | E63: 1058 | F63: 1155 | G63: 1346 | H63: 1336 | I63: 1242 | J63: 1391 | K63: 1646 | L63: 1876 | M63: 2095 | N63: 2295 | O63: 2458 | P63: 2526 | Q63: 2706 | R63: 2825 | S63: 2972 | T63: 3015 | U63: 3080 | V63: 3180 | W63: 3281 | X63: 3381 | Y63: 3419 | Z63: 3538 | AA63: 3584 | AB63: 3683 | AC63: 3763 | AD63: 3748 | AE63: 3800
A64: 73 | B64: Investigación y desarrollo | C64: 99 | D64: 102 | E64: 111 | F64: 107 | G64: 100 | H64: 104 | I64: 101 | J64: 106 | K64: 120 | L64: 127 | M64: 132 | N64: 147 | O64: 166 | P64: 171 | Q64: 179 | R64: 182 | S64: 176 | T64: 175 | U64: 172 | V64: 168 | W64: 165 | X64: 172 | Y64: 179 | Z64: 181 | AA64: 181 | AB64: 188 | AC64: 187 | AD64: 183 | AE64: 191
A65: 74 | B65: Servicios jurídicos, contables y otros servicios a empresas | C65: 11306 | D65: 11900 | E65: 12091 | F65: 12441 | G65: 11839 | H65: 11603 | I65: 10946 | J65: 11718 | K65: 13737 | L65: 14656 | M65: 15410 | N65: 16184 | O65: 16488 | P65: 16346 | Q65: 16484 | R65: 16409 | S65: 16256 | T65: 16137 | U65: 15854 | V65: 15864 | W65: 15661 | X65: 15687 | Y65: 15416 | Z65: 14938 | AA65: 14253 | AB65: 13911 | AC65: 14130 | AD65: 13783 | AE65: 13456
A66: 75 | B66: Agencias de empleo eventual | C66: 70 | D66: 71 | E66: 71 | F66: 77 | G66: 76 | H66: 73 | I66: 71 | J66: 75 | K66: 74 | L66: 75 | M66: 69 | N66: 66 | O66: 66 | P66: 64 | Q66: 63 | R66: 60 | S66: 56 | T66: 55 | U66: 52 | V66: 50 | W66: 46 | X66: 42 | Y66: 38 | Z66: 29 | AA66: 29 | AB66: 30 | AC66: 29 | AD66: 29 | AE66: 28
A67: M | B67: ENSEÑANZA | C67: 1732 | D67: 1820 | E67: 1892 | F67: 1871 | G67: 1670 | H67: 1636 | I67: 1560 | J67: 1587 | K67: 1725 | L67: 1765 | M67: 1845 | N67: 1905 | O67: 1945 | P67: 1893 | Q67: 1894 | R67: 1902 | S67: 1881 | T67: 1844 | U67: 1806 | V67: 1814 | W67: 1792 | X67: 1859 | Y67: 1865 | Z67: 1844 | AA67: 1764 | AB67: 1738 | AC67: 1753 | AD67: 1790 | AE67: 1847
A68: 80 | B68: Enseñanza | C68: 1732 | D68: 1820 | E68: 1892 | F68: 1871 | G68: 1670 | H68: 1636 | I68: 1560 | J68: 1587 | K68: 1725 | L68: 1765 | M68: 1845 | N68: 1905 | O68: 1945 | P68: 1893 | Q68: 1894 | R68: 1902 | S68: 1881 | T68: 1844 | U68: 1806 | V68: 1814 | W68: 1792 | X68: 1859 | Y68: 1865 | Z68: 1844 | AA68: 1764 | AB68: 1738 | AC68: 1753 | AD68: 1790 | AE68: 1847
A69: N | B69: SERVICIOS SOCIALES Y DE SALUD | C69: 3975 | D69: 4085 | E69: 4124 | F69: 4101 | G69: 3835 | H69: 3784 | I69: 3639 | J69: 3734 | K69: 4143 | L69: 4366 | M69: 4523 | N69: 4692 | O69: 4746 | P69: 4870 | Q69: 4983 | R69: 5037 | S69: 5090 | T69: 5111 | U69: 5117 | V69: 5156 | W69: 5138 | X69: 5185 | Y69: 5154 | Z69: 5074 | AA69: 4897 | AB69: 4783 | AC69: 4959 | AD69: 4888 | AE69: 4761
A70: 85 | B70: Servicios sociales y de salud | C70: 3975 | D70: 4085 | E70: 4124 | F70: 4101 | G70: 3835 | H70: 3784 | I70: 3639 | J70: 3734 | K70: 4143 | L70: 4366 | M70: 4523 | N70: 4692 | O70: 4746 | P70: 4870 | Q70: 4983 | R70: 5037 | S70: 5090 | T70: 5111 | U70: 5117 | V70: 5156 | W70: 5138 | X70: 5185 | Y70: 5154 | Z70: 5074 | AA70: 4897 | AB70: 4783 | AC70: 4959 | AD70: 4888 | AE70: 4761
A71: O | B71: SERVICIOS COMUNITARIOS, SOCIALES Y PERSONALES N.C.P. | C71: 9185 | D71: 9304 | E71: 9128 | F71: 8494 | G71: 7729 | H71: 7428 | I71: 7060 | J71: 7555 | K71: 10142 | L71: 10662 | M71: 10900 | N71: 10883 | O71: 10587 | P71: 10341 | Q71: 10318 | R71: 10193 | S71: 9901 | T71: 9758 | U71: 9590 | V71: 9544 | W71: 9362 | X71: 9356 | Y71: 9190 | Z71: 8836 | AA71: 8125 | AB71: 7803 | AC71: 8179 | AD71: 8009 | AE71: 7756
A72: 90 | B72: Eliminación de desperdicios | C72: 226 | D72: 229 | E72: 227 | F72: 173 | G72: 139 | H72: 110 | I72: 106 | J72: 104 | K72: 127 | L72: 131 | M72: 133 | N72: 141 | O72: 153 | P72: 150 | Q72: 164 | R72: 171 | S72: 176 | T72: 183 | U72: 185 | V72: 194 | W72: 206 | X72: 208 | Y72: 209 | Z72: 201 | AA72: 196 | AB72: 206 | AC72: 198 | AD72: 201 | AE72: 201
A73: 91 | B73: Servicios de organizaciones empresariales | C73: 2473 | D73: 2517 | E73: 2513 | F73: 2605 | G73: 2503 | H73: 2523 | I73: 2515 | J73: 2623 | K73: 2729 | L73: 2862 | M73: 2916 | N73: 2977 | O73: 2978 | P73: 3033 | Q73: 3066 | R73: 3124 | S73: 3119 | T73: 3151 | U73: 3133 | V73: 3124 | W73: 3117 | X73: 3111 | Y73: 3071 | Z73: 3057 | AA73: 3016 | AB73: 2996 | AC73: 3087 | AD73: 3023 | AE73: 2964
A74: 92 | B74: Servicios culturales, deportivos y de esparcimiento | C74: 1347 | D74: 1378 | E74: 1336 | F74: 1301 | G74: 1202 | H74: 1136 | I74: 1101 | J74: 1235 | K74: 1466 | L74: 1627 | M74: 1754 | N74: 1900 | O74: 2003 | P74: 2042 | Q74: 2139 | R74: 2186 | S74: 2234 | T74: 2293 | U74: 2323 | V74: 2411 | W74: 2402 | X74: 2492 | Y74: 2532 | Z74: 2489 | AA74: 2273 | AB74: 2261 | AC74: 2420 | AD74: 2399 | AE74: 2308
A75: 93 | B75: Servicios n.c.p. | C75: 5139 | D75: 5180 | E75: 5052 | F75: 4415 | G75: 3885 | H75: 3659 | I75: 3338 | J75: 3593 | K75: 5820 | L75: 6042 | M75: 6097 | N75: 5865 | O75: 5453 | P75: 5116 | Q75: 4949 | R75: 4712 | S75: 4372 | T75: 4131 | U75: 3949 | V75: 3815 | W75: 3637 | X75: 3545 | Y75: 3378 | Z75: 3089 | AA75: 2640 | AB75: 2340 | AC75: 2474 | AD75: 2386 | AE75: 2283
B76: TOTAL | C76: 115152 | D76: 119538 | E76: 119894 | F76: 118301 | G76: 109961 | H76: 106455 | I76: 101330 | J76: 106533 | K76: 121217 | L76: 127423 | M76: 132900 | N76: 137278 | O76: 139624 | P76: 139629 | Q76: 141357 | R76: 142598 | S76: 142540 | T76: 142765 | U76: 142323 | V76: 143253 | W76: 142948 | X76: 143321 | Y76: 141717 | Z76: 138366 | AA76: 132560 | AB76: 131244 | AC76: 137664 | AD76: 136335 | AE76: 135236
A78: Notas:
A79: 1 - Las empresas se encuentran clasificadas por provincia según las zonas donde declaran que trabajan las personas.
A80: 2 - Las firmas con participación accionaria privada y estatal se incluye dentro del sector privado
A81: 3 - s/d : Dato no publicado para resguardar el secreto estadístico de las firmas
A82: Fuente: STEySS - Dirección Nacional de Estudios y Estadísticas Laborales - Observatorio de Empleo y Dinámica Empresarial, en base a SIPA.

Sheet Resto de Buenos Aires
D1: Volver al índice
A2: RESTO DE BUENOS AIRES
A3: Empresas del sector privado por rama de actividad - Activas en cada año
B4: Ramas de actividad | C4: 1996 | D4: 1997 | E4: 1998 | F4: 1999 | G4: 2000 | H4: 2001 | I4: 2002 | J4: 2003 | K4: 2004 | L4: 2005 | M4: 2006 | N4: 2007 | O4: 2008 | P4: 2009 | Q4: 2010 | R4: 2011 | S4: 2012 | T4: 2013 | U4: 2014 | V4: 2015 | W4: 2016 | X4: 2017 | Y4: 2018 | Z4: 2019 | AA4: 2020 | AB4: 2021 | AC4: 2022 | AD4: 2023 | AE4: 2024
D5: 2º Trim 1996 | F5: 3º Trim 1996 | H5: 4º Trim 1996 | J5: 1º Trim 1997 | L5: 2º Trim 1997 | N5: 3º Trim 1997 | P5: 4º Trim 1997 | R5: 1º Trim 1998
A6: A | B6: AGRICULTURA, GANADERIA, CAZA Y SILVICULTURA | C6: 15965 | D6: 16204 | E6: 16171 | F6: 16280 | G6: 15514 | H6: 14975 | I6: 14834 | J6: 15724 | K6: 16817 | L6: 17805 | M6: 18507 | N6: 18968 | O6: 19290 | P6: 18666 | Q6: 18874 | R6: 19300 | S6: 19024 | T6: 18551 | U6: 18131 | V6: 17598 | W6: 17413 | X6: 17278 | Y6: 16989 | Z6: 16943 | AA6: 16899 | AB6: 17047 | AC6: 17003 | AD6: 16408 | AE6: 16211
A7: 1 | B7: Agricultura y ganaderia | C7: 15912 | D7: 16156 | E7: 16108 | F7: 16216 | G7: 15466 | H7: 14931 | I7: 14793 | J7: 15686 | K7: 16770 | L7: 17757 | M7: 18458 | N7: 18908 | O7: 19231 | P7: 18602 | Q7: 18806 | R7: 19226 | S7: 18951 | T7: 18481 | U7: 18067 | V7: 17527 | W7: 17352 | X7: 17222 | Y7: 16939 | Z7: 16896 | AA7: 16850 | AB7: 17001 | AC7: 16949 | AD7: 16350 | AE7: 16158
A8: 2 | B8: Silvicultura, extracción de madera | C8: 53 | D8: 48 | E8: 63 | F8: 64 | G8: 48 | H8: 44 | I8: 41 | J8: 38 | K8: 47 | L8: 48 | M8: 49 | N8: 60 | O8: 59 | P8: 64 | Q8: 68 | R8: 74 | S8: 73 | T8: 70 | U8: 64 | V8: 71 | W8: 61 | X8: 56 | Y8: 50 | Z8: 47 | AA8: 49 | AB8: 46 | AC8: 54 | AD8: 58 | AE8: 53
A9: B | B9: PESCA Y SERVICIOS CONEXOS | C9: 84 | D9: 96 | E9: 113 | F9: 134 | G9: 168 | H9: 178 | I9: 167 | J9: 165 | K9: 175 | L9: 185 | M9: 195 | N9: 194 | O9: 201 | P9: 205 | Q9: 198 | R9: 197 | S9: 197 | T9: 188 | U9: 180 | V9: 169 | W9: 171 | X9: 163 | Y9: 167 | Z9: 168 | AA9: 165 | AB9: 173 | AC9: 172 | AD9: 165 | AE9: 160
A10: 5 | B10: Pesca y actividades relacionadas con la pesca | C10: 84 | D10: 96 | E10: 113 | F10: 134 | G10: 168 | H10: 178 | I10: 167 | J10: 165 | K10: 175 | L10: 185 | M10: 195 | N10: 194 | O10: 201 | P10: 205 | Q10: 198 | R10: 197 | S10: 197 | T10: 188 | U10: 180 | V10: 169 | W10: 171 | X10: 163 | Y10: 167 | Z10: 168 | AA10: 165 | AB10: 173 | AC10: 172 | AD10: 165 | AE10: 160
A11: C | B11: EXPLOTACION DE MINAS Y CANTERAS | C11: 96 | D11: 101 | E11: 94 | F11: 106 | G11: 96 | H11: 88 | I11: 79 | J11: 79 | K11: 94 | L11: 99 | M11: 112 | N11: 113 | O11: 110 | P11: 108 | Q11: 106 | R11: 111 | S11: 116 | T11: 109 | U11: 108 | V11: 105 | W11: 104 | X11: 111 | Y11: 113 | Z11: 118 | AA11: 114 | AB11: 118 | AC11: 119 | AD11: 118 | AE11: 124
A12: 11 | B12: Extraccion de petroleo crudo y gas natural | C12: 17 | D12: 12 | E12: 15 | F12: 17 | G12: 17 | H12: 17 | I12: 16 | J12: 13 | K12: 15 | L12: 14 | M12: 22 | N12: 21 | O12: 22 | P12: 21 | Q12: 18 | R12: 19 | S12: 20 | T12: 19 | U12: 18 | V12: 17 | W12: 18 | X12: 19 | Y12: 20 | Z12: 20 | AA12: 18 | AB12: 21 | AC12: 25 | AD12: 22 | AE12: 24
A13: 13 | B13: Extraccion de minerales metaliferos | C13: s.d. | D13: s.d. | E13: s.d. | F13: s.d. | G13: s.d. | H13: s.d. | I13: s.d. | J13: s.d. | K13: s.d. | L13: s.d. | M13: s.d. | N13: s.d. | O13: s.d. | P13: s.d. | Q13: s.d. | R13: s.d. | S13: s.d. | T13: s.d. | U13: s.d. | V13: s.d. | W13: s.d. | X13: s.d. | Y13: s.d. | Z13: s.d. | AA13: s.d. | AB13: s.d. | AC13: s.d. | AD13: s.d. | AE13: s.d.
A14: 14 | B14: Explotacion de otras minas y canteras | C14: s.d. | D14: s.d. | E14: s.d. | F14: s.d. | G14: s.d. | H14: s.d. | I14: s.d. | J14: s.d. | K14: s.d. | L14: s.d. | M14: s.d. | N14: s.d. | O14: s.d. | P14: s.d. | Q14: s.d. | R14: s.d. | S14: s.d. | T14: s.d. | U14: s.d. | V14: s.d. | W14: s.d. | X14: s.d. | Y14: s.d. | Z14: s.d. | AA14: s.d. | AB14: s.d. | AC14: s.d. | AD14: s.d. | AE14: s.d.
A15: D | B15: INDUSTRIA MANUFACTURERA | C15: 5886 | D15: 5892 | E15: 5808 | F15: 5826 | G15: 5483 | H15: 5171 | I15: 4903 | J15: 5433 | K15: 6142 | L15: 6590 | M15: 7061 | N15: 7382 | O15: 7659 | P15: 7744 | Q15: 7766 | R15: 7844 | S15: 7995 | T15: 8070 | U15: 8119 | V15: 8239 | W15: 8175 | X15: 8136 | Y15: 7863 | Z15: 7654 | AA15: 7539 | AB15: 7776 | AC15: 8200 | AD15: 8190 | AE15: 8054
A16: 15 | B16: Alimentos | C16: 1931 | D16: 1899 | E16: 1847 | F16: 1786 | G16: 1690 | H16: 1590 | I16: 1532 | J16: 1652 | K16: 1850 | L16: 1944 | M16: 2055 | N16: 2162 | O16: 2324 | P16: 2418 | Q16: 2455 | R16: 2474 | S16: 2523 | T16: 2562 | U16: 2646 | V16: 2684 | W16: 2689 | X16: 2710 | Y16: 2668 | Z16: 2593 | AA16: 2552 | AB16: 2649 | AC16: 2789 | AD16: 2809 | AE16: 2815
A17: 16 | B17: Tabaco | C17: s.d. | D17: s.d. | E17: s.d. | F17: s.d. | G17: s.d. | H17: s.d. | I17: s.d. | J17: s.d. | K17: s.d. | L17: s.d. | M17: s.d. | N17: s.d. | O17: s.d. | P17: s.d. | Q17: s.d. | R17: s.d. | S17: s.d. | T17: s.d. | U17: s.d. | V17: s.d. | W17: s.d. | X17: s.d. | Y17: s.d. | Z17: s.d. | AA17: s.d. | AB17: s.d. | AC17: s.d. | AD17: s.d. | AE17: 4
A18: 17 | B18: Productos textiles | C18: 329 | D18: 337 | E18: 316 | F18: 303 | G18: 292 | H18: 274 | I18: 258 | J18: 285 | K18: 326 | L18: 347 | M18: 380 | N18: 406 | O18: 417 | P18: 412 | Q18: 415 | R18: 425 | S18: 416 | T18: 414 | U18: 423 | V18: 417 | W18: 405 | X18: 401 | Y18: 378 | Z18: 368 | AA18: 355 | AB18: 368 | AC18: 415 | AD18: 426 | AE18: 402
A19: 18 | B19: Confecciones | C19: 355 | D19: 346 | E19: 326 | F19: 309 | G19: 294 | H19: 254 | I19: 231 | J19: 301 | K19: 370 | L19: 410 | M19: 464 | N19: 457 | O19: 452 | P19: 446 | Q19: 422 | R19: 438 | S19: 450 | T19: 441 | U19: 423 | V19: 444 | W19: 430 | X19: 399 | Y19: 365 | Z19: 334 | AA19: 307 | AB19: 302 | AC19: 341 | AD19: 360 | AE19: 336
A20: 19 | B20: Calzado y cuero | C20: 65 | D20: 69 | E20: 64 | F20: 66 | G20: 55 | H20: 53 | I20: 54 | J20: 75 | K20: 86 | L20: 91 | M20: 97 | N20: 90 | O20: 84 | P20: 88 | Q20: 95 | R20: 92 | S20: 98 | T20: 97 | U20: 89 | V20: 90 | W20: 85 | X20: 80 | Y20: 72 | Z20: 69 | AA20: 67 | AB20: 69 | AC20: 80 | AD20: 75 | AE20: 72
A21: 20 | B21: Madera | C21: 324 | D21: 320 | E21: 308 | F21: 297 | G21: 279 | H21: 264 | I21: 236 | J21: 255 | K21: 299 | L21: 339 | M21: 350 | N21: 361 | O21: 363 | P21: 356 | Q21: 346 | R21: 344 | S21: 341 | T21: 335 | U21: 327 | V21: 330 | W21: 314 | X21: 304 | Y21: 285 | Z21: 275 | AA21: 270 | AB21: 268 | AC21: 286 | AD21: 268 | AE21: 248
A22: 21 | B22: Papel | C22: 63 | D22: 62 | E22: 60 | F22: 65 | G22: 64 | H22: 61 | I22: 63 | J22: 67 | K22: 75 | L22: 76 | M22: 81 | N22: 84 | O22: 84 | P22: 88 | Q22: 84 | R22: 85 | S22: 84 | T22: 89 | U22: 94 | V22: 92 | W22: 97 | X22: 92 | Y22: 94 | Z22: 96 | AA22: 96 | AB22: 105 | AC22: 99 | AD22: 88 | AE22: 90
A23: 22 | B23: Edición | C23: 391 | D23: 387 | E23: 401 | F23: 412 | G23: 394 | H23: 371 | I23: 348 | J23: 375 | K23: 418 | L23: 443 | M23: 480 | N23: 496 | O23: 519 | P23: 521 | Q23: 515 | R23: 511 | S23: 516 | T23: 499 | U23: 493 | V23: 484 | W23: 479 | X23: 474 | Y23: 440 | Z23: 412 | AA23: 391 | AB23: 377 | AC23: 363 | AD23: 352 | AE23: 337
A24: 23 | B24: Productos de petróleo | C24: 16 | D24: 16 | E24: 16 | F24: 18 | G24: 16 | H24: 15 | I24: 15 | J24: 18 | K24: 17 | L24: 17 | M24: 18 | N24: 19 | O24: 19 | P24: 21 | Q24: 21 | R24: 22 | S24: 22 | T24: 20 | U24: 19 | V24: 18 | W24: 19 | X24: 21 | Y24: 19 | Z24: 20 | AA24: 21 | AB24: 22 | AC24: 24 | AD24: 22 | AE24: 22
A25: 24 | B25: Productos químicos | C25: 274 | D25: 272 | E25: 275 | F25: 314 | G25: 321 | H25: 315 | I25: 297 | J25: 317 | K25: 327 | L25: 340 | M25: 358 | N25: 361 | O25: 374 | P25: 364 | Q25: 371 | R25: 379 | S25: 391 | T25: 414 | U25: 412 | V25: 419 | W25: 430 | X25: 431 | Y25: 421 | Z25: 425 | AA25: 425 | AB25: 428 | AC25: 443 | AD25: 443 | AE25: 451
A26: 25 | B26: Productos de caucho y plástico | C26: 181 | D26: 179 | E26: 200 | F26: 229 | G26: 216 | H26: 217 | I26: 216 | J26: 228 | K26: 254 | L26: 265 | M26: 281 | N26: 292 | O26: 302 | P26: 297 | Q26: 293 | R26: 293 | S26: 306 | T26: 315 | U26: 330 | V26: 348 | W26: 348 | X26: 348 | Y26: 338 | Z26: 323 | AA26: 338 | AB26: 352 | AC26: 384 | AD26: 372 | AE26: 372
A27: 26 | B27: Otros minerales no metálicos | C27: 357 | D27: 361 | E27: 361 | F27: 354 | G27: 325 | H27: 286 | I27: 268 | J27: 276 | K27: 294 | L27: 318 | M27: 342 | N27: 357 | O27: 365 | P27: 366 | Q27: 352 | R27: 351 | S27: 366 | T27: 374 | U27: 377 | V27: 379 | W27: 365 | X27: 363 | Y27: 358 | Z27: 359 | AA27: 359 | AB27: 381 | AC27: 399 | AD27: 380 | AE27: 364
A28: 27 | B28: Metales comunes | C28: 135 | D28: 140 | E28: 139 | F28: 136 | G28: 112 | H28: 106 | I28: 103 | J28: 113 | K28: 120 | L28: 138 | M28: 138 | N28: 135 | O28: 140 | P28: 129 | Q28: 136 | R28: 134 | S28: 134 | T28: 138 | U28: 137 | V28: 135 | W28: 135 | X28: 131 | Y28: 118 | Z28: 123 | AA28: 122 | AB28: 123 | AC28: 133 | AD28: 139 | AE28: 136
A29: 28 | B29: Otros productos de metal | C29: 615 | D29: 647 | E29: 633 | F29: 666 | G29: 639 | H29: 609 | I29: 567 | J29: 636 | K29: 750 | L29: 816 | M29: 874 | N29: 957 | O29: 989 | P29: 967 | Q29: 985 | R29: 1028 | S29: 1069 | T29: 1068 | U29: 1058 | V29: 1077 | W29: 1075 | X29: 1091 | Y29: 1040 | Z29: 1009 | AA29: 992 | AB29: 1011 | AC29: 1057 | AD29: 1055 | AE29: 1048
A30: 29 | B30: Maquinaria y equipo | C30: 263 | D30: 269 | E30: 269 | F30: 276 | G30: 243 | H30: 233 | I30: 228 | J30: 264 | K30: 299 | L30: 326 | M30: 351 | N30: 356 | O30: 350 | P30: 354 | Q30: 355 | R30: 364 | S30: 374 | T30: 385 | U30: 386 | V30: 389 | W30: 390 | X30: 403 | Y30: 382 | Z30: 373 | AA30: 375 | AB30: 395 | AC30: 406 | AD30: 398 | AE30: 380
A31: 30 | B31: Maquinaria de oficina | C31: s.d. | D31: s.d. | E31: s.d. | F31: s.d. | G31: s.d. | H31: 5 | I31: 5 | J31: 7 | K31: 7 | L31: 10 | M31: 10 | N31: 11 | O31: 11 | P31: 9 | Q31: 9 | R31: 11 | S31: s.d. | T31: s.d. | U31: s.d. | V31: s.d. | W31: s.d. | X31: s.d. | Y31: s.d. | Z31: 8 | AA31: 8 | AB31: 9 | AC31: s.d. | AD31: s.d. | AE31: 12
A32: 31 | B32: Aparatos eléctricos | C32: 83 | D32: 86 | E32: 83 | F32: 86 | G32: 78 | H32: 75 | I32: 63 | J32: 71 | K32: 78 | L32: 80 | M32: 93 | N32: 98 | O32: 104 | P32: 107 | Q32: 110 | R32: 113 | S32: 110 | T32: 112 | U32: 117 | V32: 121 | W32: 116 | X32: 114 | Y32: 114 | Z32: 110 | AA32: 107 | AB32: 113 | AC32: 115 | AD32: 111 | AE32: 114
A33: 32 | B33: Radio y televisión | C33: 16 | D33: 13 | E33: 12 | F33: 13 | G33: 11 | H33: s.d. | I33: s.d. | J33: s.d. | K33: s.d. | L33: s.d. | M33: s.d. | N33: s.d. | O33: s.d. | P33: s.d. | Q33: s.d. | R33: s.d. | S33: 10 | T33: 9 | U33: 11 | V33: 12 | W33: 12 | X33: 13 | Y33: 12 | Z33: s.d. | AA33: s.d. | AB33: s.d. | AC33: 10 | AD33: 12 | AE33: 12
A34: 33 | B34: Instrumentos médicos | C34: 33 | D34: 29 | E34: 28 | F34: 29 | G34: 27 | H34: 27 | I34: 26 | J34: 34 | K34: 38 | L34: 43 | M34: 44 | N34: 46 | O34: 43 | P34: 40 | Q34: 36 | R34: 38 | S34: 40 | T34: 41 | U34: 43 | V34: 49 | W34: 50 | X34: 45 | Y34: 45 | Z34: 44 | AA34: 44 | AB34: 47 | AC34: 52 | AD34: 47 | AE34: 50
A35: 34 | B35: Automotores | C35: 132 | D35: 137 | E35: 145 | F35: 146 | G35: 142 | H35: 144 | I35: 135 | J35: 146 | K35: 163 | L35: 176 | M35: 190 | N35: 195 | O35: 198 | P35: 198 | Q35: 207 | R35: 201 | S35: 197 | T35: 203 | U35: 199 | V35: 207 | W35: 207 | X35: 205 | Y35: 191 | Z35: 186 | AA35: 186 | AB35: 199 | AC35: 210 | AD35: 211 | AE35: 196
A36: 35 | B36: Otros equipo de transporte | C36: 59 | D36: 61 | E36: 55 | F36: 63 | G36: 52 | H36: 55 | I36: 55 | J36: 73 | K36: 82 | L36: 97 | M36: 105 | N36: 115 | O36: 116 | P36: 129 | Q36: 132 | R36: 132 | S36: 137 | T36: 139 | U36: 138 | V36: 138 | W36: 148 | X36: 148 | Y36: 155 | Z36: 157 | AA36: 171 | AB36: 198 | AC36: 210 | AD36: 209 | AE36: 205
A37: 36 | B37: Muebles | C37: 241 | D37: 238 | E37: 243 | F37: 227 | G37: 207 | H37: 190 | I37: 178 | J37: 204 | K37: 249 | L37: 276 | M37: 307 | N37: 338 | O37: 359 | P37: 382 | Q37: 380 | R37: 368 | S37: 360 | T37: 362 | U37: 344 | V37: 352 | W37: 325 | X37: 314 | Y37: 315 | Z37: 308 | AA37: 295 | AB37: 304 | AC37: 332 | AD37: 357 | AE37: 351
A38: 37 | B38: Reciclamiento de desperdicios y desechos | C38: 16 | D38: 16 | E38: 20 | F38: 21 | G38: 16 | H38: 17 | I38: 19 | J38: 25 | K38: 28 | L38: 27 | M38: 32 | N38: 32 | O38: 32 | P38: 36 | Q38: 34 | R38: 31 | S38: 39 | T38: 41 | U38: 43 | V38: 43 | W38: 45 | X38: 39 | Y38: 42 | Z38: 46 | AA38: 44 | AB38: 42 | AC38: 41 | AD38: 41 | AE38: 37
A39: E | B39: ELECTRICIDAD, GAS Y AGUA | C39: 273 | D39: 269 | E39: 278 | F39: 282 | G39: 274 | H39: 275 | I39: 270 | J39: 271 | K39: 275 | L39: 275 | M39: 277 | N39: 274 | O39: 275 | P39: 279 | Q39: 284 | R39: 286 | S39: 287 | T39: 292 | U39: 287 | V39: 290 | W39: 291 | X39: 296 | Y39: 290 | Z39: 296 | AA39: 294 | AB39: 299 | AC39: 302 | AD39: 299 | AE39: 295
A40: 40 | B40: Electricidad, gas y agua | C40: 222 | D40: 221 | E40: 228 | F40: 232 | G40: 223 | H40: 224 | I40: 219 | J40: 219 | K40: 221 | L40: 221 | M40: 221 | N40: 218 | O40: 218 | P40: 223 | Q40: 226 | R40: 228 | S40: 229 | T40: 231 | U40: 228 | V40: 232 | W40: 233 | X40: 237 | Y40: 234 | Z40: 236 | AA40: 236 | AB40: 241 | AC40: 244 | AD40: 242 | AE40: 240
A41: 41 | B41: Captación, depuración y distribución de agua | C41: 51 | D41: 48 | E41: 50 | F41: 50 | G41: 51 | H41: 51 | I41: 51 | J41: 52 | K41: 54 | L41: 54 | M41: 56 | N41: 56 | O41: 57 | P41: 56 | Q41: 58 | R41: 58 | S41: 58 | T41: 61 | U41: 59 | V41: 58 | W41: 58 | X41: 59 | Y41: 56 | Z41: 60 | AA41: 58 | AB41: 58 | AC41: 58 | AD41: 57 | AE41: 55
A42: F | B42: CONSTRUCCION | C42: 2184 | D42: 2298 | E42: 2380 | F42: 2412 | G42: 2381 | H42: 1991 | I42: 1720 | J42: 2110 | K42: 2643 | L42: 3157 | M42: 3577 | N42: 3926 | O42: 4118 | P42: 3924 | Q42: 4112 | R42: 4399 | S42: 4415 | T42: 4514 | U42: 4557 | V42: 4630 | W42: 4492 | X42: 4668 | Y42: 4585 | Z42: 4230 | AA42: 3948 | AB42: 4194 | AC42: 4411 | AD42: 4226 | AE42: 3887
A43: 45 | B43: Construccion | C43: 2184 | D43: 2298 | E43: 2380 | F43: 2412 | G43: 2381 | H43: 1991 | I43: 1720 | J43: 2110 | K43: 2643 | L43: 3157 | M43: 3577 | N43: 3926 | O43: 4118 | P43: 3924 | Q43: 4112 | R43: 4399 | S43: 4415 | T43: 4514 | U43: 4557 | V43: 4630 | W43: 4492 | X43: 4668 | Y43: 4585 | Z43: 4230 | AA43: 3948 | AB43: 4194 | AC43: 4411 | AD43: 4226 | AE43: 3887
A44: G | B44: COMERCIO AL POR MAYOR Y AL POR MENOR | C44: 16204 | D44: 16152 | E44: 16215 | F44: 15972 | G44: 15646 | H44: 14934 | I44: 14208 | J44: 15777 | K44: 19641 | L44: 21707 | M44: 23831 | N44: 25604 | O44: 27285 | P44: 28051 | Q44: 28750 | R44: 29207 | S44: 29693 | T44: 29880 | U44: 30106 | V44: 30575 | W44: 31110 | X44: 31349 | Y44: 30329 | Z44: 29366 | AA44: 28058 | AB44: 28570 | AC44: 30537 | AD44: 30765 | AE44: 30357
A45: 50 | B45: Vta y reparación de vehículos. vta por menor de combustible | C45: 2718 | D45: 2774 | E45: 2825 | F45: 2765 | G45: 2664 | H45: 2515 | I45: 2391 | J45: 2614 | K45: 3102 | L45: 3364 | M45: 3557 | N45: 3769 | O45: 3935 | P45: 3911 | Q45: 3971 | R45: 3989 | S45: 4049 | T45: 4036 | U45: 4034 | V45: 4055 | W45: 4089 | X45: 4081 | Y45: 3953 | Z45: 3822 | AA45: 3699 | AB45: 3728 | AC45: 3854 | AD45: 3878 | AE45: 3868
A46: 51 | B46: Comercio al por mayor | C46: 3477 | D46: 3472 | E46: 3428 | F46: 3540 | G46: 3371 | H46: 3185 | I46: 3085 | J46: 3351 | K46: 3695 | L46: 3917 | M46: 4096 | N46: 4229 | O46: 4442 | P46: 4494 | Q46: 4530 | R46: 4635 | S46: 4665 | T46: 4689 | U46: 4700 | V46: 4760 | W46: 4818 | X46: 4835 | Y46: 4794 | Z46: 4767 | AA46: 4774 | AB46: 4886 | AC46: 5107 | AD46: 5144 | AE46: 5178
A47: 52 | B47: Comercio al por menor | C47: 10009 | D47: 9906 | E47: 9962 | F47: 9667 | G47: 9611 | H47: 9234 | I47: 8732 | J47: 9812 | K47: 12844 | L47: 14426 | M47: 16178 | N47: 17606 | O47: 18908 | P47: 19646 | Q47: 20249 | R47: 20583 | S47: 20979 | T47: 21155 | U47: 21372 | V47: 21760 | W47: 22203 | X47: 22433 | Y47: 21582 | Z47: 20777 | AA47: 19585 | AB47: 19956 | AC47: 21576 | AD47: 21743 | AE47: 21311
A48: H | B48: HOTELERIA Y RESTAURANTES | C48: 2531 | D48: 2533 | E48: 2417 | F48: 2272 | G48: 2111 | H48: 1903 | I48: 1805 | J48: 2035 | K48: 2735 | L48: 3369 | M48: 3859 | N48: 4326 | O48: 4630 | P48: 4915 | Q48: 5015 | R48: 5241 | S48: 5472 | T48: 5558 | U48: 5750 | V48: 5824 | W48: 5842 | X48: 5802 | Y48: 5695 | Z48: 5510 | AA48: 4850 | AB48: 4865 | AC48: 5658 | AD48: 5616 | AE48: 5506
A49: 55 | B49: Servicios de hoteleria y restaurantes | C49: 2531 | D49: 2533 | E49: 2417 | F49: 2272 | G49: 2111 | H49: 1903 | I49: 1805 | J49: 2035 | K49: 2735 | L49: 3369 | M49: 3859 | N49: 4326 | O49: 4630 | P49: 4915 | Q49: 5015 | R49: 5241 | S49: 5472 | T49: 5558 | U49: 5750 | V49: 5824 | W49: 5842 | X49: 5802 | Y49: 5695 | Z49: 5510 | AA49: 4850 | AB49: 4865 | AC49: 5658 | AD49: 5616 | AE49: 5506
A50: I | B50: SERVICIOS DE TRANSPORTE, DE ALMACENAMIENTO Y DE COMUNICACIONES | C50: 3966 | D50: 4217 | E50: 4466 | F50: 4647 | G50: 4650 | H50: 4313 | I50: 3982 | J50: 4445 | K50: 5351 | L50: 6268 | M50: 7097 | N50: 8021 | O50: 8764 | P50: 8637 | Q50: 8843 | R50: 9171 | S50: 9430 | T50: 9401 | U50: 9038 | V50: 9008 | W50: 8884 | X50: 8959 | Y50: 8639 | Z50: 8268 | AA50: 7859 | AB50: 7771 | AC50: 7875 | AD50: 7628 | AE50: 7362
A51: 60 | B51: Transporte ferroviario y automotor y por tuberias | C51: 3081 | D51: 3269 | E51: 3461 | F51: 3565 | G51: 3581 | H51: 3266 | I51: 2984 | J51: 3377 | K51: 4085 | L51: 4869 | M51: 5629 | N51: 6528 | O51: 7212 | P51: 7070 | Q51: 7239 | R51: 7501 | S51: 7737 | T51: 7689 | U51: 7381 | V51: 7294 | W51: 7176 | X51: 7258 | Y51: 6961 | Z51: 6590 | AA51: 6270 | AB51: 6197 | AC51: 6228 | AD51: 5977 | AE51: 5692
A52: 61 | B52: Transporte marítimo y fluvial | C52: 21 | D52: 20 | E52: 17 | F52: 17 | G52: 26 | H52: 17 | I52: 16 | J52: 17 | K52: 21 | L52: 24 | M52: 26 | N52: 35 | O52: 37 | P52: 38 | Q52: 41 | R52: 40 | S52: 37 | T52: 37 | U52: 34 | V52: 36 | W52: 34 | X52: 34 | Y52: 33 | Z52: 35 | AA52: 33 | AB52: 32 | AC52: 38 | AD52: 36 | AE52: 35
A53: 62 | B53: Transporte aéreo de cargas y de pasajeros | C53: 7 | D53: 7 | E53: 8 | F53: 6 | G53: 7 | H53: 8 | I53: 7 | J53: 4 | K53: 7 | L53: 6 | M53: 7 | N53: 6 | O53: 7 | P53: 5 | Q53: 7 | R53: 8 | S53: 9 | T53: 9 | U53: 12 | V53: 13 | W53: 11 | X53: 10 | Y53: 13 | Z53: 16 | AA53: 14 | AB53: 12 | AC53: 10 | AD53: 9 | AE53: 9
A54: 63 | B54: Manipulación de carga, almacenamiento y depósito | C54: 509 | D54: 550 | E54: 583 | F54: 611 | G54: 593 | H54: 602 | I54: 585 | J54: 639 | K54: 781 | L54: 885 | M54: 967 | N54: 1013 | O54: 1086 | P54: 1135 | Q54: 1180 | R54: 1256 | S54: 1294 | T54: 1319 | U54: 1292 | V54: 1334 | W54: 1329 | X54: 1336 | Y54: 1327 | Z54: 1331 | AA54: 1252 | AB54: 1233 | AC54: 1285 | AD54: 1305 | AE54: 1331
A55: 64 | B55: Telecomunicaciones y correos | C55: 348 | D55: 371 | E55: 397 | F55: 448 | G55: 443 | H55: 420 | I55: 390 | J55: 408 | K55: 457 | L55: 484 | M55: 468 | N55: 439 | O55: 422 | P55: 389 | Q55: 376 | R55: 366 | S55: 353 | T55: 347 | U55: 319 | V55: 331 | W55: 334 | X55: 321 | Y55: 305 | Z55: 296 | AA55: 290 | AB55: 297 | AC55: 314 | AD55: 301 | AE55: 295
A56: J | B56: INTERMEDIACION FINANCIERA Y OTROS SERVICIOS FINANCIEROS | C56: 642 | D56: 671 | E56: 702 | F56: 682 | G56: 653 | H56: 634 | I56: 594 | J56: 626 | K56: 773 | L56: 834 | M56: 888 | N56: 933 | O56: 985 | P56: 1010 | Q56: 1013 | R56: 1051 | S56: 1066 | T56: 1097 | U56: 1068 | V56: 1111 | W56: 1131 | X56: 1134 | Y56: 1133 | Z56: 1104 | AA56: 1060 | AB56: 1053 | AC56: 1059 | AD56: 1054 | AE56: 1058
A57: 65 | B57: Intermediacion financiera y otros servicios financieros | C57: 251 | D57: 259 | E57: 273 | F57: 257 | G57: 238 | H57: 229 | I57: 209 | J57: 208 | K57: 219 | L57: 238 | M57: 243 | N57: 243 | O57: 254 | P57: 250 | Q57: 238 | R57: 256 | S57: 255 | T57: 257 | U57: 245 | V57: 254 | W57: 246 | X57: 244 | Y57: 240 | Z57: 226 | AA57: 212 | AB57: 211 | AC57: 208 | AD57: 210 | AE57: 201
A58: 66 | B58: Seguros | C58: 113 | D58: 124 | E58: 132 | F58: 136 | G58: 133 | H58: 121 | I58: 120 | J58: 124 | K58: 136 | L58: 140 | M58: 144 | N58: 138 | O58: 129 | P58: 123 | Q58: 118 | R58: 115 | S58: 119 | T58: 117 | U58: 109 | V58: 112 | W58: 107 | X58: 105 | Y58: 101 | Z58: 97 | AA58: 96 | AB58: 100 | AC58: 99 | AD58: 93 | AE58: 94
A59: 67 | B59: Servicios auxiliares a la actividad financiera | C59: 278 | D59: 288 | E59: 297 | F59: 289 | G59: 282 | H59: 284 | I59: 265 | J59: 294 | K59: 418 | L59: 456 | M59: 501 | N59: 552 | O59: 602 | P59: 637 | Q59: 657 | R59: 680 | S59: 692 | T59: 723 | U59: 714 | V59: 745 | W59: 778 | X59: 785 | Y59: 792 | Z59: 781 | AA59: 752 | AB59: 742 | AC59: 752 | AD59: 751 | AE59: 763
A60: K | B60: SERVICIOS INMOBILIARIOS, EMPRESARIALES Y DE ALQUILER | C60: 15513 | D60: 15685 | E60: 15949 | F60: 16192 | G60: 15879 | H60: 15576 | I60: 15084 | J60: 15869 | K60: 17766 | L60: 18819 | M60: 19552 | N60: 19911 | O60: 20175 | P60: 19823 | Q60: 19644 | R60: 19467 | S60: 19038 | T60: 18525 | U60: 18027 | V60: 17696 | W60: 17323 | X60: 17054 | Y60: 16499 | Z60: 15747 | AA60: 15023 | AB60: 14732 | AC60: 14466 | AD60: 13790 | AE60: 13191
A61: 70 | B61: Servicios inmobiliarios | C61: 9831 | D61: 9789 | E61: 9788 | F61: 9883 | G61: 9623 | H61: 9521 | I61: 9273 | J61: 9608 | K61: 10373 | L61: 10683 | M61: 10933 | N61: 10961 | O61: 10959 | P61: 10794 | Q61: 10652 | R61: 10488 | S61: 10234 | T61: 9895 | U61: 9594 | V61: 9365 | W61: 9111 | X61: 8895 | Y61: 8503 | Z61: 8102 | AA61: 7726 | AB61: 7455 | AC61: 7062 | AD61: 6581 | AE61: 6323
A62: 71 | B62: Alquiler de equipo de transporte y de maquinaria | C62: 180 | D62: 187 | E62: 197 | F62: 195 | G62: 188 | H62: 179 | I62: 160 | J62: 171 | K62: 221 | L62: 239 | M62: 258 | N62: 256 | O62: 282 | P62: 275 | Q62: 247 | R62: 248 | S62: 251 | T62: 242 | U62: 237 | V62: 243 | W62: 245 | X62: 259 | Y62: 245 | Z62: 233 | AA62: 209 | AB62: 198 | AC62: 205 | AD62: 204 | AE62: 195
A63: 72 | B63: Actividades de informática | C63: 97 | D63: 119 | E63: 131 | F63: 132 | G63: 144 | H63: 151 | I63: 141 | J63: 163 | K63: 229 | L63: 281 | M63: 311 | N63: 341 | O63: 372 | P63: 380 | Q63: 411 | R63: 424 | S63: 402 | T63: 401 | U63: 424 | V63: 434 | W63: 475 | X63: 472 | Y63: 491 | Z63: 493 | AA63: 487 | AB63: 534 | AC63: 568 | AD63: 580 | AE63: 581
A64: 73 | B64: Investigación y desarrollo | C64: 25 | D64: 22 | E64: 21 | F64: 23 | G64: 20 | H64: 25 | I64: 23 | J64: 28 | K64: 34 | L64: 38 | M64: 43 | N64: 41 | O64: 50 | P64: 46 | Q64: 46 | R64: 46 | S64: 49 | T64: 53 | U64: 56 | V64: 59 | W64: 60 | X64: 57 | Y64: 61 | Z64: 59 | AA64: 57 | AB64: 62 | AC64: 70 | AD64: 75 | AE64: 72
A65: 74 | B65: Servicios jurídicos, contables y otros servicios a empresas | C65: 5358 | D65: 5543 | E65: 5782 | F65: 5917 | G65: 5866 | H65: 5666 | I65: 5451 | J65: 5858 | K65: 6868 | L65: 7540 | M65: 7971 | N65: 8276 | O65: 8470 | P65: 8282 | Q65: 8245 | R65: 8221 | S65: 8065 | T65: 7899 | U65: 7680 | V65: 7561 | W65: 7399 | X65: 7341 | Y65: 7172 | Z65: 6837 | AA65: 6520 | AB65: 6461 | AC65: 6540 | AD65: 6331 | AE65: 6000
A66: 75 | B66: Agencias de empleo eventual | C66: 22 | D66: 25 | E66: 30 | F66: 42 | G66: 38 | H66: 34 | I66: 36 | J66: 41 | K66: 41 | L66: 38 | M66: 36 | N66: 36 | O66: 42 | P66: 46 | Q66: 43 | R66: 40 | S66: 37 | T66: 35 | U66: 36 | V66: 34 | W66: 33 | X66: 30 | Y66: 27 | Z66: 23 | AA66: 24 | AB66: 22 | AC66: 21 | AD66: 19 | AE66: 20
A67: M | B67: ENSEÑANZA | C67: 918 | D67: 1069 | E67: 1115 | F67: 1151 | G67: 1092 | H67: 1094 | I67: 1087 | J67: 1113 | K67: 1199 | L67: 1263 | M67: 1325 | N67: 1357 | O67: 1379 | P67: 1392 | Q67: 1401 | R67: 1401 | S67: 1409 | T67: 1388 | U67: 1377 | V67: 1360 | W67: 1376 | X67: 1363 | Y67: 1358 | Z67: 1348 | AA67: 1263 | AB67: 1249 | AC67: 1282 | AD67: 1327 | AE67: 1242
A68: 80 | B68: Enseñanza | C68: 918 | D68: 1069 | E68: 1115 | F68: 1151 | G68: 1092 | H68: 1094 | I68: 1087 | J68: 1113 | K68: 1199 | L68: 1263 | M68: 1325 | N68: 1357 | O68: 1379 | P68: 1392 | Q68: 1401 | R68: 1401 | S68: 1409 | T68: 1388 | U68: 1377 | V68: 1360 | W68: 1376 | X68: 1363 | Y68: 1358 | Z68: 1348 | AA68: 1263 | AB68: 1249 | AC68: 1282 | AD68: 1327 | AE68: 1242
A69: N | B69: SERVICIOS SOCIALES Y DE SALUD | C69: 2789 | D69: 2857 | E69: 2978 | F69: 3054 | G69: 3045 | H69: 3051 | I69: 2973 | J69: 3086 | K69: 3413 | L69: 3746 | M69: 4004 | N69: 4279 | O69: 4535 | P69: 4691 | Q69: 4786 | R69: 4946 | S69: 4959 | T69: 5015 | U69: 5032 | V69: 5147 | W69: 5155 | X69: 5203 | Y69: 5191 | Z69: 5105 | AA69: 4941 | AB69: 4937 | AC69: 5055 | AD69: 4884 | AE69: 4702
A70: 85 | B70: Servicios sociales y de salud | C70: 2789 | D70: 2857 | E70: 2978 | F70: 3054 | G70: 3045 | H70: 3051 | I70: 2973 | J70: 3086 | K70: 3413 | L70: 3746 | M70: 4004 | N70: 4279 | O70: 4535 | P70: 4691 | Q70: 4786 | R70: 4946 | S70: 4959 | T70: 5015 | U70: 5032 | V70: 5147 | W70: 5155 | X70: 5203 | Y70: 5191 | Z70: 5105 | AA70: 4941 | AB70: 4937 | AC70: 5055 | AD70: 4884 | AE70: 4702
A71: O | B71: SERVICIOS COMUNITARIOS, SOCIALES Y PERSONALES N.C.P. | C71: 5819 | D71: 5869 | E71: 5895 | F71: 5904 | G71: 5730 | H71: 5613 | I71: 5419 | J71: 5847 | K71: 7384 | L71: 7902 | M71: 8206 | N71: 8236 | O71: 8361 | P71: 8316 | Q71: 8403 | R71: 8381 | S71: 8224 | T71: 7943 | U71: 7784 | V71: 7767 | W71: 7704 | X71: 7546 | Y71: 7235 | Z71: 6848 | AA71: 6341 | AB71: 6144 | AC71: 6241 | AD71: 6034 | AE71: 5763
A72: 90 | B72: Eliminación de desperdicios | C72: 131 | D72: 123 | E72: 113 | F72: 110 | G72: 103 | H72: 99 | I72: 88 | J72: 96 | K72: 102 | L72: 102 | M72: 111 | N72: 111 | O72: 110 | P72: 108 | Q72: 114 | R72: 115 | S72: 112 | T72: 113 | U72: 120 | V72: 122 | W72: 119 | X72: 127 | Y72: 134 | Z72: 127 | AA72: 129 | AB72: 140 | AC72: 138 | AD72: 133 | AE72: 134
A73: 91 | B73: Servicios de organizaciones empresariales | C73: 2058 | D73: 2162 | E73: 2246 | F73: 2353 | G73: 2341 | H73: 2422 | I73: 2407 | J73: 2467 | K73: 2548 | L73: 2628 | M73: 2690 | N73: 2750 | O73: 2778 | P73: 2782 | Q73: 2808 | R73: 2844 | S73: 2853 | T73: 2832 | U73: 2803 | V73: 2802 | W73: 2819 | X73: 2794 | Y73: 2767 | Z73: 2714 | AA73: 2631 | AB73: 2582 | AC73: 2564 | AD73: 2489 | AE73: 2422
A74: 92 | B74: Servicios culturales, deportivos y de esparcimiento | C74: 1163 | D74: 1153 | E74: 1132 | F74: 1135 | G74: 1144 | H74: 1117 | I74: 1099 | J74: 1186 | K74: 1485 | L74: 1626 | M74: 1755 | N74: 1858 | O74: 2012 | P74: 2078 | Q74: 2151 | R74: 2232 | S74: 2261 | T74: 2274 | U74: 2292 | V74: 2342 | W74: 2344 | X74: 2323 | Y74: 2271 | Z74: 2180 | AA74: 2025 | AB74: 1977 | AC74: 2065 | AD74: 2009 | AE74: 1928
A75: 93 | B75: Servicios n.c.p. | C75: 2467 | D75: 2431 | E75: 2404 | F75: 2306 | G75: 2142 | H75: 1975 | I75: 1825 | J75: 2098 | K75: 3249 | L75: 3546 | M75: 3650 | N75: 3517 | O75: 3461 | P75: 3348 | Q75: 3330 | R75: 3190 | S75: 2998 | T75: 2724 | U75: 2569 | V75: 2501 | W75: 2422 | X75: 2302 | Y75: 2063 | Z75: 1827 | AA75: 1556 | AB75: 1445 | AC75: 1474 | AD75: 1403 | AE75: 1279
B76: TOTAL | C76: 72870 | D76: 73913 | E76: 74581 | F76: 74914 | G76: 72722 | H76: 69796 | I76: 67125 | J76: 72580 | K76: 84408 | L76: 92019 | M76: 98491 | N76: 103524 | O76: 107767 | P76: 107761 | Q76: 109195 | R76: 111002 | S76: 111325 | T76: 110531 | U76: 109564 | V76: 109519 | W76: 109171 | X76: 109062 | Y76: 106086 | Z76: 102705 | AA76: 98354 | AB76: 98928 | AC76: 102380 | AD76: 100504 | AE76: 97912
B77: serie anterior
A78: Notas:
A79: 1 - Las empresas se encuentran clasificadas por provincia según las zonas donde declaran que trabajan las personas.
A80: 2 - Las firmas con participación accionaria privada y estatal se incluye dentro del sector privado
A81: 3 - s/d : Dato no publicado para resguardar el secreto estadístico de las firmas
A82: Fuente: STEySS - Dirección Nacional de Estudios y Estadísticas Laborales - Observatorio de Empleo y Dinámica Empresarial, en base a SIPA.

Sheet Catamarca
D1: Volver al índice
A2: CATAMARCA
A3: Empresas del sector privado por rama de actividad - Activas en cada año
B4: Ramas de actividad | C4: 1996 | D4: 1997 | E4: 1998 | F4: 1999 | G4: 2000 | H4: 2001 | I4: 2002 | J4: 2003 | K4: 2004 | L4: 2005 | M4: 2006 | N4: 2007 | O4: 2008 | P4: 2009 | Q4: 2010 | R4: 2011 | S4: 2012 | T4: 2013 | U4: 2014 | V4: 2015 | W4: 2016 | X4: 2017 | Y4: 2018 | Z4: 2019 | AA4: 2020 | AB4: 2021 | AC4: 2022 | AD4: 2023 | AE4: 2024
D5: 2º Trim 1996 | F5: 3º Trim 1996 | H5: 4º Trim 1996 | J5: 1º Trim 1997 | L5: 2º Trim 1997 | N5: 3º Trim 1997 | P5: 4º Trim 1997 | R5: 1º Trim 1998
A6: A | B6: AGRICULTURA, GANADERIA, CAZA Y SILVICULTURA | C6: 263 | D6: 278 | E6: 298 | F6: 312 | G6: 298 | H6: 297 | I6: 266 | J6: 266 | K6: 271 | L6: 285 | M6: 310 | N6: 324 | O6: 328 | P6: 320 | Q6: 320 | R6: 322 | S6: 302 | T6: 309 | U6: 297 | V6: 290 | W6: 274 | X6: 284 | Y6: 261 | Z6: 249 | AA6: 239 | AB6: 241 | AC6: 249 | AD6: 240 | AE6: 225
A7: 1 | B7: Agricultura y ganaderia | C7: 257 | D7: 272 | E7: 290 | F7: 304 | G7: 291 | H7: 290 | I7: 259 | J7: 260 | K7: 265 | L7: 278 | M7: 303 | N7: 317 | O7: 321 | P7: 314 | Q7: 314 | R7: 316 | S7: 295 | T7: 301 | U7: 290 | V7: 283 | W7: 268 | X7: 279 | Y7: 257 | Z7: s.d. | AA7: s.d. | AB7: s.d. | AC7: s.d. | AD7: 235 | AE7: 221
A8: 2 | B8: Silvicultura, extracción de madera | C8: 6 | D8: 6 | E8: 8 | F8: 8 | G8: 7 | H8: 7 | I8: 7 | J8: 6 | K8: 6 | L8: 7 | M8: 7 | N8: 7 | O8: 7 | P8: 6 | Q8: 6 | R8: 6 | S8: 7 | T8: 8 | U8: 7 | V8: 7 | W8: 6 | X8: 5 | Y8: 4 | Z8: s.d. | AA8: s.d. | AB8: s.d. | AC8: s.d. | AD8: 5 | AE8: 4
A9: B | B9: PESCA Y SERVICIOS CONEXOS | C9: 0 | D9: 0 | E9: 0 | F9: 0 | G9: 0 | H9: 0 | I9: 0 | J9: 0 | K9: 0 | L9: 0 | M9: 0 | N9: 0 | O9: 0 | P9: 0 | Q9: 0 | R9: 0 | S9: 0 | T9: 0 | U9: 0 | V9: 0 | W9: 0 | X9: 0 | Y9: 0 | Z9: 0 | AA9: 0 | AB9: 0 | AC9: 0 | AD9: 0 | AE9: 0
A10: 5 | B10: Pesca y actividades relacionadas con la pesca | C10: 0 | D10: 0 | E10: 0 | F10: 0 | G10: 0 | H10: 0 | I10: 0 | J10: 0 | K10: 0 | L10: 0 | M10: 0 | N10: 0 | O10: 0 | P10: 0 | Q10: 0 | R10: 0 | S10: 0 | T10: 0 | U10: 0 | V10: 0 | W10: 0 | X10: 0 | Y10: 0 | Z10: 0 | AA10: 0 | AB10: 0 | AC10: 0 | AD10: 0 | AE10: 0
A11: C | B11: EXPLOTACION DE MINAS Y CANTERAS | C11: 19 | D11: 19 | E11: 19 | F11: 22 | G11: 14 | H11: 17 | I11: 11 | J11: 16 | K11: 15 | L11: 17 | M11: 20 | N11: 22 | O11: 24 | P11: 22 | Q11: 22 | R11: 18 | S11: 19 | T11: 21 | U11: 17 | V11: 15 | W11: 13 | X11: 17 | Y11: 18 | Z11: 18 | AA11: 18 | AB11: 18 | AC11: 23 | AD11: 28 | AE11: 31
A12: 11 | B12: Extraccion de petroleo crudo y gas natural | C12: s.d. | D12: s.d. | E12: 7 | F12: 8 | G12: s.d. | H12: s.d. | I12: s.d. | J12: s.d. | K12: s.d. | L12: s.d. | M12: s.d. | N12: s.d. | O12: s.d. | P12: s.d. | Q12: s.d. | R12: s.d. | S12: s.d. | T12: s.d. | U12: s.d. | V12: s.d. | W12: s.d. | X12: s.d. | Y12: s.d. | Z12: s.d. | AA12: s.d. | AB12: s.d. | AC12: s.d. | AD12: s.d. | AE12: s.d.
A13: 13 | B13: Extraccion de minerales metaliferos | C13: s.d. | D13: s.d. | E13: s.d. | F13: s.d. | G13: s.d. | H13: s.d. | I13: s.d. | J13: s.d. | K13: s.d. | L13: s.d. | M13: s.d. | N13: s.d. | O13: 4 | P13: s.d. | Q13: 4 | R13: s.d. | S13: s.d. | T13: s.d. | U13: s.d. | V13: s.d. | W13: s.d. | X13: s.d. | Y13: s.d. | Z13: s.d. | AA13: s.d. | AB13: s.d. | AC13: s.d. | AD13: 7 | AE13: 10
A14: 14 | B14: Explotacion de otras minas y canteras | C14: 13 | D14: 14 | E14: s.d. | F14: s.d. | G14: 9 | H14: 11 | I14: 9 | J14: 13 | K14: 12 | L14: 14 | M14: 16 | N14: 17 | O14: s.d. | P14: 18 | Q14: s.d. | R14: 15 | S14: 16 | T14: 15 | U14: 13 | V14: 13 | W14: 12 | X14: 15 | Y14: 15 | Z14: 12 | AA14: 14 | AB14: 15 | AC14: 18 | AD14: s.d. | AE14: s.d.
A15: D | B15: INDUSTRIA MANUFACTURERA | C15: 253 | D15: 268 | E15: 253 | F15: 256 | G15: 229 | H15: 226 | I15: 208 | J15: 226 | K15: 209 | L15: 222 | M15: 236 | N15: 266 | O15: 257 | P15: 247 | Q15: 260 | R15: 256 | S15: 263 | T15: 261 | U15: 265 | V15: 276 | W15: 264 | X15: 279 | Y15: 256 | Z15: 244 | AA15: 240 | AB15: 246 | AC15: 272 | AD15: 297 | AE15: 272
A16: 15 | B16: Alimentos | C16: 90 | D16: 98 | E16: 104 | F16: 105 | G16: 92 | H16: 88 | I16: 91 | J16: 103 | K16: 95 | L16: 104 | M16: 103 | N16: 117 | O16: 118 | P16: 119 | Q16: 126 | R16: 123 | S16: 125 | T16: 124 | U16: 123 | V16: 133 | W16: 123 | X16: 125 | Y16: 116 | Z16: 111 | AA16: 109 | AB16: 109 | AC16: 122 | AD16: 129 | AE16: 130
A17: 16 | B17: Tabaco | C17: s.d. | D17: s.d. | E17: s.d. | F17: s.d. | G17: s.d. | H17: s.d. | I17: s.d. | J17: s.d. | K17: s.d. | L17: s.d. | M17: s.d. | N17: s.d. | O17: s.d. | P17: s.d. | Q17: s.d. | R17: s.d. | S17: s.d. | T17: s.d. | U17: s.d. | V17: s.d. | W17: s.d. | X17: s.d. | Y17: s.d. | Z17: s.d. | AA17: s.d. | AB17: s.d. | AC17: s.d. | AD17: s.d. | AE17: s.d.
A18: 17 | B18: Productos textiles | C18: 14 | D18: 17 | E18: 15 | F18: 15 | G18: 13 | H18: 13 | I18: 13 | J18: 14 | K18: 13 | L18: 15 | M18: 14 | N18: 14 | O18: 14 | P18: 12 | Q18: 12 | R18: 12 | S18: 9 | T18: 10 | U18: 12 | V18: 11 | W18: 12 | X18: 13 | Y18: 13 | Z18: 15 | AA18: 14 | AB18: 17 | AC18: 20 | AD18: 21 | AE18: 20
A19: 18 | B19: Confecciones | C19: 15 | D19: 16 | E19: 14 | F19: 14 | G19: 14 | H19: 16 | I19: 13 | J19: 15 | K19: 14 | L19: 12 | M19: 13 | N19: 13 | O19: 14 | P19: 9 | Q19: 11 | R19: 12 | S19: 14 | T19: 14 | U19: 14 | V19: 14 | W19: 15 | X19: 13 | Y19: 12 | Z19: 13 | AA19: 12 | AB19: 14 | AC19: 17 | AD19: 18 | AE19: 18
A20: 19 | B20: Calzado y productos de cuero | C20: 6 | D20: 8 | E20: 5 | F20: 5 | G20: 6 | H20: 5 | I20: 5 | J20: 6 | K20: 7 | L20: 6 | M20: 7 | N20: 10 | O20: 9 | P20: 7 | Q20: 9 | R20: 10 | S20: 11 | T20: 6 | U20: 6 | V20: 4 | W20: 4 | X20: 5 | Y20: 5 | Z20: 5 | AA20: 5 | AB20: 6 | AC20: 8 | AD20: 8 | AE20: 7
A21: 20 | B21: Madera | C21: 11 | D21: 10 | E21: 11 | F21: 7 | G21: 7 | H21: 7 | I21: 7 | J21: 8 | K21: 7 | L21: 6 | M21: 9 | N21: 11 | O21: 12 | P21: 9 | Q21: 9 | R21: 8 | S21: 9 | T21: 9 | U21: 9 | V21: 9 | W21: 8 | X21: 8 | Y21: 8 | Z21: 7 | AA21: 5 | AB21: 5 | AC21: 7 | AD21: 5 | AE21: 6
A22: 21 | B22: Papel | C22: 5 | D22: 7 | E22: 6 | F22: 5 | G22: 4 | H22: s.d. | I22: s.d. | J22: 6 | K22: 4 | L22: s.d. | M22: s.d. | N22: s.d. | O22: s.d. | P22: s.d. | Q22: s.d. | R22: s.d. | S22: 5 | T22: 4 | U22: 4 | V22: 4 | W22: 4 | X22: 4 | Y22: 4 | Z22: 5 | AA22: s.d. | AB22: 4 | AC22: s.d. | AD22: s.d. | AE22: s.d.
A23: 22 | B23: Edición | C23: 18 | D23: 17 | E23: 17 | F23: 18 | G23: 18 | H23: 15 | I23: 12 | J23: 15 | K23: 13 | L23: 12 | M23: 12 | N23: 16 | O23: 20 | P23: 19 | Q23: 20 | R23: 19 | S23: 18 | T23: 22 | U23: 22 | V23: 23 | W23: 24 | X23: 25 | Y23: 19 | Z23: 15 | AA23: 15 | AB23: 17 | AC23: 16 | AD23: 20 | AE23: 18
A24: 23 | B24: Productos de petróleo | C24: s.d. | D24: s.d. | E24: s.d. | F24: s.d. | G24: s.d. | H24: s.d. | I24: s.d. | J24: s.d. | K24: s.d. | L24: s.d. | M24: s.d. | N24: s.d. | O24: s.d. | P24: s.d. | Q24: s.d. | R24: s.d. | S24: s.d. | T24: s.d. | U24: s.d. | V24: s.d. | W24: s.d. | X24: s.d. | Y24: s.d. | Z24: s.d. | AA24: s.d. | AB24: s.d. | AC24: s.d. | AD24: s.d. | AE24: s.d.
A25: 24 | B25: Productos químicos | C25: 28 | D25: 24 | E25: 20 | F25: 23 | G25: 21 | H25: 25 | I25: 20 | J25: 20 | K25: 18 | L25: 22 | M25: 23 | N25: 25 | O25: 21 | P25: 19 | Q25: 22 | R25: 19 | S25: 22 | T25: 22 | U25: 24 | V25: 23 | W25: 22 | X25: 21 | Y25: 21 | Z25: 19 | AA25: 19 | AB25: 21 | AC25: 18 | AD25: 19 | AE25: 16
A26: 25 | B26: Productos de caucho y plástico | C26: 8 | D26: 8 | E26: 5 | F26: 7 | G26: 5 | H26: 4 | I26: 4 | J26: s.d. | K26: s.d. | L26: s.d. | M26: 4 | N26: 5 | O26: s.d. | P26: 6 | Q26: 5 | R26: 4 | S26: 5 | T26: s.d. | U26: s.d. | V26: 4 | W26: s.d. | X26: s.d. | Y26: s.d. | Z26: s.d. | AA26: s.d. | AB26: s.d. | AC26: s.d. | AD26: s.d. | AE26: s.d.
A27: 26 | B27: Otros minerales no metálicos | C27: 9 | D27: 11 | E27: 10 | F27: 10 | G27: 9 | H27: 10 | I27: 7 | J27: 9 | K27: 7 | L27: 8 | M27: 7 | N27: 9 | O27: 7 | P27: 8 | Q27: 9 | R27: 12 | S27: 11 | T27: 12 | U27: 11 | V27: 10 | W27: 11 | X27: 13 | Y27: 11 | Z27: 11 | AA27: 10 | AB27: 11 | AC27: 10 | AD27: 10 | AE27: 9
A28: 27 | B28: Metales comunes | C28: s.d. | D28: s.d. | E28: s.d. | F28: s.d. | G28: s.d. | H28: s.d. | I28: s.d. | J28: s.d. | K28: s.d. | L28: s.d. | M28: s.d. | N28: s.d. | O28: s.d. | P28: s.d. | Q28: s.d. | R28: s.d. | S28: s.d. | T28: s.d. | U28: 4 | V28: 4 | W28: s.d. | X28: s.d. | Y28: s.d. | Z28: s.d. | AA28: s.d. | AB28: s.d. | AC28: s.d. | AD28: s.d. | AE28: s.d.
A29: 28 | B29: Otros productos de metal | C29: 13 | D29: 12 | E29: 11 | F29: 11 | G29: 10 | H29: 11 | I29: 8 | J29: 7 | K29: 7 | L29: 9 | M29: 11 | N29: 9 | O29: 8 | P29: 9 | Q29: 9 | R29: 9 | S29: 9 | T29: 9 | U29: 9 | V29: 10 | W29: 9 | X29: 11 | Y29: 10 | Z29: 8 | AA29: 12 | AB29: 10 | AC29: 18 | AD29: 22 | AE29: 16
A30: 29 | B30: Maquinaria y equipo | C30: 13 | D30: 13 | E30: 12 | F30: 13 | G30: 13 | H30: 16 | I30: 14 | J30: 11 | K30: 11 | L30: 9 | M30: 11 | N30: 10 | O30: 10 | P30: 9 | Q30: 9 | R30: 12 | S30: 11 | T30: 8 | U30: 8 | V30: 8 | W30: 7 | X30: 8 | Y30: 7 | Z30: 9 | AA30: 8 | AB30: 6 | AC30: 7 | AD30: 9 | AE30: 7
A31: 30 | B31: Maquinaria de oficina | C31: s.d. | D31: s.d. | E31: s.d. | F31: s.d. | G31: s.d. | H31: s.d. | I31: s.d. | J31: s.d. | K31: s.d. | L31: s.d. | M31: s.d. | N31: s.d. | O31: s.d. | P31: s.d. | Q31: s.d. | R31: s.d. | S31: s.d. | T31: s.d. | U31: s.d. | V31: s.d. | W31: s.d. | X31: s.d. | Y31: s.d. | Z31: s.d. | AA31: s.d. | AB31: s.d. | AC31: s.d. | AD31: s.d. | AE31: s.d.
A32: 31 | B32: Aparatos eléctricos | C32: s.d. | D32: s.d. | E32: s.d. | F32: s.d. | G32: s.d. | H32: s.d. | I32: s.d. | J32: s.d. | K32: s.d. | L32: s.d. | M32: s.d. | N32: s.d. | O32: s.d. | P32: s.d. | Q32: s.d. | R32: s.d. | S32: s.d. | T32: s.d. | U32: s.d. | V32: s.d. | W32: s.d. | X32: 4 | Y32: 6 | Z32: 5 | AA32: 5 | AB32: 4 | AC32: 4 | AD32: 4 | AE32: s.d.
A33: 32 | B33: Radio y televisión | C33: s.d. | D33: s.d. | E33: s.d. | F33: s.d. | G33: s.d. | H33: s.d. | I33: s.d. | J33: s.d. | K33: s.d. | L33: s.d. | M33: s.d. | N33: s.d. | O33: s.d. | P33: s.d. | Q33: s.d. | R33: s.d. | S33: s.d. | T33: s.d. | U33: s.d. | V33: s.d. | W33: s.d. | X33: s.d. | Y33: s.d. | Z33: s.d. | AA33: s.d. | AB33: s.d. | AC33: s.d. | AD33: s.d. | AE33: s.d.
A34: 33 | B34: Instrumentos médicos | C34: s.d. | D34: s.d. | E34: s.d. | F34: s.d. | G34: s.d. | H34: s.d. | I34: s.d. | J34: s.d. | K34: s.d. | L34: s.d. | M34: s.d. | N34: s.d. | O34: s.d. | P34: s.d. | Q34: s.d. | R34: s.d. | S34: s.d. | T34: s.d. | U34: s.d. | V34: s.d. | W34: s.d. | X34: s.d. | Y34: s.d. | Z34: s.d. | AA34: s.d. | AB34: s.d. | AC34: s.d. | AD34: s.d. | AE34: s.d.
A35: 34 | B35: Automotores | C35: s.d. | D35: s.d. | E35: s.d. | F35: s.d. | G35: s.d. | H35: s.d. | I35: s.d. | J35: s.d. | K35: s.d. | L35: s.d. | M35: s.d. | N35: s.d. | O35: s.d. | P35: s.d. | Q35: s.d. | R35: s.d. | S35: s.d. | T35: s.d. | U35: s.d. | V35: s.d. | W35: s.d. | X35: s.d. | Y35: s.d. | Z35: s.d. | AA35: s.d. | AB35: s.d. | AC35: s.d. | AD35: s.d. | AE35: s.d.
A36: 35 | B36: Otros equipo de transporte | C36: s.d. | D36: s.d. | E36: s.d. | F36: s.d. | G36: s.d. | H36: s.d. | I36: s.d. | J36: s.d. | K36: s.d. | L36: s.d. | M36: s.d. | N36: s.d. | O36: s.d. | P36: s.d. | Q36: s.d. | R36: s.d. | S36: s.d. | T36: s.d. | U36: s.d. | V36: s.d. | W36: s.d. | X36: s.d. | Y36: s.d. | Z36: s.d. | AA36: s.d. | AB36: s.d. | AC36: s.d. | AD36: 4 | AE36: s.d.
A37: 36 | B37: Muebles | C37: 12 | D37: 13 | E37: 11 | F37: 10 | G37: 8 | H37: 5 | I37: 4 | J37: s.d. | K37: 5 | L37: 7 | M37: 11 | N37: 13 | O37: 12 | P37: 11 | Q37: 8 | R37: 5 | S37: 5 | T37: 8 | U37: 9 | V37: 12 | W37: 13 | X37: 14 | Y37: 15 | Z37: 11 | AA37: 12 | AB37: 11 | AC37: 12 | AD37: 15 | AE37: 10
A38: 37 | B38: Reciclamiento de desperdicios y desechos | C38: s.d. | D38: s.d. | E38: s.d. | F38: s.d. | G38: s.d. | H38: s.d. | I38: s.d. | J38: s.d. | K38: s.d. | L38: s.d. | M38: s.d. | N38: s.d. | O38: s.d. | P38: s.d. | Q38: s.d. | R38: s.d. | S38: s.d. | T38: s.d. | U38: s.d. | V38: s.d. | W38: s.d. | X38: s.d. | Y38: s.d. | Z38: s.d. | AA38: s.d. | AB38: s.d. | AC38: s.d. | AD38: s.d. | AE38: s.d.
A39: E | B39: ELECTRICIDAD, GAS Y AGUA | C39: 4 | D39: 4 | E39: 6 | F39: 6 | G39: 7 | H39: 6 | I39: 7 | J39: 6 | K39: 7 | L39: 6 | M39: 6 | N39: 6 | O39: 7 | P39: 9 | Q39: 9 | R39: 10 | S39: 9 | T39: 9 | U39: 8 | V39: 8 | W39: 9 | X39: 11 | Y39: 11 | Z39: 11 | AA39: 9 | AB39: 11 | AC39: 10 | AD39: 11 | AE39: 11
A40: 40 | B40: Electricidad, gas y agua | C40: s.d. | D40: s.d. | E40: s.d. | F40: s.d. | G40: s.d. | H40: s.d. | I40: s.d. | J40: s.d. | K40: s.d. | L40: s.d. | M40: s.d. | N40: s.d. | O40: s.d. | P40: s.d. | Q40: s.d. | R40: s.d. | S40: s.d. | T40: s.d. | U40: s.d. | V40: s.d. | W40: s.d. | X40: s.d. | Y40: s.d. | Z40: s.d. | AA40: s.d. | AB40: s.d. | AC40: s.d. | AD40: s.d. | AE40: s.d.
A41: 41 | B41: Captación, depuración y distribución de agua | C41: s.d. | D41: s.d. | E41: s.d. | F41: s.d. | G41: s.d. | H41: s.d. | I41: s.d. | J41: s.d. | K41: s.d. | L41: s.d. | M41: s.d. | N41: s.d. | O41: s.d. | P41: s.d. | Q41: s.d. | R41: s.d. | S41: s.d. | T41: s.d. | U41: s.d. | V41: s.d. | W41: s.d. | X41: s.d. | Y41: s.d. | Z41: s.d. | AA41: s.d. | AB41: s.d. | AC41: s.d. | AD41: s.d. | AE41: s.d.
A42: F | B42: CONSTRUCCION | C42: 110 | D42: 113 | E42: 114 | F42: 107 | G42: 95 | H42: 84 | I42: 78 | J42: 93 | K42: 109 | L42: 139 | M42: 170 | N42: 195 | O42: 216 | P42: 190 | Q42: 195 | R42: 194 | S42: 208 | T42: 217 | U42: 210 | V42: 210 | W42: 206 | X42: 240 | Y42: 212 | Z42: 201 | AA42: 204 | AB42: 232 | AC42: 279 | AD42: 281 | AE42: 280
A43: 45 | B43: Construccion | C43: 110 | D43: 113 | E43: 114 | F43: 107 | G43: 95 | H43: 84 | I43: 78 | J43: 93 | K43: 109 | L43: 139 | M43: 170 | N43: 195 | O43: 216 | P43: 190 | Q43: 195 | R43: 194 | S43: 208 | T43: 217 | U43: 210 | V43: 210 | W43: 206 | X43: 240 | Y43: 212 | Z43: 201 | AA43: 204 | AB43: 232 | AC43: 279 | AD43: 281 | AE43: 280
A44: G | B44: COMERCIO AL POR MAYOR Y AL POR MENOR | C44: 552 | D44: 561 | E44: 574 | F44: 587 | G44: 609 | H44: 611 | I44: 568 | J44: 634 | K44: 716 | L44: 797 | M44: 881 | N44: 926 | O44: 1014 | P44: 1016 | Q44: 1043 | R44: 1098 | S44: 1147 | T44: 1184 | U44: 1195 | V44: 1269 | W44: 1283 | X44: 1336 | Y44: 1290 | Z44: 1202 | AA44: 1135 | AB44: 1156 | AC44: 1317 | AD44: 1425 | AE44: 1342
A45: 50 | B45: Vta y reparación de vehículos. vta por menor de combustible | C45: 78 | D45: 83 | E45: 80 | F45: 85 | G45: 87 | H45: 78 | I45: 73 | J45: 81 | K45: 87 | L45: 100 | M45: 113 | N45: 116 | O45: 126 | P45: 123 | Q45: 129 | R45: 129 | S45: 130 | T45: 133 | U45: 135 | V45: 143 | W45: 156 | X45: 152 | Y45: 143 | Z45: 135 | AA45: 135 | AB45: 143 | AC45: 165 | AD45: 171 | AE45: 166
A46: 51 | B46: Comercio al por mayor | C46: 94 | D46: 104 | E46: 105 | F46: 110 | G46: 97 | H46: 88 | I46: 88 | J46: 99 | K46: 113 | L46: 115 | M46: 115 | N46: 122 | O46: 135 | P46: 123 | Q46: 122 | R46: 133 | S46: 135 | T46: 136 | U46: 144 | V46: 142 | W46: 147 | X46: 159 | Y46: 144 | Z46: 133 | AA46: 138 | AB46: 149 | AC46: 173 | AD46: 188 | AE46: 186
A47: 52 | B47: Comercio al por menor | C47: 380 | D47: 374 | E47: 389 | F47: 392 | G47: 425 | H47: 445 | I47: 407 | J47: 454 | K47: 516 | L47: 582 | M47: 653 | N47: 688 | O47: 753 | P47: 770 | Q47: 792 | R47: 836 | S47: 882 | T47: 915 | U47: 916 | V47: 984 | W47: 980 | X47: 1025 | Y47: 1003 | Z47: 934 | AA47: 862 | AB47: 864 | AC47: 979 | AD47: 1066 | AE47: 990
A48: H | B48: HOTELERIA Y RESTAURANTES | C48: 88 | D48: 90 | E48: 96 | F48: 84 | G48: 81 | H48: 76 | I48: 80 | J48: 89 | K48: 115 | L48: 132 | M48: 156 | N48: 165 | O48: 181 | P48: 185 | Q48: 189 | R48: 206 | S48: 201 | T48: 220 | U48: 219 | V48: 236 | W48: 245 | X48: 252 | Y48: 250 | Z48: 222 | AA48: 195 | AB48: 182 | AC48: 224 | AD48: 241 | AE48: 220
A49: 55 | B49: Servicios de hoteleria y restaurantes | C49: 88 | D49: 90 | E49: 96 | F49: 84 | G49: 81 | H49: 76 | I49: 80 | J49: 89 | K49: 115 | L49: 132 | M49: 156 | N49: 165 | O49: 181 | P49: 185 | Q49: 189 | R49: 206 | S49: 201 | T49: 220 | U49: 219 | V49: 236 | W49: 245 | X49: 252 | Y49: 250 | Z49: 222 | AA49: 195 | AB49: 182 | AC49: 224 | AD49: 241 | AE49: 220
A50: I | B50: SERVICIOS DE TRANSPORTE, DE ALMACENAMIENTO Y DE COMUNICACIONES | C50: 139 | D50: 136 | E50: 138 | F50: 136 | G50: 126 | H50: 124 | I50: 126 | J50: 132 | K50: 144 | L50: 151 | M50: 166 | N50: 174 | O50: 195 | P50: 198 | Q50: 229 | R50: 228 | S50: 233 | T50: 239 | U50: 237 | V50: 235 | W50: 247 | X50: 292 | Y50: 267 | Z50: 246 | AA50: 222 | AB50: 224 | AC50: 234 | AD50: 245 | AE50: 226
A51: 60 | B51: Transporte ferroviario y automotor y por tuberias | C51: 105 | D51: 92 | E51: 87 | F51: 84 | G51: 75 | H51: 69 | I51: 70 | J51: 73 | K51: 80 | L51: 90 | M51: 99 | N51: 104 | O51: 116 | P51: 119 | Q51: 150 | R51: 146 | S51: 153 | T51: 152 | U51: 150 | V51: 149 | W51: 154 | X51: 197 | Y51: 174 | Z51: 159 | AA51: 145 | AB51: 147 | AC51: 159 | AD51: 164 | AE51: 147
A52: 61 | B52: Transporte marítimo y fluvial | C52: s.d. | D52: s.d. | E52: s.d. | F52: s.d. | G52: s.d. | H52: s.d. | I52: s.d. | J52: s.d. | K52: s.d. | L52: s.d. | M52: s.d. | N52: s.d. | O52: s.d. | P52: s.d. | Q52: s.d. | R52: s.d. | S52: s.d. | T52: s.d. | U52: s.d. | V52: s.d. | W52: s.d. | X52: s.d. | Y52: s.d. | Z52: s.d. | AA52: s.d. | AB52: s.d. | AC52: s.d. | AD52: s.d. | AE52: s.d.
A53: 62 | B53: Transporte aéreo de cargas y de pasajeros | C53: s.d. | D53: s.d. | E53: s.d. | F53: s.d. | G53: s.d. | H53: s.d. | I53: s.d. | J53: s.d. | K53: s.d. | L53: s.d. | M53: s.d. | N53: s.d. | O53: s.d. | P53: s.d. | Q53: s.d. | R53: s.d. | S53: s.d. | T53: s.d. | U53: s.d. | V53: s.d. | W53: s.d. | X53: s.d. | Y53: s.d. | Z53: s.d. | AA53: s.d. | AB53: s.d. | AC53: s.d. | AD53: s.d. | AE53: s.d.
A54: 63 | B54: Manipulación de carga, almacenamiento y depósito | C54: 15 | D54: 15 | E54: 19 | F54: 16 | G54: 17 | H54: 19 | I54: 23 | J54: 24 | K54: 30 | L54: 27 | M54: 29 | N54: 30 | O54: 40 | P54: 43 | Q54: 45 | R54: 49 | S54: 47 | T54: 51 | U54: 52 | V54: 51 | W54: 55 | X54: 60 | Y54: 62 | Z54: 59 | AA54: 49 | AB54: 50 | AC54: 49 | AD54: 54 | AE54: 50
A55: 64 | B55: Telecomunicaciones y correos | C55: 16 | D55: 23 | E55: 26 | F55: 32 | G55: 30 | H55: 33 | I55: 31 | J55: 32 | K55: 32 | L55: 31 | M55: 35 | N55: 38 | O55: 37 | P55: 34 | Q55: 31 | R55: 30 | S55: 30 | T55: 32 | U55: 32 | V55: 31 | W55: 35 | X55: 32 | Y55: 28 | Z55: 26 | AA55: 25 | AB55: 24 | AC55: 24 | AD55: 25 | AE55: 27
A56: J | B56: INTERMEDIACION FINANCIERA Y OTROS SERVICIOS FINANCIEROS | C56: 41 | D56: 53 | E56: 54 | F56: 59 | G56: 58 | H56: 59 | I56: 52 | J56: 55 | K56: 47 | L56: 63 | M56: 61 | N56: 71 | O56: 74 | P56: 64 | Q56: 69 | R56: 68 | S56: 71 | T56: 74 | U56: 72 | V56: 73 | W56: 71 | X56: 73 | Y56: 70 | Z56: 67 | AA56: 67 | AB56: 63 | AC56: 60 | AD56: 64 | AE56: 62
A57: 65 | B57: Intermediacion financiera y otros servicios financieros | C57: 17 | D57: 21 | E57: 24 | F57: 21 | G57: 18 | H57: 19 | I57: 19 | J57: 22 | K57: 19 | L57: 29 | M57: 27 | N57: 29 | O57: 32 | P57: 28 | Q57: 32 | R57: 33 | S57: 33 | T57: 33 | U57: 33 | V57: 35 | W57: 35 | X57: 32 | Y57: 32 | Z57: 30 | AA57: 29 | AB57: 27 | AC57: 25 | AD57: 26 | AE57: 25
A58: 66 | B58: Seguros | C58: 18 | D58: 27 | E58: 26 | F58: 33 | G58: 33 | H58: 33 | I58: 27 | J58: 28 | K58: 24 | L58: 29 | M58: 29 | N58: 35 | O58: 32 | P58: 25 | Q58: 26 | R58: 27 | S58: 27 | T58: 27 | U58: 26 | V58: 24 | W58: 24 | X58: 24 | Y58: 22 | Z58: 21 | AA58: 22 | AB58: 21 | AC58: 22 | AD58: 22 | AE58: 22
A59: 67 | B59: Servicios auxiliares a la actividad financiera | C59: 6 | D59: 5 | E59: 4 | F59: 5 | G59: 7 | H59: 7 | I59: 6 | J59: 5 | K59: 4 | L59: 5 | M59: 5 | N59: 7 | O59: 10 | P59: 11 | Q59: 11 | R59: 8 | S59: 11 | T59: 14 | U59: 13 | V59: 14 | W59: 12 | X59: 17 | Y59: 16 | Z59: 16 | AA59: 16 | AB59: 15 | AC59: 13 | AD59: 16 | AE59: 15
A60: K | B60: SERVICIOS INMOBILIARIOS, EMPRESARIALES Y DE ALQUILER | C60: 282 | D60: 296 | E60: 272 | F60: 273 | G60: 274 | H60: 273 | I60: 253 | J60: 273 | K60: 302 | L60: 322 | M60: 342 | N60: 375 | O60: 394 | P60: 395 | Q60: 399 | R60: 413 | S60: 415 | T60: 411 | U60: 418 | V60: 398 | W60: 376 | X60: 412 | Y60: 387 | Z60: 360 | AA60: 336 | AB60: 343 | AC60: 390 | AD60: 460 | AE60: 421
A61: 70 | B61: Servicios inmobiliarios | C61: 144 | D61: 153 | E61: 123 | F61: 114 | G61: 101 | H61: 96 | I61: 95 | J61: 103 | K61: 112 | L61: 108 | M61: 108 | N61: 115 | O61: 121 | P61: 115 | Q61: 115 | R61: 122 | S61: 120 | T61: 113 | U61: 114 | V61: 101 | W61: 101 | X61: 105 | Y61: 98 | Z61: 81 | AA61: 74 | AB61: 73 | AC61: 84 | AD61: 78 | AE61: 79
A62: 71 | B62: Alquiler de equipo de transporte y de maquinaria | C62: 15 | D62: 13 | E62: 15 | F62: 15 | G62: 9 | H62: 9 | I62: 7 | J62: 9 | K62: 13 | L62: 13 | M62: 16 | N62: 19 | O62: 21 | P62: s.d. | Q62: s.d. | R62: 17 | S62: 19 | T62: 19 | U62: 17 | V62: 18 | W62: 17 | X62: s.d. | Y62: s.d. | Z62: s.d. | AA62: s.d. | AB62: s.d. | AC62: 16 | AD62: s.d. | AE62: s.d.
A63: 72 | B63: Actividades de informática | C63: s.d. | D63: s.d. | E63: s.d. | F63: s.d. | G63: s.d. | H63: s.d. | I63: s.d. | J63: s.d. | K63: s.d. | L63: s.d. | M63: s.d. | N63: s.d. | O63: s.d. | P63: 9 | Q63: 10 | R63: s.d. | S63: s.d. | T63: s.d. | U63: s.d. | V63: s.d. | W63: s.d. | X63: 15 | Y63: 15 | Z63: 19 | AA63: 14 | AB63: 19 | AC63: 22 | AD63: 25 | AE63: 26
A64: 73 | B64: Investigación y desarrollo | C64: s.d. | D64: s.d. | E64: s.d. | F64: s.d. | G64: s.d. | H64: s.d. | I64: s.d. | J64: s.d. | K64: s.d. | L64: s.d. | M64: s.d. | N64: s.d. | O64: s.d. | P64: s.d. | Q64: s.d. | R64: s.d. | S64: s.d. | T64: s.d. | U64: s.d. | V64: s.d. | W64: s.d. | X64: s.d. | Y64: s.d. | Z64: s.d. | AA64: s.d. | AB64: s.d. | AC64: s.d. | AD64: s.d. | AE64: s.d.
A65: 74 | B65: Servicios jurídicos, contables y otros servicios a empresas | C65: 119 | D65: 123 | E65: 126 | F65: 133 | G65: 150 | H65: 152 | I65: 139 | J65: 146 | K65: 160 | L65: 180 | M65: 203 | N65: 220 | O65: 231 | P65: 236 | Q65: 241 | R65: 252 | S65: 253 | T65: 260 | U65: 264 | V65: 256 | W65: 239 | X65: 267 | Y65: 252 | Z65: 238 | AA65: 226 | AB65: 226 | AC65: 257 | AD65: 328 | AE65: 285
A66: 75 | B66: Agencias de empleo eventual | C66: s.d. | D66: 5 | E66: 5 | F66: 7 | G66: 9 | H66: 10 | I66: 9 | J66: 10 | K66: 11 | L66: 14 | M66: 9 | N66: 11 | O66: 10 | P66: 11 | Q66: 12 | R66: 11 | S66: 11 | T66: 10 | U66: 12 | V66: 9 | W66: 6 | X66: 8 | Y66: 7 | Z66: 7 | AA66: 7 | AB66: 8 | AC66: s.d. | AD66: 7 | AE66: s.d.
A67: M | B67: ENSEÑANZA | C67: 41 | D67: 43 | E67: 41 | F67: 44 | G67: 37 | H67: 37 | I67: 34 | J67: 38 | K67: 39 | L67: 38 | M67: 47 | N67: 52 | O67: 54 | P67: 53 | Q67: 57 | R67: 57 | S67: 52 | T67: 50 | U67: 50 | V67: 51 | W67: 57 | X67: 60 | Y67: 59 | Z67: 56 | AA67: 52 | AB67: 48 | AC67: 50 | AD67: 65 | AE67: 59
A68: 80 | B68: Enseñanza | C68: 41 | D68: 43 | E68: 41 | F68: 44 | G68: 37 | H68: 37 | I68: 34 | J68: 38 | K68: 39 | L68: 38 | M68: 47 | N68: 52 | O68: 54 | P68: 53 | Q68: 57 | R68: 57 | S68: 52 | T68: 50 | U68: 50 | V68: 51 | W68: 57 | X68: 60 | Y68: 59 | Z68: 56 | AA68: 52 | AB68: 48 | AC68: 50 | AD68: 65 | AE68: 59
A69: N | B69: SERVICIOS SOCIALES Y DE SALUD | C69: 127 | D69: 125 | E69: 131 | F69: 132 | G69: 135 | H69: 151 | I69: 132 | J69: 128 | K69: 127 | L69: 129 | M69: 145 | N69: 151 | O69: 161 | P69: 169 | Q69: 173 | R69: 173 | S69: 179 | T69: 194 | U69: 179 | V69: 188 | W69: 194 | X69: 205 | Y69: 192 | Z69: 189 | AA69: 191 | AB69: 195 | AC69: 210 | AD69: 265 | AE69: 199
A70: 85 | B70: Servicios sociales y de salud | C70: 127 | D70: 125 | E70: 131 | F70: 132 | G70: 135 | H70: 151 | I70: 132 | J70: 128 | K70: 127 | L70: 129 | M70: 145 | N70: 151 | O70: 161 | P70: 169 | Q70: 173 | R70: 173 | S70: 179 | T70: 194 | U70: 179 | V70: 188 | W70: 194 | X70: 205 | Y70: 192 | Z70: 189 | AA70: 191 | AB70: 195 | AC70: 210 | AD70: 265 | AE70: 199
A71: O | B71: SERVICIOS COMUNITARIOS, SOCIALES Y PERSONALES N.C.P. | C71: 215 | D71: 218 | E71: 206 | F71: 190 | G71: 197 | H71: 195 | I71: 183 | J71: 229 | K71: 262 | L71: 294 | M71: 301 | N71: 303 | O71: 297 | P71: 287 | Q71: 304 | R71: 289 | S71: 288 | T71: 268 | U71: 271 | V71: 268 | W71: 257 | X71: 263 | Y71: 261 | Z71: 228 | AA71: 215 | AB71: 206 | AC71: 246 | AD71: 284 | AE71: 242
A72: 90 | B72: Eliminación de desperdicios | C72: 4 | D72: 5 | E72: 4 | F72: s.d. | G72: 5 | H72: 4 | I72: 4 | J72: 4 | K72: 6 | L72: 6 | M72: 7 | N72: 5 | O72: 5 | P72: 5 | Q72: 4 | R72: 5 | S72: 5 | T72: 7 | U72: 7 | V72: 7 | W72: 4 | X72: 4 | Y72: 5 | Z72: 5 | AA72: 4 | AB72: 5 | AC72: 5 | AD72: 6 | AE72: 7
A73: 91 | B73: Servicios de organizaciones empresariales | C73: 100 | D73: 102 | E73: 95 | F73: 96 | G73: 94 | H73: 93 | I73: 91 | J73: 96 | K73: 96 | L73: 102 | M73: 96 | N73: 101 | O73: 102 | P73: 99 | Q73: 101 | R73: 103 | S73: 105 | T73: 104 | U73: 103 | V73: 110 | W73: 106 | X73: 108 | Y73: 113 | Z73: 106 | AA73: 103 | AB73: 105 | AC73: 110 | AD73: 113 | AE73: 111
A74: 92 | B74: Servicios culturales, deportivos y de esparcimiento | C74: 28 | D74: 30 | E74: 29 | F74: s.d. | G74: 17 | H74: 20 | I74: 19 | J74: 26 | K74: 32 | L74: 31 | M74: 35 | N74: 41 | O74: 40 | P74: 40 | Q74: 40 | R74: 48 | S74: 45 | T74: 43 | U74: 46 | V74: 45 | W74: 48 | X74: 53 | Y74: 52 | Z74: 46 | AA74: 38 | AB74: 28 | AC74: 41 | AD74: 54 | AE74: 41
A75: 93 | B75: Servicios n.c.p. | C75: 83 | D75: 81 | E75: 78 | F75: 73 | G75: 81 | H75: 78 | I75: 69 | J75: 103 | K75: 128 | L75: 155 | M75: 163 | N75: 156 | O75: 150 | P75: 143 | Q75: 159 | R75: 133 | S75: 133 | T75: 114 | U75: 115 | V75: 106 | W75: 99 | X75: 98 | Y75: 91 | Z75: 71 | AA75: 70 | AB75: 68 | AC75: 90 | AD75: 111 | AE75: 83
B76: TOTAL | C76: 2134 | D76: 2204 | E76: 2202 | F76: 2208 | G76: 2160 | H76: 2156 | I76: 1998 | J76: 2185 | K76: 2363 | L76: 2595 | M76: 2841 | N76: 3030 | O76: 3202 | P76: 3155 | Q76: 3269 | R76: 3332 | S76: 3387 | T76: 3457 | U76: 3438 | V76: 3517 | W76: 3496 | X76: 3724 | Y76: 3534 | Z76: 3293 | AA76: 3123 | AB76: 3165 | AC76: 3564 | AD76: 3906 | AE76: 3590
A78: Notas:
A79: 1 - Las empresas se encuentran clasificadas por provincia según las zonas donde declaran que trabajan las personas.
A80: 2 - Las firmas con participación accionaria privada y estatal se incluye dentro del sector privado
A81: 3 - s/d : Dato no publicado para resguardar el secreto estadístico de las firmas
A82: Fuente: STEySS - Dirección Nacional de Estudios y Estadísticas Laborales - Observatorio de Empleo y Dinámica Empresarial, en base a SIPA.

Sheet Cordoba
D1: Volver al índice
A2: CORDOBA
A3: Empresas del sector privado por rama de actividad - Activas en cada año
B4: Ramas de actividad | C4: 1996 | D4: 1997 | E4: 1998 | F4: 1999 | G4: 2000 | H4: 2001 | I4: 2002 | J4: 2003 | K4: 2004 | L4: 2005 | M4: 2006 | N4: 2007 | O4: 2008 | P4: 2009 | Q4: 2010 | R4: 2011 | S4: 2012 | T4: 2013 | U4: 2014 | V4: 2015 | W4: 2016 | X4: 2017 | Y4: 2018 | Z4: 2019 | AA4: 2020 | AB4: 2021 | AC4: 2022 | AD4: 2023 | AE4: 2024
D5: 2º Trim 1996 | F5: 3º Trim 1996 | H5: 4º Trim 1996 | J5: 1º Trim 1997 | L5: 2º Trim 1997 | N5: 3º Trim 1997 | P5: 4º Trim 1997 | R5: 1º Trim 1998
A6: A | B6: AGRICULTURA, GANADERIA, CAZA Y SILVICULTURA | C6: 7134 | D6: 7115 | E6: 7035 | F6: 6922 | G6: 6764 | H6: 6785 | I6: 6975 | J6: 7611 | K6: 8159 | L6: 8648 | M6: 8910 | N6: 9151 | O6: 9254 | P6: 9123 | Q6: 9085 | R6: 9317 | S6: 9151 | T6: 8978 | U6: 8868 | V6: 8606 | W6: 8526 | X6: 8487 | Y6: 8433 | Z6: 8519 | AA6: 8574 | AB6: 8794 | AC6: 8950 | AD6: 8784 | AE6: 8606
A7: 1 | B7: Agricultura y ganaderia | C7: 7118 | D7: 7098 | E7: 7018 | F7: 6906 | G7: 6750 | H7: 6770 | I7: 6959 | J7: 7590 | K7: 8133 | L7: 8620 | M7: 8882 | N7: 9119 | O7: 9222 | P7: 9095 | Q7: 9062 | R7: 9296 | S7: 9131 | T7: 8957 | U7: 8845 | V7: 8585 | W7: 8504 | X7: 8463 | Y7: 8412 | Z7: 8498 | AA7: 8558 | AB7: 8773 | AC7: 8929 | AD7: 8768 | AE7: 8587
A8: 2 | B8: Silvicultura, extracción de madera | C8: 16 | D8: 17 | E8: 17 | F8: 16 | G8: 14 | H8: 15 | I8: 16 | J8: 21 | K8: 26 | L8: 28 | M8: 28 | N8: 32 | O8: 32 | P8: 28 | Q8: 23 | R8: 21 | S8: 20 | T8: 21 | U8: 23 | V8: 21 | W8: 22 | X8: 24 | Y8: 21 | Z8: 21 | AA8: 16 | AB8: 21 | AC8: 21 | AD8: 16 | AE8: 19
A9: B | B9: PESCA Y SERVICIOS CONEXOS | C9: 10 | D9: 12 | E9: 10 | F9: 7 | G9: 4 | H9: 4 | I9: 4 | J9: 4 | K9: s.d. | L9: 4 | M9: 5 | N9: 4 | O9: 4 | P9: 9 | Q9: s.d. | R9: 4 | S9: 4 | T9: 4 | U9: 4 | V9: 4 | W9: 4 | X9: 4 | Y9: s.d. | Z9: s.d. | AA9: s.d. | AB9: 5 | AC9: 5 | AD9: 5 | AE9: 4
A10: 5 | B10: Pesca y actividades relacionadas con la pesca | C10: 10 | D10: 12 | E10: 10 | F10: 7 | G10: 4 | H10: 4 | I10: 4 | J10: 4 | K10: s.d. | L10: 4 | M10: 5 | N10: 4 | O10: 4 | P10: 9 | Q10: s.d. | R10: 4 | S10: 4 | T10: 4 | U10: 4 | V10: 4 | W10: 4 | X10: 4 | Y10: s.d. | Z10: s.d. | AA10: s.d. | AB10: 5 | AC10: 5 | AD10: 5 | AE10: 4
A11: C | B11: EXPLOTACION DE MINAS Y CANTERAS | C11: 90 | D11: 92 | E11: 96 | F11: 88 | G11: 80 | H11: 71 | I11: 63 | J11: 73 | K11: 89 | L11: 107 | M11: 116 | N11: 131 | O11: 133 | P11: 128 | Q11: 119 | R11: 122 | S11: 129 | T11: 124 | U11: 120 | V11: 124 | W11: 122 | X11: 126 | Y11: 123 | Z11: 118 | AA11: 120 | AB11: 121 | AC11: 127 | AD11: 127 | AE11: 118
A12: 11 | B12: Extraccion de petroleo crudo y gas natural | C12: s.d. | D12: s.d. | E12: s.d. | F12: s.d. | G12: s.d. | H12: s.d. | I12: s.d. | J12: s.d. | K12: s.d. | L12: s.d. | M12: s.d. | N12: s.d. | O12: s.d. | P12: s.d. | Q12: s.d. | R12: s.d. | S12: s.d. | T12: s.d. | U12: s.d. | V12: s.d. | W12: s.d. | X12: s.d. | Y12: s.d. | Z12: s.d. | AA12: s.d. | AB12: s.d. | AC12: s.d. | AD12: s.d. | AE12: s.d.
A13: 13 | B13: Extraccion de minerales metaliferos | C13: s.d. | D13: s.d. | E13: s.d. | F13: s.d. | G13: s.d. | H13: s.d. | I13: s.d. | J13: s.d. | K13: s.d. | L13: s.d. | M13: s.d. | N13: s.d. | O13: s.d. | P13: s.d. | Q13: s.d. | R13: s.d. | S13: s.d. | T13: s.d. | U13: s.d. | V13: s.d. | W13: s.d. | X13: s.d. | Y13: s.d. | Z13: s.d. | AA13: s.d. | AB13: s.d. | AC13: s.d. | AD13: s.d. | AE13: s.d.
A14: 14 | B14: Explotacion de otras minas y canteras | C14: 82 | D14: 85 | E14: 84 | F14: 78 | G14: 74 | H14: 66 | I14: 59 | J14: 66 | K14: 83 | L14: 101 | M14: 109 | N14: 125 | O14: 128 | P14: 122 | Q14: 111 | R14: 117 | S14: 123 | T14: 116 | U14: 115 | V14: 119 | W14: 117 | X14: 121 | Y14: 118 | Z14: 112 | AA14: 113 | AB14: 115 | AC14: 118 | AD14: 119 | AE14: 111
A15: D | B15: INDUSTRIA MANUFACTURERA | C15: 4158 | D15: 4275 | E15: 4234 | F15: 4188 | G15: 4134 | H15: 3948 | I15: 3727 | J15: 4086 | K15: 4587 | L15: 4986 | M15: 5251 | N15: 5511 | O15: 5701 | P15: 5739 | Q15: 5807 | R15: 5874 | S15: 5890 | T15: 5851 | U15: 5841 | V15: 5857 | W15: 5844 | X15: 5801 | Y15: 5714 | Z15: 5525 | AA15: 5388 | AB15: 5489 | AC15: 5741 | AD15: 5855 | AE15: 5764
A16: 15 | B16: Alimentos | C16: 1264 | D16: 1279 | E16: 1223 | F16: 1182 | G16: 1161 | H16: 1122 | I16: 1105 | J16: 1204 | K16: 1334 | L16: 1420 | M16: 1458 | N16: 1494 | O16: 1589 | P16: 1645 | Q16: 1649 | R16: 1690 | S16: 1686 | T16: 1698 | U16: 1730 | V16: 1768 | W16: 1793 | X16: 1781 | Y16: 1765 | Z16: 1730 | AA16: 1687 | AB16: 1684 | AC16: 1774 | AD16: 1801 | AE16: 1812
A17: 16 | B17: Tabaco | C17: s.d. | D17: s.d. | E17: s.d. | F17: s.d. | G17: s.d. | H17: s.d. | I17: s.d. | J17: s.d. | K17: s.d. | L17: s.d. | M17: s.d. | N17: s.d. | O17: s.d. | P17: s.d. | Q17: s.d. | R17: s.d. | S17: s.d. | T17: s.d. | U17: s.d. | V17: s.d. | W17: s.d. | X17: s.d. | Y17: s.d. | Z17: s.d. | AA17: 4 | AB17: 4 | AC17: 4 | AD17: 4 | AE17: 5
A18: 17 | B18: Productos textiles | C18: 75 | D18: 82 | E18: 75 | F18: 75 | G18: 92 | H18: 85 | I18: 76 | J18: 87 | K18: 107 | L18: 120 | M18: 130 | N18: 135 | O18: 132 | P18: 138 | Q18: 141 | R18: 153 | S18: 160 | T18: 158 | U18: 149 | V18: 152 | W18: 149 | X18: 152 | Y18: 154 | Z18: 140 | AA18: 137 | AB18: 132 | AC18: 140 | AD18: 140 | AE18: 140
A19: 18 | B19: Confecciones | C19: 178 | D19: 169 | E19: 156 | F19: 142 | G19: 139 | H19: 125 | I19: 123 | J19: 137 | K19: 161 | L19: 183 | M19: 199 | N19: 211 | O19: 206 | P19: 212 | Q19: 213 | R19: 203 | S19: 207 | T19: 182 | U19: 191 | V19: 192 | W19: 184 | X19: 192 | Y19: 181 | Z19: 167 | AA19: 152 | AB19: 159 | AC19: 171 | AD19: 192 | AE19: 177
A20: 19 | B20: Calzado y cuero | C20: 131 | D20: 131 | E20: 121 | F20: 113 | G20: 114 | H20: 106 | I20: 91 | J20: 111 | K20: 132 | L20: 143 | M20: 149 | N20: 155 | O20: 142 | P20: 134 | Q20: 131 | R20: 138 | S20: 142 | T20: 135 | U20: 140 | V20: 140 | W20: 139 | X20: 130 | Y20: 118 | Z20: 109 | AA20: 107 | AB20: 106 | AC20: 113 | AD20: 112 | AE20: 105
A21: 20 | B21: Madera | C21: 175 | D21: 180 | E21: 183 | F21: 186 | G21: 170 | H21: 170 | I21: 159 | J21: 183 | K21: 206 | L21: 220 | M21: 231 | N21: 236 | O21: 250 | P21: 235 | Q21: 237 | R21: 233 | S21: 244 | T21: 235 | U21: 229 | V21: 215 | W21: 210 | X21: 208 | Y21: 207 | Z21: 182 | AA21: 172 | AB21: 176 | AC21: 181 | AD21: 193 | AE21: 177
A22: 21 | B22: Papel | C22: 46 | D22: 46 | E22: 38 | F22: 41 | G22: 45 | H22: 39 | I22: 39 | J22: 45 | K22: 54 | L22: 53 | M22: 58 | N22: 58 | O22: 61 | P22: 56 | Q22: 58 | R22: 63 | S22: 66 | T22: 63 | U22: 64 | V22: 63 | W22: 64 | X22: 65 | Y22: 63 | Z22: 66 | AA22: 66 | AB22: 69 | AC22: 72 | AD22: 77 | AE22: 70
A23: 22 | B23: Edición | C23: 234 | D23: 246 | E23: 257 | F23: 263 | G23: 264 | H23: 248 | I23: 219 | J23: 230 | K23: 271 | L23: 294 | M23: 307 | N23: 323 | O23: 326 | P23: 331 | Q23: 327 | R23: 315 | S23: 317 | T23: 317 | U23: 300 | V23: 294 | W23: 285 | X23: 278 | Y23: 252 | Z23: 222 | AA23: 201 | AB23: 198 | AC23: 208 | AD23: 214 | AE23: 204
A24: 23 | B24: Productos de petróleo | C24: 14 | D24: 15 | E24: 13 | F24: 17 | G24: 15 | H24: 12 | I24: 11 | J24: 10 | K24: 12 | L24: 11 | M24: 10 | N24: 11 | O24: 12 | P24: 12 | Q24: 11 | R24: 13 | S24: 14 | T24: 14 | U24: 11 | V24: 11 | W24: 11 | X24: 12 | Y24: 13 | Z24: 11 | AA24: 10 | AB24: 10 | AC24: 10 | AD24: 10 | AE24: 10
A25: 24 | B25: Productos químicos | C25: 168 | D25: 169 | E25: 175 | F25: 189 | G25: 190 | H25: 196 | I25: 196 | J25: 195 | K25: 199 | L25: 215 | M25: 214 | N25: 229 | O25: 223 | P25: 226 | Q25: 232 | R25: 233 | S25: 226 | T25: 222 | U25: 223 | V25: 232 | W25: 237 | X25: 238 | Y25: 228 | Z25: 226 | AA25: 223 | AB25: 229 | AC25: 233 | AD25: 236 | AE25: 237
A26: 25 | B26: Productos de caucho y plástico | C26: 161 | D26: 153 | E26: 169 | F26: 174 | G26: 185 | H26: 181 | I26: 171 | J26: 185 | K26: 203 | L26: 204 | M26: 218 | N26: 236 | O26: 240 | P26: 234 | Q26: 249 | R26: 252 | S26: 251 | T26: 254 | U26: 252 | V26: 254 | W26: 251 | X26: 246 | Y26: 254 | Z26: 245 | AA26: 248 | AB26: 256 | AC26: 262 | AD26: 276 | AE26: 283
A27: 26 | B27: Otros minerales no metálicos | C27: 185 | D27: 183 | E27: 193 | F27: 195 | G27: 189 | H27: 178 | I27: 168 | J27: 169 | K27: 191 | L27: 207 | M27: 217 | N27: 234 | O27: 242 | P27: 249 | Q27: 252 | R27: 250 | S27: 255 | T27: 268 | U27: 258 | V27: 251 | W27: 253 | X27: 244 | Y27: 234 | Z27: 233 | AA27: 234 | AB27: 246 | AC27: 254 | AD27: 260 | AE27: 254
A28: 27 | B28: Metales comunes | C28: 92 | D28: 92 | E28: 90 | F28: 87 | G28: 80 | H28: 71 | I28: 59 | J28: 68 | K28: 75 | L28: 90 | M28: 98 | N28: 101 | O28: 105 | P28: 97 | Q28: 93 | R28: 93 | S28: 89 | T28: 91 | U28: 93 | V28: 94 | W28: 91 | X28: 91 | Y28: 85 | Z28: 79 | AA28: 77 | AB28: 80 | AC28: 81 | AD28: 84 | AE28: 82
A29: 28 | B29: Otros productos de metal | C29: 489 | D29: 529 | E29: 534 | F29: 517 | G29: 529 | H29: 493 | I29: 464 | J29: 535 | K29: 611 | L29: 696 | M29: 758 | N29: 830 | O29: 866 | P29: 865 | Q29: 874 | R29: 898 | S29: 889 | T29: 888 | U29: 880 | V29: 867 | W29: 860 | X29: 866 | Y29: 869 | Z29: 848 | AA29: 834 | AB29: 859 | AC29: 903 | AD29: 916 | AE29: 878
... A32: 31 | B32: Aparatos eléctricos | C32: 68 | D32: 66 | E32: 65 | F32: 68 | G32: 62 | H32: 60 | I32: 57 | J32: 60 | K32: 71 | L32: 78 | M32: 85 | N32: 95 | O32: 99 | P32: 106 | Q32: 108 | R32: 109 | S32: 107 | T32: 112 | U32: 114 | V32: 122 | W32: 115 | X32: 120 | Y32: 119 | Z32: 113 | AA32: 113 | AB32: 120 | AC32: 125 | AD32: 123 | AE32: 121
A33: 32 | B33: Radio y televisión | C33: 18 | D33: 18 | E33: 14 | F33: 15 | G33: 17 | H33: 15 | I33: 13 | J33: 12 | K33: 17 | L33: 19 | M33: 17 | N33: 19 | O33: 19 | P33: 16 | Q33: 18 | R33: 15 | S33: 19 | T33: 18 | U33: 17 | V33: 17 | W33: 17 | X33: 17 | Y33: 17 | Z33: s.d. | AA33: 19 | AB33: 21 | AC33: 22 | AD33: 22 | AE33: 19
A34: 33 | B34: Instrumentos médicos | C34: 43 | D34: 43 | E34: 44 | F34: 44 | G34: 43 | H34: 46 | I34: 47 | J34: 51 | K34: 63 | L34: 65 | M34: 66 | N34: 65 | O34: 69 | P34: 67 | Q34: 71 | R34: 70 | S34: 74 | T34: 71 | U34: 67 | V34: 70 | W34: 73 | X34: 74 | Y34: 73 | Z34: 77 | AA34: 75 | AB34: 75 | AC34: 82 | AD34: 81 | AE34: 84
A35: 34 | B35: Automotores | C35: 237 | D35: 255 | E35: 254 | F35: 254 | G35: 245 | H35: 232 | I35: 217 | J35: 233 | K35: 242 | L35: 256 | M35: 265 | N35: 280 | O35: 287 | P35: 286 | Q35: 291 | R35: 293 | S35: 293 | T35: 286 | U35: 289 | V35: 289 | W35: 286 | X35: 275 | Y35: 271 | Z35: 265 | AA35: 257 | AB35: 269 | AC35: 274 | AD35: 273 | AE35: 261
A36: 35 | B36: Otros equipo de transporte | C36: 23 | D36: 26 | E36: 24 | F36: 24 | G36: 27 | H36: 29 | I36: 25 | J36: 25 | K36: 28 | L36: 33 | M36: 33 | N36: 31 | O36: 33 | P36: 32 | Q36: 33 | R36: 36 | S36: 34 | T36: 35 | U36: 36 | V36: 33 | W36: 35 | X36: 35 | Y36: 34 | Z36: 34 | AA36: 32 | AB36: 34 | AC36: 36 | AD36: 34 | AE36: 35
A37: 36 | B37: Muebles | C37: 254 | D37: 276 | E37: 279 | F37: 271 | G37: 254 | H37: 239 | I37: 206 | J37: 232 | K37: 258 | L37: 290 | M37: 318 | N37: 331 | O37: 345 | P37: 345 | Q37: 354 | R37: 343 | S37: 343 | T37: 340 | U37: 337 | V37: 338 | W37: 331 | X37: 329 | Y37: 330 | Z37: 314 | AA37: 291 | AB37: 301 | AC37: 311 | AD37: 329 | AE37: 329
A38: 37 | B38: Reciclamiento de desperdicios y desechos | C38: s.d. | D38: s.d. | E38: s.d. | F38: s.d. | G38: s.d. | H38: s.d. | I38: s.d. | J38: s.d. | K38: s.d. | L38: s.d. | M38: s.d. | N38: s.d. | O38: s.d. | P38: s.d. | Q38: s.d. | R38: s.d. | S38: s.d. | T38: s.d. | U38: s.d. | V38: s.d. | W38: s.d. | X38: s.d. | Y38: s.d. | Z38: 20 | AA38: 23 | AB38: 24 | AC38: 23 | AD38: 28 | AE38: 30
A39: E | B39: ELECTRICIDAD, GAS Y AGUA | C39: 253 | D39: 255 | E39: 259 | F39: 263 | G39: 256 | H39: 258 | I39: 255 | J39: 257 | K39: 253 | L39: 256 | M39: 259 | N39: 259 | O39: 261 | P39: 259 | Q39: 256 | R39: 261 | S39: 258 | T39: 255 | U39: 257 | V39: 255 | W39: 258 | X39: 258 | Y39: 259 | Z39: 258 | AA39: 260 | AB39: 264 | AC39: 260 | AD39: 262 | AE39: 267
A40: 40 | B40: Electricidad, gas y agua | C40: 204 | D40: 205 | E40: 205 | F40: 210 | G40: 206 | H40: 208 | I40: 207 | J40: 207 | K40: 207 | L40: 208 | M40: 208 | N40: 208 | O40: 209 | P40: 207 | Q40: 206 | R40: 211 | S40: 211 | T40: 207 | U40: 209 | V40: 209 | W40: 210 | X40: 212 | Y40: 214 | Z40: 214 | AA40: 216 | AB40: 220 | AC40: 219 | AD40: 218 | AE40: 220
A41: 41 | B41: Captación, depuración y distribución de agua | C41: 49 | D41: 50 | E41: 54 | F41: 53 | G41: 50 | H41: 50 | I41: 48 | J41: 50 | K41: 46 | L41: 48 | M41: 51 | N41: 51 | O41: 52 | P41: 52 | Q41: 50 | R41: 50 | S41: 47 | T41: 48 | U41: 48 | V41: 46 | W41: 48 | X41: 46 | Y41: 45 | Z41: 44 | AA41: 44 | AB41: 44 | AC41: 41 | AD41: 44 | AE41: 47
A42: F | B42: CONSTRUCCION | C42: 1044 | D42: 1065 | E42: 1113 | F42: 1168 | G42: 1179 | H42: 1024 | I42: 828 | J42: 1031 | K42: 1265 | L42: 1487 | M42: 1741 | N42: 1983 | O42: 2119 | P42: 2123 | Q42: 2112 | R42: 2221 | S42: 2147 | T42: 2151 | U42: 2068 | V42: 2017 | W42: 2064 | X42: 2160 | Y42: 2154 | Z42: 2058 | AA42: 1944 | AB42: 2058 | AC42: 2186 | AD42: 2175 | AE42: 2020
A43: 45 | B43: Construccion | C43: 1044 | D43: 1065 | E43: 1113 | F43: 1168 | G43: 1179 | H43: 1024 | I43: 828 | J43: 1031 | K43: 1265 | L43: 1487 | M43: 1741 | N43: 1983 | O43: 2119 | P43: 2123 | Q43: 2112 | R43: 2221 | S43: 2147 | T43: 2151 | U43: 2068 | V43: 2017 | W43: 2064 | X43: 2160 | Y43: 2154 | Z43: 2058 | AA43: 1944 | AB43: 2058 | AC43: 2186 | AD43: 2175 | AE43: 2020
A44: G | B44: COMERCIO AL POR MAYOR Y AL POR MENOR | C44: 8179 | D44: 8202 | E44: 8183 | F44: 8092 | G44: 8294 | H44: 8180 | I44: 7806 | J44: 8806 | K44: 10492 | L44: 11580 | M44: 12557 | N44: 13478 | O44: 14374 | P44: 14711 | Q44: 14888 | R44: 15105 | S44: 15297 | T44: 15225 | U44: 15054 | V44: 15286 | W44: 15443 | X44: 15656 | Y44: 15572 | Z44: 15143 | AA44: 14516 | AB44: 14873 | AC44: 16083 | AD44: 17027 | AE44: 16352
A45: 50 | B45: Vta y reparación de vehículos. vta por menor de combustible | C45: 1431 | D45: 1441 | E45: 1434 | F45: 1446 | G45: 1489 | H45: 1462 | I45: 1398 | J45: 1515 | K45: 1737 | L45: 1914 | M45: 2029 | N45: 2129 | O45: 2211 | P45: 2244 | Q45: 2205 | R45: 2190 | S45: 2188 | T45: 2187 | U45: 2178 | V45: 2172 | W45: 2166 | X45: 2146 | Y45: 2085 | Z45: 2072 | AA45: 2044 | AB45: 2073 | AC45: 2149 | AD45: 2262 | AE45: 2222
A46: 51 | B46: Comercio al por mayor | C46: 2080 | D46: 2121 | E46: 2145 | F46: 2179 | G46: 2189 | H46: 2137 | I46: 2063 | J46: 2301 | K46: 2521 | L46: 2713 | M46: 2854 | N46: 3030 | O46: 3139 | P46: 3143 | Q46: 3160 | R46: 3240 | S46: 3288 | T46: 3250 | U46: 3193 | V46: 3173 | W46: 3177 | X46: 3205 | Y46: 3188 | Z46: 3164 | AA46: 3195 | AB46: 3358 | AC46: 3480 | AD46: 3566 | AE46: 3592
A47: 52 | B47: Comercio al por menor | C47: 4668 | D47: 4640 | E47: 4604 | F47: 4467 | G47: 4616 | H47: 4581 | I47: 4345 | J47: 4990 | K47: 6234 | L47: 6953 | M47: 7674 | N47: 8319 | O47: 9024 | P47: 9324 | Q47: 9523 | R47: 9675 | S47: 9821 | T47: 9788 | U47: 9683 | V47: 9941 | W47: 10100 | X47: 10305 | Y47: 10299 | Z47: 9907 | AA47: 9277 | AB47: 9442 | AC47: 10454 | AD47: 11199 | AE47: 10538
A48: H | B48: HOTELERIA Y RESTAURANTES | C48: 1197 | D48: 1169 | E48: 1152 | F48: 1022 | G48: 1038 | H48: 955 | I48: 945 | J48: 1064 | K48: 1447 | L48: 1707 | M48: 2023 | N48: 2190 | O48: 2426 | P48: 2622 | Q48: 2632 | R48: 2732 | S48: 2866 | T48: 2936 | U48: 3030 | V48: 3004 | W48: 3056 | X48: 3134 | Y48: 3183 | Z48: 3066 | AA48: 2500 | AB48: 2481 | AC48: 2886 | AD48: 3119 | AE48: 2961
A49: 55 | B49: Servicios de hoteleria y restaurantes | C49: 1197 | D49: 1169 | E49: 1152 | F49: 1022 | G49: 1038 | H49: 955 | I49: 945 | J49: 1064 | K49: 1447 | L49: 1707 | M49: 2023 | N49: 2190 | O49: 2426 | P49: 2622 | Q49: 2632 | R49: 2732 | S49: 2866 | T49: 2936 | U49: 3030 | V49: 3004 | W49: 3056 | X49: 3134 | Y49: 3183 | Z49: 3066 | AA49: 2500 | AB49: 2481 | AC49: 2886 | AD49: 3119 | AE49: 2961
A50: I | B50: SERVICIOS DE TRANSPORTE, DE ALMACENAMIENTO Y DE COMUNICACIONES | C50: 2971 | D50: 3115 | E50: 3245 | F50: 3113 | G50: 3098 | H50: 3099 | I50: 2786 | J50: 3422 | K50: 3962 | L50: 4451 | M50: 5302 | N50: 6099 | O50: 6667 | P50: 6779 | Q50: 7002 | R50: 7186 | S50: 7318 | T50: 7244 | U50: 7170 | V50: 7084 | W50: 7190 | X50: 7148 | Y50: 6992 | Z50: 6788 | AA50: 6141 | AB50: 5789 | AC50: 5784 | AD50: 5426 | AE50: 4919
A51: 60 | B51: Transporte ferroviario y automotor y por tuberias | C51: 2542 | D51: 2636 | E51: 2705 | F51: 2524 | G51: 2463 | H51: 2492 | I51: 2239 | J51: 2849 | K51: 3301 | L51: 3781 | M51: 4620 | N51: 5405 | O51: 5920 | P51: 6019 | Q51: 6226 | R51: 6380 | S51: 6488 | T51: 6435 | U51: 6374 | V51: 6276 | W51: 6341 | X51: 6287 | Y51: 6127 | Z51: 5935 | AA51: 5367 | AB51: 5040 | AC51: 4987 | AD51: 4588 | AE51: 4070
A52: 61 | B52: Transporte marítimo y fluvial | C52: 4 | D52: s.d. | E52: 6 | F52: 5 | G52: 8 | H52: 7 | I52: 5 | J52: 5 | K52: 7 | L52: 7 | M52: 6 | N52: s.d. | O52: 5 | P52: 6 | Q52: 6 | R52: 6 | S52: 4 | T52: 6 | U52: 7 | V52: 6 | W52: 4 | X52: 4 | Y52: 4 | Z52: 6 | AA52: 6 | AB52: 5 | AC52: 7 | AD52: 6 | AE52: 5
A53: 62 | B53: Transporte aéreo de cargas y de pasajeros | C53: 10 | D53: s.d. | E53: 11 | F53: 14 | G53: 13 | H53: 14 | I53: 11 | J53: 9 | K53: 9 | L53: 10 | M53: 11 | N53: s.d. | O53: 10 | P53: 11 | Q53: 9 | R53: 10 | S53: 9 | T53: 9 | U53: 9 | V53: 10 | W53: 10 | X53: 10 | Y53: 13 | Z53: 13 | AA53: 13 | AB53: 9 | AC53: 7 | AD53: 8 | AE53: 8
A54: 63 | B54: Manipulación de carga, almacenamiento y depósito | C54: 261 | D54: 286 | E54: 310 | F54: 290 | G54: 296 | H54: 284 | I54: 263 | J54: 287 | K54: 357 | L54: 390 | M54: 430 | N54: 454 | O54: 501 | P54: 531 | Q54: 559 | R54: 592 | S54: 620 | T54: 605 | U54: 595 | V54: 605 | W54: 651 | X54: 668 | Y54: 667 | Z54: 664 | AA54: 584 | AB54: 560 | AC54: 607 | AD54: 643 | AE54: 664
A55: 64 | B55: Telecomunicaciones y correos | C55: 154 | D55: 178 | E55: 213 | F55: 280 | G55: 318 | H55: 302 | I55: 268 | J55: 272 | K55: 288 | L55: 263 | M55: 235 | N55: 227 | O55: 231 | P55: 212 | Q55: 202 | R55: 198 | S55: 197 | T55: 189 | U55: 185 | V55: 187 | W55: 184 | X55: 179 | Y55: 181 | Z55: 170 | AA55: 171 | AB55: 175 | AC55: 176 | AD55: 181 | AE55: 172
A56: J | B56: INTERMEDIACION FINANCIERA Y OTROS SERVICIOS FINANCIEROS | C56: 360 | D56: 374 | E56: 383 | F56: 378 | G56: 390 | H56: 385 | I56: 372 | J56: 390 | K56: 458 | L56: 476 | M56: 522 | N56: 552 | O56: 582 | P56: 590 | Q56: 625 | R56: 646 | S56: 654 | T56: 669 | U56: 660 | V56: 653 | W56: 656 | X56: 653 | Y56: 659 | Z56: 640 | AA56: 617 | AB56: 595 | AC56: 606 | AD56: 616 | AE56: 592
A57: 65 | B57: Intermediacion financiera y otros servicios financieros | C57: 140 | D57: 144 | E57: 151 | F57: 139 | G57: 133 | H57: 137 | I57: 129 | J57: 125 | K57: 133 | L57: 139 | M57: 152 | N57: 156 | O57: 166 | P57: 154 | Q57: 159 | R57: 169 | S57: 174 | T57: 180 | U57: 179 | V57: 172 | W57: 175 | X57: 168 | Y57: 167 | Z57: 164 | AA57: 161 | AB57: 143 | AC57: 147 | AD57: 140 | AE57: 137
A58: 66 | B58: Seguros | C58: 87 | D58: 93 | E58: 93 | F58: 106 | G58: 112 | H58: 104 | I58: 100 | J58: 103 | K58: 105 | L58: 109 | M58: 110 | N58: 107 | O58: 104 | P58: 95 | Q58: 95 | R58: 96 | S58: 92 | T58: 89 | U58: 85 | V58: 89 | W58: 90 | X58: 86 | Y58: 86 | Z58: 81 | AA58: 76 | AB58: 77 | AC58: 74 | AD58: 76 | AE58: 76
A59: 67 | B59: Servicios auxiliares a la actividad financiera | C59: 133 | D59: 137 | E59: 139 | F59: 133 | G59: 145 | H59: 144 | I59: 143 | J59: 162 | K59: 220 | L59: 228 | M59: 260 | N59: 289 | O59: 312 | P59: 341 | Q59: 371 | R59: 381 | S59: 388 | T59: 400 | U59: 396 | V59: 392 | W59: 391 | X59: 399 | Y59: 406 | Z59: 395 | AA59: 380 | AB59: 375 | AC59: 385 | AD59: 400 | AE59: 379
A60: K | B60: SERVICIOS INMOBILIARIOS, EMPRESARIALES Y DE ALQUILER | C60: 7945 | D60: 8266 | E60: 8456 | F60: 8469 | G60: 8569 | H60: 8562 | I60: 8277 | J60: 9001 | K60: 10049 | L60: 10632 | M60: 11168 | N60: 11536 | O60: 11869 | P60: 11650 | Q60: 11639 | R60: 11620 | S60: 11325 | T60: 10978 | U60: 10620 | V60: 10343 | W60: 10025 | X60: 9736 | Y60: 9415 | Z60: 8896 | AA60: 8264 | AB60: 8061 | AC60: 8239 | AD60: 8296 | AE60: 7646
A61: 70 | B61: Servicios inmobiliarios | C61: 5033 | D61: 5135 | E61: 5180 | F61: 5098 | G61: 5036 | H61: 5010 | I61: 4912 | J61: 5193 | K61: 5584 | L61: 5767 | M61: 5994 | N61: 5953 | O61: 5972 | P61: 5849 | Q61: 5795 | R61: 5730 | S61: 5519 | T61: 5306 | U61: 5055 | V61: 4861 | W61: 4639 | X61: 4407 | Y61: 4191 | Z61: 3928 | AA61: 3611 | AB61: 3426 | AC61: 3494 | AD61: 3345 | AE61: 3097
A62: 71 | B62: Alquiler de equipo de transporte y de maquinaria | C62: 111 | D62: 118 | E62: 109 | F62: 104 | G62: 100 | H62: 96 | I62: 91 | J62: 109 | K62: 136 | L62: 149 | M62: 153 | N62: 169 | O62: 176 | P62: 178 | Q62: 180 | R62: 191 | S62: 174 | T62: 173 | U62: 170 | V62: 160 | W62: 150 | X62: 156 | Y62: 153 | Z62: 135 | AA62: 110 | AB62: 107 | AC62: 110 | AD62: 117 | AE62: 114
A63: 72 | B63: Actividades de informática | C63: 78 | D63: 81 | E63: 95 | F63: 113 | G63: 122 | H63: 128 | I63: 112 | J63: 153 | K63: 194 | L63: 228 | M63: 270 | N63: 346 | O63: 378 | P63: 363 | Q63: 373 | R63: 392 | S63: 402 | T63: 399 | U63: 393 | V63: 401 | W63: 428 | X63: 460 | Y63: 481 | Z63: 498 | AA63: 525 | AB63: 563 | AC63: 616 | AD63: 658 | AE63: 632
A64: 73 | B64: Investigación y desarrollo | C64: 10 | D64: 12 | E64: 14 | F64: 13 | G64: 17 | H64: 17 | I64: 17 | J64: 18 | K64: 20 | L64: 22 | M64: 24 | N64: 24 | O64: 28 | P64: 34 | Q64: 33 | R64: 34 | S64: 32 | T64: 32 | U64: 33 | V64: 36 | W64: 34 | X64: 37 | Y64: 40 | Z64: 44 | AA64: 43 | AB64: 49 | AC64: 51 | AD64: 59 | AE64: 55
A65: 74 | B65: Servicios jurídicos, contables y otros servicios a empresas | C65: 2698 | D65: 2898 | E65: 3036 | F65: 3117 | G65: 3269 | H65: 3285 | I65: 3117 | J65: 3501 | K65: 4087 | L65: 4435 | M65: 4694 | N65: 5013 | O65: 5284 | P65: 5195 | Q65: 5231 | R65: 5247 | S65: 5173 | T65: 5042 | U65: 4946 | V65: 4865 | W65: 4752 | X65: 4658 | Y65: 4532 | Z65: 4276 | AA65: 3962 | AB65: 3902 | AC65: 3955 | AD65: 4103 | AE65: 3735
A66: 75 | B66: Agencias de empleo eventual | C66: 15 | D66: 22 | E66: 22 | F66: 24 | G66: 25 | H66: 26 | I66: 28 | J66: 27 | K66: 28 | L66: 31 | M66: 33 | N66: 31 | O66: 31 | P66: 31 | Q66: 27 | R66: 26 | S66: 25 | T66: 26 | U66: 23 | V66: 20 | W66: 22 | X66: 18 | Y66: 18 | Z66: 15 | AA66: 13 | AB66: 14 | AC66: 13 | AD66: 14 | AE66: 13
A67: M | B67: ENSEÑANZA | C67: 668 | D67: 673 | E67: 678 | F67: 680 | G67: 641 | H67: 649 | I67: 634 | J67: 667 | K67: 706 | L67: 740 | M67: 781 | N67: 805 | O67: 845 | P67: 860 | Q67: 866 | R67: 883 | S67: 934 | T67: 954 | U67: 955 | V67: 941 | W67: 947 | X67: 953 | Y67: 937 | Z67: 920 | AA67: 876 | AB67: 866 | AC67: 915 | AD67: 933 | AE67: 890
A68: 80 | B68: Enseñanza | C68: 668 | D68: 673 | E68: 678 | F68: 680 | G68: 641 | H68: 649 | I68: 634 | J68: 667 | K68: 706 | L68: 740 | M68: 781 | N68: 805 | O68: 845 | P68: 860 | Q68: 866 | R68: 883 | S68: 934 | T68: 954 | U68: 955 | V68: 941 | W68: 947 | X68: 953 | Y68: 937 | Z68: 920 | AA68: 876 | AB68: 866 | AC68: 915 | AD68: 933 | AE68: 890
A69: N | B69: SERVICIOS SOCIALES Y DE SALUD | C69: 1465 | D69: 1477 | E69: 1537 | F69: 1510 | G69: 1524 | H69: 1526 | I69: 1469 | J69: 1539 | K69: 1708 | L69: 1846 | M69: 1941 | N69: 2067 | O69: 2197 | P69: 2286 | Q69: 2291 | R69: 2318 | S69: 2313 | T69: 2366 | U69: 2331 | V69: 2333 | W69: 2349 | X69: 2351 | Y69: 2306 | Z69: 2280 | AA69: 2179 | AB69: 2193 | AC69: 2251 | AD69: 2463 | AE69: 2272
A70: 85 | B70: Servicios sociales y de salud | C70: 1465 | D70: 1477 | E70: 1537 | F70: 1510 | G70: 1524 | H70: 1526 | I70: 1469 | J70: 1539 | K70: 1708 | L70: 1846 | M70: 1941 | N70: 2067 | O70: 2197 | P70: 2286 | Q70: 2291 | R70: 2318 | S70: 2313 | T70: 2366 | U70: 2331 | V70: 2333 | W70: 2349 | X70: 2351 | Y70: 2306 | Z70: 2280 | AA70: 2179 | AB70: 2193 | AC70: 2251 | AD70: 2463 | AE70: 2272
A71: O | B71: SERVICIOS COMUNITARIOS, SOCIALES Y PERSONALES N.C.P. | C71: 3149 | D71: 3140 | E71: 3124 | F71: 3078 | G71: 3073 | H71: 3035 | I71: 2883 | J71: 3126 | K71: 3635 | L71: 3842 | M71: 4055 | N71: 4116 | O71: 4155 | P71: 4113 | Q71: 4045 | R71: 3948 | S71: 3878 | T71: 3796 | U71: 3753 | V71: 3677 | W71: 3629 | X71: 3551 | Y71: 3479 | Z71: 3321 | AA71: 3023 | AB71: 2915 | AC71: 3088 | AD71: 3186 | AE71: 2954
A72: 90 | B72: Eliminación de desperdicios | C72: 54 | D72: 46 | E72: 48 | F72: 43 | G72: 39 | H72: 35 | I72: 28 | J72: 34 | K72: 37 | L72: 39 | M72: 44 | N72: 45 | O72: 48 | P72: 49 | Q72: 49 | R72: 48 | S72: 44 | T72: 44 | U72: 45 | V72: 52 | W72: 53 | X72: 52 | Y72: 52 | Z72: 63 | AA72: 65 | AB72: 67 | AC72: 70 | AD72: 73 | AE72: 73
A73: 91 | B73: Servicios de organizaciones empresariales | C73: 1465 | D73: 1463 | E73: 1438 | F73: 1451 | G73: 1449 | H73: 1460 | I73: 1438 | J73: 1473 | K73: 1497 | L73: 1545 | M73: 1557 | N73: 1582 | O73: 1595 | P73: 1593 | Q73: 1606 | R73: 1600 | S73: 1609 | T73: 1635 | U73: 1647 | V73: 1653 | W73: 1666 | X73: 1658 | Y73: 1652 | Z73: 1645 | AA73: 1622 | AB73: 1596 | AC73: 1607 | AD73: 1610 | AE73: 1571
A74: 92 | B74: Servicios culturales, deportivos y de esparcimiento | C74: 408 | D74: 409 | E74: 388 | F74: 360 | G74: 366 | H74: 373 | I74: 357 | J74: 385 | K74: 463 | L74: 492 | M74: 555 | N74: 597 | O74: 603 | P74: 628 | Q74: 649 | R74: 632 | S74: 646 | T74: 671 | U74: 682 | V74: 655 | W74: 663 | X74: 661 | Y74: 671 | Z74: 643 | AA74: 563 | AB74: 565 | AC74: 662 | AD74: 693 | AE74: 647
A75: 93 | B75: Servicios n.c.p. | C75: 1222 | D75: 1222 | E75: 1250 | F75: 1224 | G75: 1219 | H75: 1167 | I75: 1060 | J75: 1234 | K75: 1638 | L75: 1766 | M75: 1899 | N75: 1892 | O75: 1909 | P75: 1843 | Q75: 1741 | R75: 1668 | S75: 1579 | T75: 1446 | U75: 1379 | V75: 1317 | W75: 1247 | X75: 1180 | Y75: 1104 | Z75: 970 | AA75: 773 | AB75: 687 | AC75: 749 | AD75: 810 | AE75: 663
B76: TOTAL | C76: 38623 | D76: 39230 | E76: 39505 | F76: 38978 | G76: 39044 | H76: 38481 | I76: 37024 | J76: 41077 | K76: 46810 | L76: 50762 | M76: 54631 | N76: 57882 | O76: 60587 | P76: 60992 | Q76: 61367 | R76: 62237 | S76: 62164 | T76: 61531 | U76: 60731 | V76: 60184 | W76: 60113 | X76: 60018 | Y76: 59226 | Z76: 57532 | AA76: 54402 | AB76: 54504 | AC76: 57121 | AD76: 58274 | AE76: 55365
A78: Notas:
A79: 1 - Las empresas se encuentran clasificadas por provincia según las zonas donde declaran que trabajan las personas.
A80: 2 - Las firmas con participación accionaria privada y estatal se incluye dentro del sector privado
A81: 3 - s/d : Dato no publicado para resguardar el secreto estadístico de las firmas
A82: Fuente: STEySS - Dirección Nacional de Estudios y Estadísticas Laborales - Observatorio de Empleo y Dinámica Empresarial, en base a SIPA.

Sheet Corrientes
D1: Volver al índice
A2: Corrientes
A3: Empresas del sector privado por rama de actividad - Activas en cada año
B4: Ramas de actividad | C4: 1996 | D4: 1997 | E4: 1998 | F4: 1999 | G4: 2000 | H4: 2001 | I4: 2002 | J4: 2003 | K4: 2004 | L4: 2005 | M4: 2006 | N4: 2007 | O4: 2008 | P4: 2009 | Q4: 2010 | R4: 2011 | S4: 2012 | T4: 2013 | U4: 2014 | V4: 2015 | W4: 2016 | X4: 2017 | Y4: 2018 | Z4: 2019 | AA4: 2020 | AB4: 2021 | AC4: 2022 | AD4: 2023 | AE4: 2024
D5: 2º Trim 1996 | F5: 3º Trim 1996 | H5: 4º Trim 1996 | J5: 1º Trim 1997 | L5: 2º Trim 1997 | N5: 3º Trim 1997 | P5: 4º Trim 1997 | R5: 1º Trim 1998
A6: A | B6: AGRICULTURA, GANADERIA, CAZA Y SILVICULTURA | C6: 1669 | D6: 1587 | E6: 1620 | F6: 1648 | G6: 1519 | H6: 1477 | I6: 1442 | J6: 1478 | K6: 1588 | L6: 1755 | M6: 1796 | N6: 1839 | O6: 1962 | P6: 1967 | Q6: 1984 | R6: 2033 | S6: 2042 | T6: 2037 | U6: 2027 | V6: 2018 | W6: 2021 | X6: 1986 | Y6: 1976 | Z6: 1949 | AA6: 1934 | AB6: 1956 | AC6: 2041 | AD6: 1990 | AE6: 1903
A7: 1 | B7: Agricultura y ganaderia | C7: 1623 | D7: 1538 | E7: 1570 | F7: 1592 | G7: 1461 | H7: 1417 | I7: 1379 | J7: 1411 | K7: 1510 | L7: 1655 | M7: 1688 | N7: 1723 | O7: 1840 | P7: 1838 | Q7: 1858 | R7: 1909 | S7: 1918 | T7: 1906 | U7: 1902 | V7: 1892 | W7: 1889 | X7: 1855 | Y7: 1852 | Z7: 1833 | AA7: 1816 | AB7: 1822 | AC7: 1893 | AD7: 1848 | AE7: 1772
A8: 2 | B8: Silvicultura, extracción de madera | C8: 46 | D8: 49 | E8: 50 | F8: 56 | G8: 58 | H8: 60 | I8: 63 | J8: 67 | K8: 78 | L8: 100 | M8: 108 | N8: 116 | O8: 122 | P8: 129 | Q8: 126 | R8: 124 | S8: 124 | T8: 131 | U8: 125 | V8: 126 | W8: 132 | X8: 131 | Y8: 124 | Z8: 116 | AA8: 118 | AB8: 134 | AC8: 148 | AD8: 142 | AE8: 131
A9: B | B9: PESCA Y SERVICIOS CONEXOS | C9: 4 | D9: 6 | E9: s.d. | F9: s.d. | G9: s.d. | H9: s.d. | I9: s.d. | J9: s.d. | K9: s.d. | L9: 4 | M9: 7 | N9: 8 | O9: 7 | P9: 7 | Q9: 7 | R9: 5 | S9: 5 | T9: 4 | U9: 4 | V9: s.d. | W9: 6 | X9: 6 | Y9: 5 | Z9: 5 | AA9: 5 | AB9: 5 | AC9: 5 | AD9: 7 | AE9: 8
A10: 5 | B10: Pesca y actividades relacionadas con la pesca | C10: 4 | D10: 6 | E10: s.d. | F10: s.d. | G10: s.d. | H10: s.d. | I10: s.d. | J10: s.d. | K10: s.d. | L10: 4 | M10: 7 | N10: 8 | O10: 7 | P10: 7 | Q10: 7 | R10: 5 | S10: 5 | T10: 4 | U10: 4 | V10: s.d. | W10: 6 | X10: 6 | Y10: 5 | Z10: 5 | AA10: 5 | AB10: 5 | AC10: 5 | AD10: 7 | AE10: 8
A11: C | B11: EXPLOTACION DE MINAS Y CANTERAS | C11: 19 | D11: 21 | E11: 20 | F11: 21 | G11: 17 | H11: 19 | I11: 11 | J11: 12 | K11: 13 | L11: 16 | M11: 13 | N11: 15 | O11: 13 | P11: 18 | Q11: 20 | R11: 19 | S11: 19 | T11: 22 | U11: 20 | V11: 21 | W11: 22 | X11: 25 | Y11: 24 | Z11: 24 | AA11: 22 | AB11: 22 | AC11: 25 | AD11: 25 | AE11: 25
A12: 11 | B12: Extraccion de petroleo crudo y gas natural | C12: s.d. | D12: s.d. | E12: s.d. | F12: s.d. | G12: s.d. | H12: s.d. | I12: s.d. | J12: s.d. | K12: s.d. | L12: s.d. | M12: s.d. | N12: s.d. | O12: s.d. | P12: s.d. | Q12: s.d. | R12: s.d. | S12: s.d. | T12: s.d. | U12: s.d. | V12: s.d. | W12: s.d. | X12: s.d. | Y12: s.d. | Z12: s.d. | AA12: s.d. | AB12: s.d. | AC12: s.d. | AD12: s.d. | AE12: s.d.
A13: 13 | B13: Extraccion de minerales metaliferos | C13: s.d. | D13: s.d. | E13: s.d. | F13: s.d. | G13: s.d. | H13: s.d. | I13: s.d. | J13: s.d. | K13: s.d. | L13: s.d. | M13: s.d. | N13: s.d. | O13: s.d. | P13: s.d. | Q13: s.d. | R13: s.d. | S13: s.d. | T13: s.d. | U13: s.d. | V13: s.d. | W13: s.d. | X13: s.d. | Y13: s.d. | Z13: s.d. | AA13: s.d. | AB13: s.d. | AC13: s.d. | AD13: s.d. | AE13: s.d.
A14: 14 | B14: Explotacion de otras minas y canteras | C14: 13 | D14: 16 | E14: 17 | F14: 16 | G14: 13 | H14: 14 | I14: 10 | J14: 11 | K14: 13 | L14: 16 | M14: 13 | N14: 13 | O14: 13 | P14: 16 | Q14: 18 | R14: 18 | S14: 18 | T14: 20 | U14: 19 | V14: 20 | W14: 20 | X14: 23 | Y14: 22 | Z14: 22 | AA14: 21 | AB14: 21 | AC14: 24 | AD14: 24 | AE14: 24
A15: D | B15: INDUSTRIA MANUFACTURERA | C15: 506 | D15: 502 | E15: 500 | F15: 521 | G15: 459 | H15: 449 | I15: 395 | J15: 420 | K15: 445 | L15: 500 | M15: 544 | N15: 574 | O15: 596 | P15: 608 | Q15: 608 | R15: 637 | S15: 629 | T15: 630 | U15: 632 | V15: 674 | W15: 684 | X15: 658 | Y15: 671 | Z15: 636 | AA15: 616 | AB15: 646 | AC15: 747 | AD15: 780 | AE15: 736
A16: 15 | B16: Alimentos | C16: 202 | D16: 191 | E16: 187 | F16: 199 | G16: 172 | H16: 173 | I16: 152 | J16: 156 | K16: 167 | L16: 194 | M16: 199 | N16: 209 | O16: 215 | P16: 219 | Q16: 220 | R16: 219 | S16: 223 | T16: 223 | U16: 224 | V16: 238 | W16: 246 | X16: 225 | Y16: 227 | Z16: 218 | AA16: 206 | AB16: 214 | AC16: 251 | AD16: 260 | AE16: 248
A17: 16 | B17: Tabaco | C17: s.d. | D17: s.d. | E17: s.d. | F17: s.d. | G17: s.d. | H17: s.d. | I17: 4 | J17: 5 | K17: 4 | L17: 4 | M17: 6 | N17: 6 | O17: 6 | P17: 6 | Q17: 6 | R17: 6 | S17: 6 | T17: 5 | U17: 6 | V17: 6 | W17: 6 | X17: 5 | Y17: 5 | Z17: 5 | AA17: 5 | AB17: 4 | AC17: s.d. | AD17: s.d. | AE17: s.d.
A18: 17 | B18: Productos textiles | C18: 23 | D18: 19 | E18: 19 | F18: 17 | G18: 15 | H18: 13 | I18: 10 | J18: 11 | K18: 11 | L18: 12 | M18: 12 | N18: 12 | O18: 10 | P18: 10 | Q18: 11 | R18: 14 | S18: 15 | T18: 14 | U18: 13 | V18: 12 | W18: 16 | X18: 15 | Y18: 17 | Z18: 14 | AA18: 13 | AB18: 13 | AC18: 14 | AD18: 15 | AE18: 16
A19: 18 | B19: Confecciones | C19: 16 | D19: 15 | E19: 16 | F19: 17 | G19: 17 | H19: 17 | I19: 16 | J19: 15 | K19: 11 | L19: 13 | M19: 15 | N19: 12 | O19: 14 | P19: 18 | Q19: 19 | R19: 21 | S19: 20 | T19: 18 | U19: 14 | V19: 13 | W19: 11 | X19: 8 | Y19: 12 | Z19: 9 | AA19: 8 | AB19: 8 | AC19: 11 | AD19: 15 | AE19: 12
A20: 19 | B20: Calzado y productos de cuero | C20: 4 | D20: 5 | E20: 6 | F20: 6 | G20: 6 | H20: 7 | I20: 7 | J20: 4 | K20: s.d. | L20: 4 | M20: 5 | N20: 5 | O20: 4 | P20: 4 | Q20: 5 | R20: s.d. | S20: 4 | T20: 4 | U20: s.d. | V20: s.d. | W20: s.d. | X20: s.d. | Y20: 4 | Z20: s.d. | AA20: s.d. | AB20: s.d. | AC20: s.d. | AD20: 7 | AE20: 4
A21: 20 | B21: Madera | C21: 52 | D21: 58 | E21: 62 | F21: 63 | G21: 61 | H21: 64 | I21: 55 | J21: 81 | K21: 94 | L21: 96 | M21: 110 | N21: 130 | O21: 140 | P21: 135 | Q21: 130 | R21: 136 | S21: 134 | T21: 137 | U21: 151 | V21: 176 | W21: 178 | X21: 174 | Y21: 168 | Z21: 165 | AA21: 161 | AB21: 171 | AC21: 197 | AD21: 200 | AE21: 196
A22: 21 | B22: Papel | C22: 8 | D22: 8 | E22: 8 | F22: 9 | G22: 9 | H22: 6 | I22: 5 | J22: 5 | K22: 6 | L22: 6 | M22: 4 | N22: 4 | O22: 5 | P22: s.d. | Q22: s.d. | R22: s.d. | S22: s.d. | T22: s.d. | U22: s.d. | V22: s.d. | W22: s.d. | X22: s.d. | Y22: s.d. | Z22: s.d. | AA22: s.d. | AB22: s.d. | AC22: s.d. | AD22: s.d. | AE22: s.d.
A23: 22 | B23: Edición | C23: 31 | D23: 34 | E23: 33 | F23: 35 | G23: 31 | H23: 30 | I23: 30 | J23: 27 | K23: 24 | L23: 26 | M23: 27 | N23: 32 | O23: 30 | P23: 32 | Q23: 33 | R23: 35 | S23: 30 | T23: 29 | U23: 30 | V23: 29 | W23: 25 | X23: 27 | Y23: 32 | Z23: 31 | AA23: 30 | AB23: 27 | AC23: 28 | AD23: 33 | AE23: 28
A24: 23 | B24: Productos de petróleo | C24: 5 | D24: 4 | E24: 4 | F24: s.d. | G24: s.d. | H24: s.d. | I24: s.d. | J24: s.d. | K24: s.d. | L24: s.d. | M24: s.d. | N24: s.d. | O24: s.d. | P24: s.d. | Q24: s.d. | R24: s.d. | S24: s.d. | T24: s.d. | U24: s.d. | V24: s.d. | W24: s.d. | X24: s.d. | Y24: s.d. | Z24: s.d. | AA24: s.d. | AB24: s.d. | AC24: s.d. | AD24: s.d. | AE24: s.d.
A25: 24 | B25: Productos químicos | C25: 52 | D25: 52 | E25: 56 | F25: 63 | G25: 55 | H25: 57 | I25: 51 | J25: 44 | K25: 46 | L25: 47 | M25: 48 | N25: 55 | O25: 53 | P25: 55 | Q25: 53 | R25: 54 | S25: 51 | T25: 47 | U25: 50 | V25: 50 | W25: 52 | X25: 51 | Y25: 53 | Z25: 53 | AA25: 56 | AB25: 59 | AC25: 60 | AD25: 59 | AE25: 59
A26: 25 | B26: Productos de caucho y plástico | C26: 7 | D26: 7 | E26: 5 | F26: 6 | G26: s.d. | H26: 4 | I26: s.d. | J26: 4 | K26: 4 | L26: 6 | M26: 8 | N26: 7 | O26: 6 | P26: 5 | Q26: 9 | R26: 8 | S26: 8 | T26: 9 | U26: 8 | V26: 8 | W26: 9 | X26: 9 | Y26: 7 | Z26: 6 | AA26: 6 | AB26: 10 | AC26: 14 | AD26: 14 | AE26: 12
A27: 26 | B27: Otros minerales no metálicos | C27: 17 | D27: 16 | E27: 14 | F27: 17 | G27: 19 | H27: 12 | I27: 9 | J27: 10 | K27: 9 | L27: 11 | M27: 10 | N27: 13 | O27: 12 | P27: 12 | Q27: 15 | R27: 20 | S27: 16 | T27: 20 | U27: 20 | V27: 21 | W27: 20 | X27: 19 | Y27: 21 | Z27: 22 | AA27: 22 | AB27: 21 | AC27: 24 | AD27: 31 | AE27: 28
A28: 27 | B28: Metales comunes | C28: 5 | D28: 8 | E28: 5 | F28: 7 | G28: s.d. | H28: 4 | I28: s.d. | J28: s.d. | K28: s.d. | L28: s.d. | M28: s.d. | N28: s.d. | O28: s.d. | P28: s.d. | Q28: s.d. | R28: s.d. | S28: s.d. | T28: s.d. | U28: s.d. | V28: s.d. | W28: s.d. | X28: s.d. | Y28: s.d. | Z28: s.d. | AA28: s.d. | AB28: s.d. | AC28: s.d. | AD28: s.d. | AE28: s.d.
A29: 28 | B29: Otros productos de metal | C29: 28 | D29: 31 | E29: 38 | F29: 33 | G29: 29 | H29: 25 | I29: 24 | J29: 25 | K29: 30 | L29: 39 | M29: 45 | N29: 43 | O29: 49 | P29: 46 | Q29: 44 | R29: 52 | S29: 53 | T29: 57 | U29: 54 | V29: 54 | W29: 55 | X29: 58 | Y29: 56 | Z29: 50 | AA29: 54 | AB29: 54 | AC29: 59 | AD29: 61 | AE29: 57
A30: 29 | B30: Maquinaria y equipo | C30: 11 | D30: 16 | E30: 12 | F30: 9 | G30: 9 | H30: 7 | I30: 6 | J30: 8 | K30: 8 | L30: 7 | M30: 10 | N30: 9 | O30: 11 | P30: 10 | Q30: 8 | R30: 11 | S30: 11 | T30: 13 | U30: 11 | V30: 11 | W30: 13 | X30: 8 | Y30: 12 | Z30: 9 | AA30: 10 | AB30: 15 | AC30: 18 | AD30: 21 | AE30: 13
A31: 30 | B31: Maquinaria de oficina | C31: s.d. | D31: s.d. | E31: s.d. | F31: s.d. | G31: s.d. | H31: s.d. | I31: s.d. | J31: s.d. | K31: s.d. | L31: s.d. | M31: s.d. | N31: s.d. | O31: s.d. | P31: s.d. | Q31: s.d. | R31: s.d. | S31: s.d. | T31: s.d. | U31: s.d. | V31: s.d. | W31: s.d. | X31: s.d. | Y31: s.d. | Z31: s.d. | AA31: s.d. | AB31: 4 | AC31: 4 | AD31: 4 | AE31: 4
A32: 31 | B32: Aparatos eléctricos | C32: 6 | D32: 5 | E32: 5 | F32: 5 | G32: s.d. | H32: s.d. | I32: s.d. | J32: s.d. | K32: s.d. | L32: s.d. | M32: s.d. | N32: s.d. | O32: s.d. | P32: 6 | Q32: 5 | R32: 6 | S32: 6 | T32: s.d. | U32: s.d. | V32: 4 | W32: s.d. | X32: s.d. | Y32: s.d. | Z32: 5 | AA32: s.d. | AB32: s.d. | AC32: 4 | AD32: s.d. | AE32: s.d.
A33: 32 | B33: Radio y televisión | C33: 4 | D33: s.d. | E33: s.d. | F33: s.d. | G33: s.d. | H33: s.d. | I33: s.d. | J33: s.d. | K33: s.d. | L33: s.d. | M33: s.d. | N33: s.d. | O33: s.d. | P33: s.d. | Q33: s.d. | R33: s.d. | S33: s.d. | T33: s.d. | U33: s.d. | V33: s.d. | W33: s.d. | X33: s.d. | Y33: s.d. | Z33: s.d. | AA33: s.d. | AB33: s.d. | AC33: s.d. | AD33: s.d. | AE33: s.d.
A34: 33 | B34: Instrumentos médicos | C34: 4 | D34: s.d. | E34: s.d. | F34: 4 | G34: s.d. | H34: s.d. | I34: s.d. | J34: s.d. | K34: s.d. | L34: s.d. | M34: s.d. | N34: s.d. | O34: s.d. | P34: s.d. | Q34: s.d. | R34: s.d. | S34: s.d. | T34: s.d. | U34: s.d. | V34: s.d. | W34: s.d. | X34: s.d. | Y34: s.d. | Z34: s.d. | AA34: s.d. | AB34: s.d. | AC34: s.d. | AD34: s.d. | AE34: s.d.
A35: 34 | B35: Automotores | C35: 10 | D35: 5 | E35: s.d. | F35: s.d. | G35: s.d. | H35: s.d. | I35: s.d. | J35: 5 | K35: s.d. | L35: 5 | M35: 6 | N35: 6 | O35: 6 | P35: 7 | Q35: 6 | R35: 7 | S35: 7 | T35: 7 | U35: 6 | V35: 5 | W35: 5 | X35: 7 | Y35: 7 | Z35: 4 | AA35: 4 | AB35: 5 | AC35: 7 | AD35: 8 | AE35: 8
A36: 35 | B36: Otros equipo de transporte | C36: s.d. | D36: 4 | E36: 5 | F36: 4 | G36: s.d. | H36: s.d. | I36: s.d. | J36: s.d. | K36: s.d. | L36: s.d. | M36: s.d. | N36: s.d. | O36: 4 | P36: 6 | Q36: 6 | R36: 7 | S36: 5 | T36: 6 | U36: 6 | V36: 6 | W36: 5 | X36: 5 | Y36: 5 | Z36: 5 | AA36: s.d. | AB36: s.d. | AC36: s.d. | AD36: s.d. | AE36: s.d.
A37: 36 | B37: Muebles | C37: 17 | D37: 17 | E37: 14 | F37: 16 | G37: 12 | H37: 14 | I37: 11 | J37: 10 | K37: 15 | L37: 21 | M37: 27 | N37: 22 | O37: 24 | P37: 24 | Q37: 25 | R37: 28 | S37: 30 | T37: 30 | U37: 27 | V37: 30 | W37: 29 | X37: 31 | Y37: 32 | Z37: 30 | AA37: 26 | AB37: 27 | AC37: 38 | AD37: 36 | AE37: 35
A38: 37 | B38: Reciclamiento de desperdicios y desechos | C38: s.d. | D38: s.d. | E38: s.d. | F38: s.d. | G38: s.d. | H38: s.d. | I38: s.d. | J38: s.d. | K38: s.d. | L38: s.d. | M38: s.d. | N38: s.d. | O38: s.d. | P38: s.d. | Q38: s.d. | R38: s.d. | S38: s.d. | T38: s.d. | U38: s.d. | V38: s.d. | W38: s.d. | X38: s.d. | Y38: s.d. | Z38: s.d. | AA38: s.d. | AB38: s.d. | AC38: s.d. | AD38: s.d. | AE38: s.d.
A39: E | B39: ELECTRICIDAD, GAS Y AGUA | C39: 22 | D39: 24 | E39: 22 | F39: 24 | G39: 20 | H39: 19 | I39: 19 | J39: 18 | K39: 19 | L39: 20 | M39: 21 | N39: 21 | O39: 21 | P39: 22 | Q39: 20 | R39: 22 | S39: 23 | T39: 22 | U39: 20 | V39: 22 | W39: 21 | X39: 24 | Y39: 21 | Z39: 20 | AA39: 20 | AB39: 23 | AC39: 26 | AD39: 25 | AE39: 25
A40: 40 | B40: Electricidad, gas y agua | C40: 11 | D40: 12 | E40: 11 | F40: 12 | G40: 8 | H40: 6 | I40: 6 | J40: 5 | K40: 7 | L40: 6 | M40: 7 | N40: 7 | O40: 7 | P40: 8 | Q40: 7 | R40: 8 | S40: 10 | T40: 10 | U40: 8 | V40: 10 | W40: 10 | X40: 13 | Y40: 10 | Z40: 9 | AA40: 9 | AB40: 12 | AC40: 15 | AD40: 13 | AE40: 14
A41: 41 | B41: Captación, depuración y distribución de agua | C41: 11 | D41: 12 | E41: 11 | F41: 12 | G41: 12 | H41: 13 | I41: 13 | J41: 13 | K41: 12 | L41: 14 | M41: 14 | N41: 14 | O41: 14 | P41: 14 | Q41: 13 | R41: 14 | S41: 13 | T41: 12 | U41: 12 | V41: 12 | W41: 11 | X41: 11 | Y41: 11 | Z41: 11 | AA41: 11 | AB41: 11 | AC41: 11 | AD41: 12 | AE41: 11
A42: F | B42: CONSTRUCCION | C42: 226 | D42: 220 | E42: 236 | F42: 217 | G42: 205 | H42: 165 | I42: 156 | J42: 177 | K42: 224 | L42: 299 | M42: 322 | N42: 378 | O42: 380 | P42: 384 | Q42: 388 | R42: 417 | S42: 437 | T42: 443 | U42: 433 | V42: 432 | W42: 442 | X42: 452 | Y42: 444 | Z42: 437 | AA42: 425 | AB42: 444 | AC42: 476 | AD42: 467 | AE42: 405
A43: 45 | B43: Construccion | C43: 226 | D43: 220 | E43: 236 | F43: 217 | G43: 205 | H43: 165 | I43: 156 | J43: 177 | K43: 224 | L43: 299 | M43: 322 | N43: 378 | O43: 380 | P43: 384 | Q43: 388 | R43: 417 | S43: 437 | T43: 443 | U43: 433 | V43: 432 | W43: 442 | X43: 452 | Y43: 444 | Z43: 437 | AA43: 425 | AB43: 444 | AC43: 476 | AD43: 467 | AE43: 405
A44: G | B44: COMERCIO AL POR MAYOR Y AL POR MENOR | C44: 1678 | D44: 1646 | E44: 1657 | F44: 1599 | G44: 1537 | H44: 1440 | I44: 1329 | J44: 1461 | K44: 1636 | L44: 1850 | M44: 2007 | N44: 2142 | O44: 2364 | P44: 2464 | Q44: 2500 | R44: 2709 | S44: 2783 | T44: 2823 | U44: 2884 | V44: 2975 | W44: 3003 | X44: 3071 | Y44: 3083 | Z44: 2904 | AA44: 2785 | AB44: 2784 | AC44: 3162 | AD44: 3351 | AE44: 3056
A45: 50 | B45: Vta y reparación de vehículos. vta por menor de combustible | C45: 224 | D45: 221 | E45: 239 | F45: 250 | G45: 233 | H45: 218 | I45: 194 | J45: 216 | K45: 232 | L45: 261 | M45: 277 | N45: 284 | O45: 315 | P45: 339 | Q45: 338 | R45: 354 | S45: 365 | T45: 370 | U45: 370 | V45: 381 | W45: 385 | X45: 397 | Y45: 409 | Z45: 377 | AA45: 376 | AB45: 379 | AC45: 430 | AD45: 449 | AE45: 427
A46: 51 | B46: Comercio al por mayor | C46: 349 | D46: 349 | E46: 363 | F46: 342 | G46: 312 | H46: 292 | I46: 268 | J46: 284 | K46: 305 | L46: 341 | M46: 363 | N46: 387 | O46: 406 | P46: 405 | Q46: 418 | R46: 436 | S46: 447 | T46: 442 | U46: 461 | V46: 468 | W46: 476 | X46: 474 | Y46: 477 | Z46: 455 | AA46: 456 | AB46: 468 | AC46: 541 | AD46: 563 | AE46: 536
A47: 52 | B47: Comercio al por menor | C47: 1105 | D47: 1076 | E47: 1055 | F47: 1007 | G47: 992 | H47: 930 | I47: 867 | J47: 961 | K47: 1099 | L47: 1248 | M47: 1367 | N47: 1471 | O47: 1643 | P47: 1720 | Q47: 1744 | R47: 1919 | S47: 1971 | T47: 2011 | U47: 2053 | V47: 2126 | W47: 2142 | X47: 2200 | Y47: 2197 | Z47: 2072 | AA47: 1953 | AB47: 1937 | AC47: 2191 | AD47: 2339 | AE47: 2093
A48: H | B48: HOTELERIA Y RESTAURANTES | C48: 160 | D48: 152 | E48: 162 | F48: 153 | G48: 140 | H48: 133 | I48: 120 | J48: 128 | K48: 151 | L48: 187 | M48: 201 | N48: 245 | O48: 275 | P48: 280 | Q48: 322 | R48: 339 | S48: 355 | T48: 366 | U48: 387 | V48: 382 | W48: 399 | X48: 407 | Y48: 393 | Z48: 376 | AA48: 327 | AB48: 328 | AC48: 406 | AD48: 436 | AE48: 397
A49: 55 | B49: Servicios de hoteleria y restaurantes | C49: 160 | D49: 152 | E49: 162 | F49: 153 | G49: 140 | H49: 133 | I49: 120 | J49: 128 | K49: 151 | L49: 187 | M49: 201 | N49: 245 | O49: 275 | P49: 280 | Q49: 322 | R49: 339 | S49: 355 | T49: 366 | U49: 387 | V49: 382 | W49: 399 | X49: 407 | Y49: 393 | Z49: 376 | AA49: 327 | AB49: 328 | AC49: 406 | AD49: 436 | AE49: 397
A50: I | B50: SERVICIOS DE TRANSPORTE, DE ALMACENAMIENTO Y DE COMUNICACIONES | C50: 312 | D50: 316 | E50: 349 | F50: 367 | G50: 333 | H50: 316 | I50: 306 | J50: 333 | K50: 367 | L50: 426 | M50: 464 | N50: 500 | O50: 561 | P50: 567 | Q50: 614 | R50: 639 | S50: 632 | T50: 643 | U50: 660 | V50: 656 | W50: 657 | X50: 670 | Y50: 661 | Z50: 644 | AA50: 640 | AB50: 634 | AC50: 714 | AD50: 715 | AE50: 680
A51: 60 | B51: Transporte ferroviario y automotor y por tuberias | C51: 190 | D51: 179 | E51: 208 | F51: 215 | G51: 184 | H51: 172 | I51: 165 | J51: 183 | K51: 207 | L51: 254 | M51: 296 | N51: 327 | O51: 374 | P51: 375 | Q51: 422 | R51: 432 | S51: 425 | T51: 432 | U51: 446 | V51: 439 | W51: 446 | X51: 451 | Y51: 450 | Z51: 438 | AA51: 434 | AB51: 434 | AC51: 487 | AD51: 495 | AE51: 483
A52: 61 | B52: Transporte marítimo y fluvial | C52: s.d. | D52: s.d. | E52: s.d. | F52: s.d. | G52: s.d. | H52: s.d. | I52: s.d. | J52: s.d. | K52: s.d. | L52: s.d. | M52: s.d. | N52: s.d. | O52: s.d. | P52: s.d. | Q52: s.d. | R52: s.d. | S52: s.d. | T52: s.d. | U52: s.d. | V52: s.d. | W52: s.d. | X52: s.d. | Y52: s.d. | Z52: s.d. | AA52: s.d. | AB52: s.d. | AC52: s.d. | AD52: s.d. | AE52: s.d.
A53: 62 | B53: Transporte aéreo de cargas y de pasajeros | C53: s.d. | D53: s.d. | E53: s.d. | F53: s.d. | G53: s.d. | H53: s.d. | I53: s.d. | J53: s.d. | K53: s.d. | L53: s.d. | M53: s.d. | N53: s.d. | O53: s.d. | P53: s.d. | Q53: s.d. | R53: s.d. | S53: s.d. | T53: s.d. | U53: s.d. | V53: s.d. | W53: s.d. | X53: s.d. | Y53: s.d. | Z53: s.d. | AA53: s.d. | AB53: s.d. | AC53: s.d. | AD53: s.d. | AE53: s.d.
A54: 63 | B54: Manipulación de carga, almacenamiento y depósito | C54: 66 | D54: 72 | E54: 79 | F54: 77 | G54: 71 | H54: 68 | I54: 69 | J54: 75 | K54: 86 | L54: 97 | M54: 95 | N54: 96 | O54: 116 | P54: 125 | Q54: 124 | R54: 134 | S54: 139 | T54: 149 | U54: 147 | V54: 152 | W54: 148 | X54: 152 | Y54: 151 | Z54: 141 | AA54: 135 | AB54: 136 | AC54: 152 | AD54: 146 | AE54: 127
A55: 64 | B55: Telecomunicaciones y correos | C55: 47 | D55: 55 | E55: 56 | F55: 68 | G55: 71 | H55: 69 | I55: 65 | J55: 67 | K55: 66 | L55: 65 | M55: 63 | N55: 67 | O55: 63 | P55: 57 | Q55: 59 | R55: 63 | S55: 60 | T55: 54 | U55: 60 | V55: 58 | W55: 56 | X55: 60 | Y55: 55 | Z55: 57 | AA55: 64 | AB55: 59 | AC55: 70 | AD55: 69 | AE55: 64
A56: J | B56: INTERMEDIACION FINANCIERA Y OTROS SERVICIOS FINANCIEROS | C56: 68 | D56: 78 | E56: 86 | F56: 93 | G56: 95 | H56: 99 | I56: 86 | J56: 90 | K56: 88 | L56: 103 | M56: 115 | N56: 125 | O56: 124 | P56: 115 | Q56: 115 | R56: 130 | S56: 124 | T56: 136 | U56: 131 | V56: 135 | W56: 137 | X56: 131 | Y56: 129 | Z56: 129 | AA56: 132 | AB56: 134 | AC56: 129 | AD56: 136 | AE56: 128
A57: 65 | B57: Intermediacion financiera y otros servicios financieros | C57: 30 | D57: 35 | E57: 36 | F57: 34 | G57: 38 | H57: 38 | I57: 33 | J57: 31 | K57: 32 | L57: 37 | M57: 34 | N57: 42 | O57: 42 | P57: 39 | Q57: 43 | R57: 52 | S57: 51 | T57: 55 | U57: 55 | V57: 53 | W57: 55 | X57: 49 | Y57: 48 | Z57: 50 | AA57: 50 | AB57: 50 | AC57: 47 | AD57: 48 | AE57: 48
A58: 66 | B58: Seguros | C58: 24 | D58: 29 | E58: 31 | F58: 36 | G58: 37 | H58: 39 | I58: 37 | J58: 38 | K58: 33 | L58: 40 | M58: 46 | N58: 47 | O58: 44 | P58: 35 | Q58: 33 | R58: 37 | S58: 34 | T58: 35 | U58: 28 | V58: 31 | W58: 34 | X58: 29 | Y58: 29 | Z58: 29 | AA58: 33 | AB58: 36 | AC58: 32 | AD58: 35 | AE58: 32
A59: 67 | B59: Servicios auxiliares a la actividad financiera | C59: 14 | D59: 14 | E59: 19 | F59: 23 | G59: 20 | H59: 22 | I59: 16 | J59: 21 | K59: 23 | L59: 26 | M59: 35 | N59: 36 | O59: 38 | P59: 41 | Q59: 39 | R59: 41 | S59: 39 | T59: 46 | U59: 48 | V59: 51 | W59: 48 | X59: 53 | Y59: 52 | Z59: 50 | AA59: 49 | AB59: 48 | AC59: 50 | AD59: 53 | AE59: 48
A60: K | B60: SERVICIOS INMOBILIARIOS, EMPRESARIALES Y DE ALQUILER | C60: 962 | D60: 975 | E60: 1007 | F60: 992 | G60: 924 | H60: 943 | I60: 855 | J60: 897 | K60: 994 | L60: 1110 | M60: 1130 | N60: 1137 | O60: 1173 | P60: 1154 | Q60: 1179 | R60: 1227 | S60: 1227 | T60: 1223 | U60: 1188 | V60: 1190 | W60: 1158 | X60: 1172 | Y60: 1080 | Z60: 1054 | AA60: 973 | AB60: 983 | AC60: 1098 | AD60: 1219 | AE60: 1013
A61: 70 | B61: Servicios inmobiliarios | C61: 426 | D61: 427 | E61: 434 | F61: 430 | G61: 392 | H61: 382 | I61: 353 | J61: 374 | K61: 403 | L61: 403 | M61: 410 | N61: 398 | O61: 398 | P61: 399 | Q61: 410 | R61: 435 | S61: 441 | T61: 441 | U61: 413 | V61: 398 | W61: 388 | X61: 385 | Y61: 347 | Z61: 352 | AA61: 321 | AB61: 314 | AC61: 348 | AD61: 341 | AE61: 303
A62: 71 | B62: Alquiler de equipo de transporte y de maquinaria | C62: 13 | D62: 10 | E62: s.d. | F62: s.d. | G62: s.d. | H62: s.d. | I62: 6 | J62: 7 | K62: s.d. | L62: s.d. | M62: s.d. | N62: s.d. | O62: s.d. | P62: s.d. | Q62: 22 | R62: 23 | S62: 19 | T62: 20 | U62: 19 | V62: 20 | W62: 19 | X62: 24 | Y62: 19 | Z62: 18 | AA62: 15 | AB62: 14 | AC62: 15 | AD62: 18 | AE62: 19
A63: 72 | B63: Actividades de informática | C63: 12 | D63: 14 | E63: 19 | F63: 20 | G63: 13 | H63: 12 | I63: s.d. | J63: s.d. | K63: 15 | L63: 25 | M63: 23 | N63: 28 | O63: 32 | P63: 33 | Q63: 34 | R63: 31 | S63: 35 | T63: 44 | U63: 46 | V63: 39 | W63: 41 | X63: 41 | Y63: 44 | Z63: 44 | AA63: 47 | AB63: 65 | AC63: 72 | AD63: 73 | AE63: 69
A64: 73 | B64: Investigación y desarrollo | C64: 5 | D64: s.d. | E64: s.d. | F64: s.d. | G64: s.d. | H64: s.d. | I64: s.d. | J64: s.d. | K64: s.d. | L64: s.d. | M64: s.d. | N64: s.d. | O64: s.d. | P64: s.d. | Q64: 6 | R64: 8 | S64: 9 | T64: 9 | U64: 11 | V64: 12 | W64: 13 | X64: 13 | Y64: 12 | Z64: 9 | AA64: 7 | AB64: 7 | AC64: 7 | AD64: 9 | AE64: 7
A65: 74 | B65: Servicios jurídicos, contables y otros servicios a empresas | C65: 501 | D65: 516 | E65: 535 | F65: 519 | G65: 500 | H65: 525 | I65: 469 | J65: 491 | K65: 552 | L65: 659 | M65: 668 | N65: 679 | O65: 709 | P65: 682 | Q65: 693 | R65: 714 | S65: 710 | T65: 697 | U65: 688 | V65: 712 | W65: 689 | X65: 700 | Y65: 651 | Z65: 624 | AA65: 576 | AB65: 575 | AC65: 648 | AD65: 770 | AE65: 606
A66: 75 | B66: Agencias de empleo eventual | C66: 5 | D66: s.d. | E66: 5 | F66: 7 | G66: 10 | H66: 13 | I66: 11 | J66: 9 | K66: 12 | L66: 10 | M66: 11 | N66: 12 | O66: 14 | P66: 16 | Q66: 14 | R66: 16 | S66: 13 | T66: 12 | U66: 11 | V66: 9 | W66: 8 | X66: 9 | Y66: 7 | Z66: 7 | AA66: 7 | AB66: 8 | AC66: 8 | AD66: 8 | AE66: 9
A67: M | B67: ENSEÑANZA | C67: 103 | D67: 108 | E67: 116 | F67: 115 | G67: 100 | H67: 94 | I67: 92 | J67: 99 | K67: 102 | L67: 112 | M67: 114 | N67: 122 | O67: 120 | P67: 123 | Q67: 123 | R67: 125 | S67: 125 | T67: 121 | U67: 127 | V67: 126 | W67: 131 | X67: 142 | Y67: 145 | Z67: 146 | AA67: 133 | AB67: 139 | AC67: 144 | AD67: 162 | AE67: 148
A68: 80 | B68: Enseñanza | C68: 103 | D68: 108 | E68: 116 | F68: 115 | G68: 100 | H68: 94 | I68: 92 | J68: 99 | K68: 102 | L68: 112 | M68: 114 | N68: 122 | O68: 120 | P68: 123 | Q68: 123 | R68: 125 | S68: 125 | T68: 121 | U68: 127 | V68: 126 | W68: 131 | X68: 142 | Y68: 145 | Z68: 146 | AA68: 133 | AB68: 139 | AC68: 144 | AD68: 162 | AE68: 148
A69: N | B69: SERVICIOS SOCIALES Y DE SALUD | C69: 310 | D69: 320 | E69: 334 | F69: 317 | G69: 303 | H69: 303 | I69: 272 | J69: 278 | K69: 298 | L69: 320 | M69: 332 | N69: 344 | O69: 354 | P69: 389 | Q69: 401 | R69: 416 | S69: 434 | T69: 448 | U69: 467 | V69: 471 | W69: 488 | X69: 494 | Y69: 523 | Z69: 553 | AA69: 526 | AB69: 529 | AC69: 557 | AD69: 563 | AE69: 510
A70: 85 | B70: Servicios sociales y de salud | C70: 310 | D70: 320 | E70: 334 | F70: 317 | G70: 303 | H70: 303 | I70: 272 | J70: 278 | K70: 298 | L70: 320 | M70: 332 | N70: 344 | O70: 354 | P70: 389 | Q70: 401 | R70: 416 | S70: 434 | T70: 448 | U70: 467 | V70: 471 | W70: 488 | X70: 494 | Y70: 523 | Z70: 553 | AA70: 526 | AB70: 529 | AC70: 557 | AD70: 563 | AE70: 510
A71: O | B71: SERVICIOS COMUNITARIOS, SOCIALES Y PERSONALES N.C.P. | C71: 556 | D71: 541 | E71: 534 | F71: 502 | G71: 472 | H71: 506 | I71: 476 | J71: 500 | K71: 524 | L71: 611 | M71: 614 | N71: 583 | O71: 580 | P71: 575 | Q71: 578 | R71: 607 | S71: 608 | T71: 640 | U71: 635 | V71: 628 | W71: 639 | X71: 642 | Y71: 613 | Z71: 593 | AA71: 557 | AB71: 555 | AC71: 606 | AD71: 633 | AE71: 568
A72: 90 | B72: Eliminación de desperdicios | C72: 10 | D72: 12 | E72: 9 | F72: 7 | G72: 5 | H72: 6 | I72: 6 | J72: 5 | K72: 5 | L72: 7 | M72: 8 | N72: 6 | O72: 6 | P72: 5 | Q72: 6 | R72: 9 | S72: 7 | T72: 8 | U72: 6 | V72: 6 | W72: 7 | X72: 7 | Y72: 6 | Z72: 8 | AA72: 7 | AB72: 7 | AC72: 8 | AD72: 5 | AE72: 5
A73: 91 | B73: Servicios de organizaciones empresariales | C73: 215 | D73: 222 | E73: 223 | F73: 227 | G73: 216 | H73: 228 | I73: 222 | J73: 228 | K73: 230 | L73: 246 | M73: 254 | N73: 256 | O73: 261 | P73: 268 | Q73: 266 | R73: 271 | S73: 279 | T73: 287 | U73: 291 | V73: 291 | W73: 286 | X73: 292 | Y73: 288 | Z73: 281 | AA73: 273 | AB73: 281 | AC73: 296 | AD73: 296 | AE73: 279
A74: 92 | B74: Servicios culturales, deportivos y de esparcimiento | C74: 92 | D74: 81 | E74: 73 | F74: 64 | G74: 73 | H74: 72 | I74: 63 | J74: 68 | K74: 70 | L74: 86 | M74: 92 | N74: 106 | O74: 107 | P74: 119 | Q74: 123 | R74: 130 | S74: 134 | T74: 154 | U74: 153 | V74: 150 | W74: 167 | X74: 168 | Y74: 163 | Z74: 155 | AA74: 146 | AB74: 145 | AC74: 161 | AD74: 174 | AE74: 150
A75: 93 | B75: Servicios n.c.p. | C75: 239 | D75: 226 | E75: 229 | F75: 204 | G75: 178 | H75: 200 | I75: 185 | J75: 199 | K75: 219 | L75: 272 | M75: 260 | N75: 215 | O75: 206 | P75: 183 | Q75: 183 | R75: 197 | S75: 188 | T75: 191 | U75: 185 | V75: 181 | W75: 179 | X75: 175 | Y75: 156 | Z75: 149 | AA75: 131 | AB75: 122 | AC75: 141 | AD75: 158 | AE75: 134
B76: TOTAL | C76: 6595 | D76: 6496 | E76: 6643 | F76: 6569 | G76: 6124 | H76: 5963 | I76: 5559 | J76: 5891 | K76: 6449 | L76: 7313 | M76: 7680 | N76: 8033 | O76: 8530 | P76: 8673 | Q76: 8859 | R76: 9325 | S76: 9443 | T76: 9558 | U76: 9615 | V76: 9730 | W76: 9808 | X76: 9880 | Y76: 9768 | Z76: 9470 | AA76: 9095 | AB76: 9182 | AC76: 10136 | AD76: 10509 | AE76: 9602
A78: Notas:
A79: 1 - Las empresas se encuentran clasificadas por provincia según las zonas donde declaran que trabajan las personas.
A80: 2 - Las firmas con participación accionaria privada y estatal se incluye dentro del sector privado
A81: 3 - s/d : Dato no publicado para resguardar el secreto estadístico de las firmas
A82: Fuente: STEySS - Dirección Nacional de Estudios y Estadísticas Laborales - Observatorio de Empleo y Dinámica Empresarial, en base a SIPA.

Sheet Chaco
D1: Volver al índice
A2: CHACO
A3: Empresas del sector privado por rama de actividad - Activas en cada año
B4: Ramas de actividad | C4: 1996 | D4: 1997 | E4: 1998 | F4: 1999 | G4: 2000 | H4: 2001 | I4: 2002 | J4: 2003 | K4: 2004 | L4: 2005 | M4: 2006 | N4: 2007 | O4: 2008 | P4: 2009 | Q4: 2010 | R4: 2011 | S4: 2012 | T4: 2013 | U4: 2014 | V4: 2015 | W4: 2016 | X4: 2017 | Y4: 2018 | Z4: 2019 | AA4: 2020 | AB4: 2021 | AC4: 2022 | AD4: 2023 | AE4: 2024
D5: 2º Trim 1996 | F5: 3º Trim 1996 | H5: 4º Trim 1996 | J5: 1º Trim 1997 | L5: 2º Trim 1997 | N5: 3º Trim 1997 | P5: 4º Trim 1997 | R5: 1º Trim 1998
A6: A | B6: AGRICULTURA, GANADERIA, CAZA Y SILVICULTURA | C6: 3531 | D6: 3298 | E6: 3110 | F6: 3040 | G6: 3160 | H6: 2743 | I6: 2328 | J6: 2182 | K6: 2132 | L6: 2142 | M6: 2201 | N6: 2230 | O6: 2433 | P6: 2388 | Q6: 2029 | R6: 2268 | S6: 2326 | T6: 2380 | U6: 2317 | V6: 2232 | W6: 2223 | X6: 2214 | Y6: 2208 | Z6: 2173 | AA6: 2097 | AB6: 2081 | AC6: 2122 | AD6: 2181 | AE6: 2181
A7: 1 | B7: Agricultura y ganaderia | C7: 3328 | D7: 3118 | E7: 2922 | F7: 2851 | G7: 2923 | H7: 2542 | I7: 2181 | J7: 2040 | K7: 1998 | L7: 2013 | M7: 2077 | N7: 2097 | O7: 2268 | P7: 2195 | Q7: 1888 | R7: 1947 | S7: 1964 | T7: 2032 | U7: 2011 | V7: 1945 | W7: 1948 | X7: 1939 | Y7: 1940 | Z7: 1904 | AA7: 1852 | AB7: 1826 | AC7: 1879 | AD7: 1953 | AE7: 1938
A8: 2 | B8: Silvicultura, extracción de madera | C8: 203 | D8: 180 | E8: 188 | F8: 189 | G8: 237 | H8: 201 | I8: 147 | J8: 142 | K8: 134 | L8: 129 | M8: 124 | N8: 133 | O8: 165 | P8: 193 | Q8: 141 | R8: 321 | S8: 362 | T8: 348 | U8: 306 | V8: 287 | W8: 275 | X8: 275 | Y8: 268 | Z8: 269 | AA8: 245 | AB8: 255 | AC8: 243 | AD8: 228 | AE8: 243
A9: B | B9: PESCA Y SERVICIOS CONEXOS | C9: s.d. | D9: s.d. | E9: s.d. | F9: s.d. | G9: s.d. | H9: s.d. | I9: s.d. | J9: s.d. | K9: s.d. | L9: s.d. | M9: s.d. | N9: s.d. | O9: s.d. | P9: 4 | Q9: s.d. | R9: s.d. | S9: s.d. | T9: s.d. | U9: s.d. | V9: s.d. | W9: s.d. | X9: s.d. | Y9: s.d. | Z9: s.d. | AA9: s.d. | AB9: s.d. | AC9: s.d. | AD9: s.d. | AE9: s.d.
A10: 5 | B10: Pesca y actividades relacionadas con la pesca | C10: s.d. | D10: s.d. | E10: s.d. | F10: s.d. | G10: s.d. | H10: s.d. | I10: s.d. | J10: s.d. | K10: s.d. | L10: s.d. | M10: s.d. | N10: s.d. | O10: s.d. | P10: 4 | Q10: s.d. | R10: s.d. | S10: s.d. | T10: s.d. | U10: s.d. | V10: s.d. | W10: s.d. | X10: s.d. | Y10: s.d. | Z10: s.d. | AA10: s.d. | AB10: s.d. | AC10: s.d. | AD10: s.d. | AE10: s.d.
A11: C | B11: EXPLOTACION DE MINAS Y CANTERAS | C11: 5 | D11: 5 | E11: 7 | F11: 7 | G11: 7 | H11: 8 | I11: 7 | J11: 8 | K11: 6 | L11: 6 | M11: 6 | N11: 6 | O11: 8 | P11: 25 | Q11: 5 | R11: 8 | S11: 6 | T11: 8 | U11: 8 | V11: 7 | W11: 7 | X11: 6 | Y11: 5 | Z11: 6 | AA11: 6 | AB11: 6 | AC11: 7 | AD11: 10 | AE11: 10
A12: 11 | B12: Extraccion de petroleo crudo y gas natural | C12: s.d. | D12: s.d. | E12: s.d. | F12: s.d. | G12: s.d. | H12: s.d. | I12: s.d. | J12: s.d. | K12: s.d. | L12: s.d. | M12: s.d. | N12: s.d. | O12: s.d. | P12: s.d. | Q12: s.d. | R12: s.d. | S12: s.d. | T12: s.d. | U12: s.d. | V12: s.d. | W12: s.d. | X12: s.d. | Y12: s.d. | Z12: s.d. | AA12: s.d. | AB12: s.d. | AC12: s.d. | AD12: s.d. | AE12: s.d.
A13: 13 | B13: Extraccion de minerales metaliferos | C13: 0 | D13: 0 | E13: 0 | F13: 0 | G13: 0 | H13: 0 | I13: 0 | J13: 0 | K13: 0 | L13: 0 | M13: 0 | N13: 0 | O13: 0 | P13: 0 | Q13: 0 | R13: 0 | S13: 0 | T13: 0 | U13: 0 | V13: 0 | W13: 0 | X13: 0 | Y13: 0 | Z13: 0 | AA13: 0 | AB13: 0 | AC13: 0 | AD13: 0 | AE13: 0
A14: 14 | B14: Explotacion de otras minas y canteras | C14: s.d. | D14: s.d. | E14: s.d. | F14: s.d. | G14: s.d. | H14: s.d. | I14: s.d. | J14: s.d. | K14: s.d. | L14: s.d. | M14: s.d. | N14: s.d. | O14: s.d. | P14: s.d. | Q14: s.d. | R14: s.d. | S14: s.d. | T14: s.d. | U14: s.d. | V14: s.d. | W14: s.d. | X14: s.d. | Y14: s.d. | Z14: s.d. | AA14: s.d. | AB14: s.d. | AC14: s.d. | AD14: s.d. | AE14: s.d.
A15: D | B15: INDUSTRIA MANUFACTURERA | C15: 588 | D15: 579 | E15: 564 | F15: 574 | G15: 610 | H15: 519 | I15: 440 | J15: 492 | K15: 540 | L15: 556 | M15: 579 | N15: 613 | O15: 674 | P15: 754 | Q15: 668 | R15: 696 | S15: 699 | T15: 712 | U15: 669 | V15: 653 | W15: 677 | X15: 707 | Y15: 717 | Z15: 667 | AA15: 645 | AB15: 653 | AC15: 691 | AD15: 755 | AE15: 706
A16: 15 | B16: Alimentos | C16: 182 | D16: 174 | E16: 171 | F16: 165 | G16: 173 | H16: 135 | I16: 119 | J16: 129 | K16: 142 | L16: 146 | M16: 147 | N16: 157 | O16: 170 | P16: 166 | Q16: 166 | R16: 170 | S16: 176 | T16: 182 | U16: 171 | V16: 168 | W16: 176 | X16: 181 | Y16: 187 | Z16: 168 | AA16: 164 | AB16: 164 | AC16: 189 | AD16: 214 | AE16: 196
A17: 16 | B17: Tabaco | C17: s.d. | D17: s.d. | E17: s.d. | F17: s.d. | G17: s.d. | H17: s.d. | I17: s.d. | J17: s.d. | K17: s.d. | L17: s.d. | M17: s.d. | N17: s.d. | O17: s.d. | P17: s.d. | Q17: s.d. | R17: s.d. | S17: s.d. | T17: s.d. | U17: s.d. | V17: s.d. | W17: s.d. | X17: s.d. | Y17: s.d. | Z17: s.d. | AA17: s.d. | AB17: s.d. | AC17: s.d. | AD17: s.d. | AE17: s.d.
A18: 17 | B18: Productos textiles | C18: 60 | D18: 61 | E18: 64 | F18: 56 | G18: 50 | H18: 43 | I18: 37 | J18: 42 | K18: 40 | L18: 44 | M18: 42 | N18: 43 | O18: 48 | P18: 48 | Q18: 44 | R18: 47 | S18: 50 | T18: 49 | U18: 50 | V18: 52 | W18: 54 | X18: 50 | Y18: 50 | Z18: 49 | AA18: 49 | AB18: 54 | AC18: 50 | AD18: 51 | AE18: 48
A19: 18 | B19: Confecciones | C19: 12 | D19: 11 | E19: 11 | F19: 19 | G19: 17 | H19: 17 | I19: 13 | J19: 13 | K19: 12 | L19: 15 | M19: 13 | N19: 14 | O19: 15 | P19: 18 | Q19: 16 | R19: 18 | S19: 18 | T19: 21 | U19: 19 | V19: 18 | W19: 19 | X19: 17 | Y19: 13 | Z19: 13 | AA19: 12 | AB19: 11 | AC19: 11 | AD19: 16 | AE19: 13
A20: 19 | B20: Calzado | C20: 8 | D20: 11 | E20: 8 | F20: 8 | G20: 9 | H20: 4 | I20: 7 | J20: 8 | K20: 8 | L20: 8 | M20: 8 | N20: 10 | O20: 10 | P20: 13 | Q20: 11 | R20: 12 | S20: 11 | T20: 10 | U20: 10 | V20: 9 | W20: 9 | X20: 7 | Y20: 7 | Z20: 6 | AA20: 7 | AB20: 7 | AC20: 9 | AD20: 11 | AE20: 11
A21: 20 | B21: Madera | C21: 77 | D21: 79 | E21: 79 | F21: 81 | G21: 97 | H21: 79 | I21: 64 | J21: 82 | K21: 91 | L21: 91 | M21: 105 | N21: 116 | O21: 122 | P21: 136 | Q21: 105 | R21: 114 | S21: 117 | T21: 111 | U21: 89 | V21: 83 | W21: 94 | X21: 119 | Y21: 122 | Z21: 110 | AA21: 104 | AB21: 111 | AC21: 106 | AD21: 109 | AE21: 104
A22: 21 | B22: Papel | C22: 8 | D22: 6 | E22: 5 | F22: 5 | G22: 6 | H22: 5 | I22: 6 | J22: 6 | K22: 7 | L22: 7 | M22: 6 | N22: 5 | O22: 6 | P22: 6 | Q22: 5 | R22: 5 | S22: 6 | T22: 4 | U22: 6 | V22: 6 | W22: 6 | X22: 6 | Y22: 5 | Z22: 7 | AA22: 4 | AB22: 4 | AC22: 4 | AD22: 5 | AE22: 5
A23: 22 | B23: Edición | C23: 31 | D23: 28 | E23: 28 | F23: 28 | G23: 30 | H23: 31 | I23: 26 | J23: 27 | K23: 28 | L23: 34 | M23: 34 | N23: 33 | O23: 32 | P23: 31 | Q23: 34 | R23: 36 | S23: 33 | T23: 37 | U23: 33 | V23: 31 | W23: 32 | X23: 30 | Y23: 27 | Z23: 24 | AA23: 22 | AB23: 23 | AC23: 25 | AD23: 31 | AE23: 21
A24: 23 | B24: Productos de petróleo | C24: 5 | D24: 4 | E24: 4 | F24: 5 | G24: 5 | H24: 4 | I24: 4 | J24: 4 | K24: 4 | L24: s.d. | M24: s.d. | N24: s.d. | O24: s.d. | P24: s.d. | Q24: s.d. | R24: s.d. | S24: s.d. | T24: s.d. | U24: s.d. | V24: s.d. | W24: s.d. | X24: s.d. | Y24: s.d. | Z24: s.d. | AA24: s.d. | AB24: s.d. | AC24: s.d. | AD24: s.d. | AE24: s.d.
A25: 24 | B25: Productos químicos | C25: 54 | D25: 56 | E25: 49 | F25: 57 | G25: 60 | H25: 56 | I25: 49 | J25: 50 | K25: 49 | L25: 47 | M25: 49 | N25: 48 | O25: 43 | P25: 50 | Q25: 51 | R25: 52 | S25: 52 | T25: 54 | U25: 54 | V25: 54 | W25: 51 | X25: 48 | Y25: 47 | Z25: 51 | AA25: 52 | AB25: 50 | AC25: 52 | AD25: 53 | AE25: 54
A26: 25 | B26: Productos de caucho y plástico | C26: 12 | D26: 12 | E26: 11 | F26: 14 | G26: 14 | H26: 15 | I26: 14 | J26: 14 | K26: 15 | L26: 12 | M26: 12 | N26: 13 | O26: 14 | P26: 13 | Q26: 15 | R26: 16 | S26: 18 | T26: 18 | U26: 18 | V26: 18 | W26: 17 | X26: 18 | Y26: 17 | Z26: 18 | AA26: 16 | AB26: 14 | AC26: 17 | AD26: 21 | AE26: 21
A27: 26 | B27: Otros minerales no metálicos | C27: 25 | D27: 24 | E27: 25 | F27: 24 | G27: 46 | H27: 35 | I27: 22 | J27: 26 | K27: 29 | L27: 31 | M27: 33 | N27: 37 | O27: 43 | P27: 94 | Q27: 45 | R27: 39 | S27: 37 | T27: 38 | U27: 40 | V27: 40 | W27: 35 | X27: 36 | Y27: 35 | Z27: 35 | AA27: 34 | AB27: 40 | AC27: 43 | AD27: 46 | AE27: 38
A28: 27 | B28: Metales comunes | C28: 6 | D28: 8 | E28: 7 | F28: 5 | G28: 5 | H28: 4 | I28: s.d. | J28: 4 | K28: 5 | L28: 5 | M28: 4 | N28: 4 | O28: 8 | P28: 8 | Q28: 7 | R28: 7 | S28: 7 | T28: 7 | U28: 7 | V28: 6 | W28: 6 | X28: 5 | Y28: 5 | Z28: 4 | AA28: s.d. | AB28: s.d. | AC28: 4 | AD28: 5 | AE28: 4
A29: 28 | B29: Otros productos de metal | C29: 23 | D29: 24 | E29: 24 | F29: 22 | G29: 19 | H29: 21 | I29: 22 | J29: 22 | K29: 26 | L29: 27 | M29: 27 | N29: 28 | O29: 34 | P29: 38 | Q29: 38 | R29: 42 | S29: 42 | T29: 41 | U29: 42 | V29: 43 | W29: 47 | X29: 46 | Y29: 47 | Z29: 42 | AA29: 41 | AB29: 42 | AC29: 48 | AD29: 48 | AE29: 42
A30: 29 | B30: Maquinaria y equipo | C30: 19 | D30: 23 | E30: 19 | F30: 19 | G30: 15 | H30: 11 | I30: 10 | J30: 9 | K30: 12 | L30: 11 | M30: 12 | N30: 12 | O30: 15 | P30: 17 | Q30: 19 | R30: 18 | S30: 17 | T30: 23 | U30: 18 | V30: 16 | W30: 17 | X30: 18 | Y30: 17 | Z30: 18 | AA30: 18 | AB30: 15 | AC30: 16 | AD30: 17 | AE30: 16
A31: 30 | B31: Maquinaria de oficina | C31: s.d. | D31: s.d. | E31: s.d. | F31: s.d. | G31: s.d. | H31: s.d. | I31: s.d. | J31: s.d. | K31: s.d. | L31: s.d. | M31: s.d. | N31: s.d. | O31: s.d. | P31: s.d. | Q31: s.d. | R31: s.d. | S31: s.d. | T31: s.d. | U31: s.d. | V31: s.d. | W31: s.d. | X31: s.d. | Y31: s.d. | Z31: s.d. | AA31: s.d. | AB31: s.d. | AC31: s.d. | AD31: s.d. | AE31: s.d.
A32: 31 | B32: Aparatos eléctricos | C32: 5 | D32: 6 | E32: 7 | F32: 6 | G32: 5 | H32: 5 | I32: 4 | J32: 4 | K32: 8 | L32: 8 | M32: 8 | N32: 8 | O32: 7 | P32: 10 | Q32: 10 | R32: 9 | S32: 10 | T32: 10 | U32: 8 | V32: 10 | W32: 8 | X32: 8 | Y32: 9 | Z32: 6 | AA32: 5 | AB32: s.d. | AC32: 4 | AD32: s.d. | AE32: s.d.
A33: 32 | B33: Radio y televisión | C33: s.d. | D33: s.d. | E33: s.d. | F33: 5 | G33: 5 | H33: 4 | I33: s.d. | J33: s.d. | K33: s.d. | L33: s.d. | M33: s.d. | N33: s.d. | O33: s.d. | P33: s.d. | Q33: s.d. | R33: s.d. | S33: s.d. | T33: s.d. | U33: s.d. | V33: s.d. | W33: s.d. | X33: s.d. | Y33: s.d. | Z33: s.d. | AA33: s.d. | AB33: s.d. | AC33: s.d. | AD33: s.d. | AE33: s.d.
A34: 33 | B34: Instrumentos médicos | C34: s.d. | D34: s.d. | E34: s.d. | F34: s.d. | G34: s.d. | H34: s.d. | I34: s.d. | J34: s.d. | K34: 4 | L34: s.d. | M34: s.d. | N34: s.d. | O34: s.d. | P34: s.d. | Q34: s.d. | R34: s.d. | S34: s.d. | T34: s.d. | U34: s.d. | V34: s.d. | W34: s.d. | X34: s.d. | Y34: s.d. | Z34: s.d. | AA34: s.d. | AB34: s.d. | AC34: s.d. | AD34: s.d. | AE34: s.d.
A35: 34 | B35: Automotores | C35: 6 | D35: 6 | E35: 6 | F35: 7 | G35: 6 | H35: 4 | I35: 5 | J35: 7 | K35: 9 | L35: 11 | M35: 11 | N35: 12 | O35: 12 | P35: 12 | Q35: 11 | R35: 12 | S35: 11 | T35: 11 | U35: 12 | V35: 13 | W35: 14 | X35: 14 | Y35: 11 | Z35: 11 | AA35: 10 | AB35: 9 | AC35: 10 | AD35: 11 | AE35: 13
A36: 35 | B36: Otros equipo de transporte | C36: s.d. | D36: s.d. | E36: s.d. | F36: s.d. | G36: s.d. | H36: s.d. | I36: s.d. | J36: s.d. | K36: s.d. | L36: s.d. | M36: s.d. | N36: s.d. | O36: s.d. | P36: s.d. | Q36: s.d. | R36: 4 | S36: s.d. | T36: s.d. | U36: s.d. | V36: s.d. | W36: s.d. | X36: 4 | Y36: 5 | Z36: 4 | AA36: s.d. | AB36: s.d. | AC36: s.d. | AD36: s.d. | AE36: s.d.
A37: 36 | B37: Muebles | C37: 47 | D37: 39 | E37: 39 | F37: 42 | G37: 42 | H37: 40 | I37: 31 | J37: 39 | K37: 48 | L37: 49 | M37: 59 | N37: 61 | O37: 83 | P37: 84 | Q37: 79 | R37: 85 | S37: 81 | T37: 85 | U37: 81 | V37: 75 | W37: 83 | X37: 93 | Y37: 107 | Z37: 96 | AA37: 96 | AB37: 94 | AC37: 94 | AD37: 103 | AE37: 106
A38: 37 | B38: Reciclamiento de desperdicios y desechos | C38: s.d. | D38: s.d. | E38: s.d. | F38: s.d. | G38: s.d. | H38: s.d. | I38: s.d. | J38: s.d. | K38: s.d. | L38: s.d. | M38: s.d. | N38: s.d. | O38: s.d. | P38: s.d. | Q38: s.d. | R38: 4 | S38: 4 | T38: 4 | U38: 4 | V38: s.d. | W38: s.d. | X38: s.d. | Y38: s.d. | Z38: s.d. | AA38: s.d. | AB38: s.d. | AC38: s.d. | AD38: s.d. | AE38: s.d.
A39: E | B39: ELECTRICIDAD, GAS Y AGUA | C39: 13 | D39: 13 | E39: 14 | F39: 16 | G39: 19 | H39: 18 | I39: 18 | J39: 19 | K39: 19 | L39: 21 | M39: 19 | N39: 20 | O39: 22 | P39: 22 | Q39: 22 | R39: 19 | S39: 19 | T39: 19 | U39: 21 | V39: 22 | W39: 22 | X39: 21 | Y39: 21 | Z39: 20 | AA39: 22 | AB39: 21 | AC39: 21 | AD39: 22 | AE39: 22
A40: 40 | B40: Electricidad, gas y agua | C40: 6 | D40: 6 | E40: 6 | F40: 9 | G40: 11 | H40: 10 | I40: 10 | J40: 11 | K40: 11 | L40: 13 | M40: 11 | N40: 12 | O40: 14 | P40: 14 | Q40: 15 | R40: 12 | S40: 12 | T40: 13 | U40: 15 | V40: 16 | W40: 16 | X40: 16 | Y40: 16 | Z40: 15 | AA40: 15 | AB40: 15 | AC40: 15 | AD40: 16 | AE40: 16
A41: 41 | B41: Captación, depuración y distribución de agua | C41: 7 | D41: 7 | E41: 8 | F41: 7 | G41: 8 | H41: 8 | I41: 8 | J41: 8 | K41: 8 | L41: 8 | M41: 8 | N41: 8 | O41: 8 | P41: 8 | Q41: 7 | R41: 7 | S41: 7 | T41: 6 | U41: 6 | V41: 6 | W41: 6 | X41: 5 | Y41: 5 | Z41: 5 | AA41: 7 | AB41: 6 | AC41: 6 | AD41: 6 | AE41: 6
A42: F | B42: CONSTRUCCION | C42: 170 | D42: 190 | E42: 203 | F42: 179 | G42: 189 | H42: 160 | I42: 140 | J42: 167 | K42: 201 | L42: 244 | M42: 280 | N42: 334 | O42: 346 | P42: 366 | Q42: 391 | R42: 419 | S42: 394 | T42: 408 | U42: 422 | V42: 430 | W42: 427 | X42: 413 | Y42: 391 | Z42: 351 | AA42: 338 | AB42: 359 | AC42: 412 | AD42: 406 | AE42: 345
A43: 45 | B43: Construccion | C43: 170 | D43: 190 | E43: 203 | F43: 179 | G43: 189 | H43: 160 | I43: 140 | J43: 167 | K43: 201 | L43: 244 | M43: 280 | N43: 334 | O43: 346 | P43: 366 | Q43: 391 | R43: 419 | S43: 394 | T43: 408 | U43: 422 | V43: 430 | W43: 427 | X43: 413 | Y43: 391 | Z43: 351 | AA43: 338 | AB43: 359 | AC43: 412 | AD43: 406 | AE43: 345
A44: G | B44: COMERCIO AL POR MAYOR Y AL POR MENOR | C44: 1791 | D44: 1782 | E44: 1783 | F44: 1797 | G44: 1839 | H44: 1691 | I44: 1530 | J44: 1672 | K44: 1840 | L44: 1961 | M44: 2165 | N44: 2282 | O44: 2445 | P44: 2518 | Q44: 2575 | R44: 2739 | S44: 2850 | T44: 2941 | U44: 2938 | V44: 3048 | W44: 3165 | X44: 3161 | Y44: 3148 | Z44: 3028 | AA44: 2926 | AB44: 2987 | AC44: 3336 | AD44: 3521 | AE44: 3248
A45: 50 | B45: Vta y reparación de vehículos. vta por menor de combustible | C45: 254 | D45: 262 | E45: 258 | F45: 266 | G45: 268 | H45: 242 | I45: 227 | J45: 243 | K45: 267 | L45: 309 | M45: 333 | N45: 329 | O45: 355 | P45: 362 | Q45: 354 | R45: 393 | S45: 414 | T45: 410 | U45: 399 | V45: 418 | W45: 421 | X45: 416 | Y45: 417 | Z45: 403 | AA45: 404 | AB45: 415 | AC45: 453 | AD45: 470 | AE45: 455
A46: 51 | B46: Comercio al por mayor | C46: 375 | D46: 373 | E46: 384 | F46: 396 | G46: 406 | H46: 371 | I46: 324 | J46: 358 | K46: 367 | L46: 387 | M46: 416 | N46: 438 | O46: 462 | P46: 458 | Q46: 488 | R46: 509 | S46: 530 | T46: 543 | U46: 540 | V46: 577 | W46: 587 | X46: 590 | Y46: 586 | Z46: 582 | AA46: 570 | AB46: 601 | AC46: 645 | AD46: 647 | AE46: 631
A47: 52 | B47: Comercio al por menor | C47: 1162 | D47: 1147 | E47: 1141 | F47: 1135 | G47: 1165 | H47: 1078 | I47: 979 | J47: 1071 | K47: 1206 | L47: 1265 | M47: 1416 | N47: 1515 | O47: 1628 | P47: 1698 | Q47: 1733 | R47: 1837 | S47: 1906 | T47: 1988 | U47: 1999 | V47: 2053 | W47: 2157 | X47: 2155 | Y47: 2145 | Z47: 2043 | AA47: 1952 | AB47: 1971 | AC47: 2238 | AD47: 2404 | AE47: 2162
A48: H | B48: HOTELERIA Y RESTAURANTES | C48: 132 | D48: 127 | E48: 116 | F48: 107 | G48: 106 | H48: 104 | I48: 95 | J48: 99 | K48: 108 | L48: 116 | M48: 137 | N48: 152 | O48: 174 | P48: 185 | Q48: 190 | R48: 201 | S48: 216 | T48: 229 | U48: 249 | V48: 241 | W48: 251 | X48: 253 | Y48: 255 | Z48: 233 | AA48: 189 | AB48: 192 | AC48: 219 | AD48: 245 | AE48: 233
A49: 55 | B49: Servicios de hoteleria y restaurantes | C49: 132 | D49: 127 | E49: 116 | F49: 107 | G49: 106 | H49: 104 | I49: 95 | J49: 99 | K49: 108 | L49: 116 | M49: 137 | N49: 152 | O49: 174 | P49: 185 | Q49: 190 | R49: 201 | S49: 216 | T49: 229 | U49: 249 | V49: 241 | W49: 251 | X49: 253 | Y49: 255 | Z49: 233 | AA49: 189 | AB49: 192 | AC49: 219 | AD49: 245 | AE49: 233
A50: I | B50: SERVICIOS DE TRANSPORTE, DE ALMACENAMIENTO Y DE COMUNICACIONES | C50: 261 | D50: 280 | E50: 276 | F50: 286 | G50: 293 | H50: 264 | I50: 238 | J50: 255 | K50: 270 | L50: 304 | M50: 348 | N50: 390 | O50: 419 | P50: 419 | Q50: 457 | R50: 520 | S50: 521 | T50: 499 | U50: 511 | V50: 533 | W50: 533 | X50: 557 | Y50: 545 | Z50: 526 | AA50: 526 | AB50: 517 | AC50: 567 | AD50: 586 | AE50: 561
A51: 60 | B51: Transporte ferroviario y automotor y por tuberias | C51: 199 | D51: 199 | E51: 184 | F51: 188 | G51: 188 | H51: 161 | I51: 140 | J51: 156 | K51: 169 | L51: 208 | M51: 241 | N51: 272 | O51: 300 | P51: 290 | Q51: 324 | R51: 378 | S51: 389 | T51: 376 | U51: 391 | V51: 404 | W51: 391 | X51: 411 | Y51: 400 | Z51: 382 | AA51: 382 | AB51: 377 | AC51: 414 | AD51: 430 | AE51: 410
A52: 61 | B52: Transporte marítimo y fluvial | C52: s.d. | D52: s.d. | E52: s.d. | F52: s.d. | G52: s.d. | H52: s.d. | I52: s.d. | J52: s.d. | K52: s.d. | L52: s.d. | M52: s.d. | N52: s.d. | O52: s.d. | P52: s.d. | Q52: s.d. | R52: s.d. | S52: s.d. | T52: s.d. | U52: s.d. | V52: s.d. | W52: s.d. | X52: s.d. | Y52: s.d. | Z52: s.d. | AA52: s.d. | AB52: s.d. | AC52: s.d. | AD52: s.d. | AE52: s.d.
A53: 62 | B53: Transporte aéreo de cargas y de pasajeros | C53: s.d. | D53: s.d. | E53: s.d. | F53: s.d. | G53: s.d. | H53: s.d. | I53: s.d. | J53: s.d. | K53: s.d. | L53: s.d. | M53: s.d. | N53: s.d. | O53: s.d. | P53: s.d. | Q53: s.d. | R53: s.d. | S53: s.d. | T53: s.d. | U53: s.d. | V53: s.d. | W53: s.d. | X53: s.d. | Y53: s.d. | Z53: s.d. | AA53: s.d. | AB53: s.d. | AC53: s.d. | AD53: s.d. | AE53: s.d.
A54: 63 | B54: Manipulación de carga, almacenamiento y depósito | C54: 29 | D54: 37 | E54: 37 | F54: 35 | G54: 38 | H54: 36 | I54: 35 | J54: 35 | K54: 38 | L54: 37 | M54: 49 | N54: 58 | O54: 62 | P54: 67 | Q54: 71 | R54: 82 | S54: 79 | T54: 71 | U54: 68 | V54: 72 | W54: 78 | X54: 82 | Y54: 79 | Z54: 76 | AA54: 78 | AB54: 74 | AC54: 84 | AD54: 89 | AE54: 88
A55: 64 | B55: Telecomunicaciones y correos | C55: 31 | D55: 41 | E55: 50 | F55: 58 | G55: 64 | H55: 64 | I55: 60 | J55: 61 | K55: 61 | L55: 56 | M55: 57 | N55: 57 | O55: 54 | P55: 59 | Q55: 57 | R55: 55 | S55: 49 | T55: 48 | U55: 48 | V55: 52 | W55: 59 | X55: 60 | Y55: 60 | Z55: 62 | AA55: 60 | AB55: 61 | AC55: 66 | AD55: 64 | AE55: 60
A56: J | B56: INTERMEDIACION FINANCIERA Y OTROS SERVICIOS FINANCIEROS | C56: 87 | D56: 87 | E56: 98 | F56: 103 | G56: 111 | H56: 111 | I56: 97 | J56: 92 | K56: 94 | L56: 98 | M56: 102 | N56: 108 | O56: 108 | P56: 103 | Q56: 103 | R56: 113 | S56: 115 | T56: 115 | U56: 105 | V56: 107 | W56: 123 | X56: 125 | Y56: 118 | Z56: 116 | AA56: 124 | AB56: 122 | AC56: 131 | AD56: 132 | AE56: 127
A57: 65 | B57: Intermediacion financiera y otros servicios financieros | C57: 33 | D57: 32 | E57: 34 | F57: 32 | G57: 35 | H57: 37 | I57: 33 | J57: 30 | K57: 29 | L57: 32 | M57: 34 | N57: 33 | O57: 36 | P57: 37 | Q57: 38 | R57: 40 | S57: 39 | T57: 40 | U57: 37 | V57: 39 | W57: 42 | X57: 44 | Y57: 43 | Z57: 46 | AA57: 45 | AB57: 42 | AC57: 45 | AD57: 41 | AE57: 45
A58: 66 | B58: Seguros | C58: 38 | D58: 36 | E58: 43 | F58: 50 | G58: 54 | H58: 49 | I58: 42 | J58: 40 | K58: 41 | L58: 43 | M58: 44 | N58: 48 | O58: 45 | P58: 34 | Q58: 33 | R58: 36 | S58: 36 | T58: 35 | U58: 32 | V58: 34 | W58: 38 | X58: 35 | Y58: 32 | Z58: 31 | AA58: 35 | AB58: 34 | AC58: 34 | AD58: 34 | AE58: 34
A59: 67 | B59: Servicios auxiliares a la actividad financiera | C59: 16 | D59: 19 | E59: 21 | F59: 21 | G59: 22 | H59: 25 | I59: 22 | J59: 22 | K59: 24 | L59: 23 | M59: 24 | N59: 27 | O59: 27 | P59: 32 | Q59: 32 | R59: 37 | S59: 40 | T59: 40 | U59: 36 | V59: 34 | W59: 43 | X59: 46 | Y59: 43 | Z59: 39 | AA59: 44 | AB59: 46 | AC59: 52 | AD59: 57 | AE59: 48
A60: K | B60: SERVICIOS INMOBILIARIOS, EMPRESARIALES Y DE ALQUILER | C60: 901 | D60: 904 | E60: 931 | F60: 932 | G60: 993 | H60: 926 | I60: 830 | J60: 836 | K60: 898 | L60: 915 | M60: 976 | N60: 1003 | O60: 1045 | P60: 1022 | Q60: 1041 | R60: 1084 | S60: 1052 | T60: 1058 | U60: 1057 | V60: 1041 | W60: 983 | X60: 978 | Y60: 944 | Z60: 873 | AA60: 819 | AB60: 793 | AC60: 846 | AD60: 957 | AE60: 806
A61: 70 | B61: Servicios inmobiliarios | C61: 428 | D61: 420 | E61: 414 | F61: 400 | G61: 401 | H61: 375 | I61: 330 | J61: 332 | K61: 339 | L61: 335 | M61: 341 | N61: 349 | O61: 353 | P61: 342 | Q61: 346 | R61: 349 | S61: 338 | T61: 340 | U61: 334 | V61: 319 | W61: 300 | X61: 282 | Y61: 267 | Z61: 245 | AA61: 242 | AB61: 232 | AC61: 233 | AD61: 232 | AE61: 204
A62: 71 | B62: Alquiler de equipo de transporte y de maquinaria | C62: 14 | D62: s.d. | E62: s.d. | F62: 16 | G62: 18 | H62: 17 | I62: 14 | J62: 19 | K62: 20 | L62: 20 | M62: 24 | N62: 24 | O62: 27 | P62: s.d. | Q62: s.d. | R62: s.d. | S62: 23 | T62: 22 | U62: 26 | V62: 25 | W62: 27 | X62: 26 | Y62: 27 | Z62: 30 | AA62: 23 | AB62: 20 | AC62: 17 | AD62: 17 | AE62: 16
A63: 72 | B63: Actividades de informática | C63: 17 | D63: 21 | E63: 19 | F63: s.d. | G63: s.d. | H63: s.d. | I63: s.d. | J63: s.d. | K63: s.d. | L63: s.d. | M63: s.d. | N63: 29 | O63: 29 | P63: s.d. | Q63: 24 | R63: 36 | S63: 40 | T63: 44 | U63: 49 | V63: 46 | W63: 41 | X63: 45 | Y63: 39 | Z63: 40 | AA63: 39 | AB63: 53 | AC63: 68 | AD63: 82 | AE63: 69
A64: 73 | B64: Investigación y desarrollo | C64: s.d. | D64: s.d. | E64: s.d. | F64: s.d. | G64: s.d. | H64: s.d. | I64: s.d. | J64: s.d. | K64: s.d. | L64: s.d. | M64: s.d. | N64: 4 | O64: 4 | P64: s.d. | Q64: s.d. | R64: s.d. | S64: 5 | T64: 8 | U64: 8 | V64: 6 | W64: 5 | X64: 5 | Y64: 6 | Z64: 8 | AA64: 7 | AB64: 8 | AC64: 8 | AD64: 8 | AE64: 8
A65: 74 | B65: Servicios jurídicos, contables y otros servicios a empresas | C65: 438 | D65: 446 | E65: 476 | F65: 492 | G65: 542 | H65: 508 | I65: 465 | J65: 463 | K65: 507 | L65: 528 | M65: 573 | N65: 586 | O65: 619 | P65: 612 | Q65: 632 | R65: 661 | S65: 633 | T65: 632 | U65: 629 | V65: 634 | W65: 598 | X65: 608 | Y65: 594 | Z65: 542 | AA65: 500 | AB65: 472 | AC65: 512 | AD65: 610 | AE65: 498
A66: 75 | B66: Agencias de empleo eventual | C66: s.d. | D66: 4 | E66: 6 | F66: 9 | G66: 9 | H66: 11 | I66: 10 | J66: 10 | K66: 12 | L66: 10 | M66: 11 | N66: 11 | O66: 13 | P66: 13 | Q66: 12 | R66: 13 | S66: 13 | T66: 12 | U66: 11 | V66: 11 | W66: 12 | X66: 12 | Y66: 11 | Z66: 8 | AA66: 8 | AB66: 8 | AC66: 8 | AD66: 8 | AE66: 11
A67: M | B67: ENSEÑANZA | C67: 87 | D67: 91 | E67: 90 | F67: 90 | G67: 82 | H67: 76 | I67: 69 | J67: 74 | K67: 81 | L67: 84 | M67: 93 | N67: 96 | O67: 101 | P67: 105 | Q67: 106 | R67: 103 | S67: 110 | T67: 122 | U67: 132 | V67: 132 | W67: 131 | X67: 132 | Y67: 137 | Z67: 136 | AA67: 137 | AB67: 134 | AC67: 142 | AD67: 166 | AE67: 153
A68: 80 | B68: Enseñanza | C68: 87 | D68: 91 | E68: 90 | F68: 90 | G68: 82 | H68: 76 | I68: 69 | J68: 74 | K68: 81 | L68: 84 | M68: 93 | N68: 96 | O68: 101 | P68: 105 | Q68: 106 | R68: 103 | S68: 110 | T68: 122 | U68: 132 | V68: 132 | W68: 131 | X68: 132 | Y68: 137 | Z68: 136 | AA68: 137 | AB68: 134 | AC68: 142 | AD68: 166 | AE68: 153
A69: N | B69: SERVICIOS SOCIALES Y DE SALUD | C69: 322 | D69: 326 | E69: 330 | F69: 332 | G69: 329 | H69: 326 | I69: 313 | J69: 307 | K69: 317 | L69: 326 | M69: 331 | N69: 333 | O69: 358 | P69: 385 | Q69: 373 | R69: 385 | S69: 396 | T69: 416 | U69: 410 | V69: 431 | W69: 452 | X69: 452 | Y69: 466 | Z69: 465 | AA69: 466 | AB69: 460 | AC69: 477 | AD69: 492 | AE69: 489
A70: 85 | B70: Servicios sociales y de salud | C70: 322 | D70: 326 | E70: 330 | F70: 332 | G70: 329 | H70: 326 | I70: 313 | J70: 307 | K70: 317 | L70: 326 | M70: 331 | N70: 333 | O70: 358 | P70: 385 | Q70: 373 | R70: 385 | S70: 396 | T70: 416 | U70: 410 | V70: 431 | W70: 452 | X70: 452 | Y70: 466 | Z70: 465 | AA70: 466 | AB70: 460 | AC70: 477 | AD70: 492 | AE70: 489
A71: O | B71: SERVICIOS COMUNITARIOS, SOCIALES Y PERSONALES N.C.P. | C71: 660 | D71: 676 | E71: 672 | F71: 665 | G71: 699 | H71: 646 | I71: 620 | J71: 650 | K71: 705 | L71: 722 | M71: 728 | N71: 736 | O71: 754 | P71: 805 | Q71: 789 | R71: 803 | S71: 830 | T71: 821 | U71: 812 | V71: 824 | W71: 858 | X71: 821 | Y71: 808 | Z71: 771 | AA71: 722 | AB71: 703 | AC71: 746 | AD71: 838 | AE71: 693
A72: 90 | B72: Eliminación de desperdicios | C72: s.d. | D72: s.d. | E72: s.d. | F72: s.d. | G72: s.d. | H72: s.d. | I72: s.d. | J72: 4 | K72: s.d. | L72: s.d. | M72: s.d. | N72: s.d. | O72: s.d. | P72: s.d. | Q72: s.d. | R72: s.d. | S72: s.d. | T72: s.d. | U72: 4 | V72: 4 | W72: 4 | X72: s.d. | Y72: 6 | Z72: 7 | AA72: 5 | AB72: 5 | AC72: 5 | AD72: 5 | AE72: 4
A73: 91 | B73: Servicios de organizaciones empresariales | C73: 325 | D73: 344 | E73: 343 | F73: 352 | G73: 359 | H73: 348 | I73: 345 | J73: 357 | K73: 364 | L73: 364 | M73: 361 | N73: 359 | O73: 364 | P73: 380 | Q73: 383 | R73: 383 | S73: 400 | T73: 415 | U73: 416 | V73: 429 | W73: 445 | X73: 444 | Y73: 442 | Z73: 439 | AA73: 439 | AB73: 430 | AC73: 429 | AD73: 421 | AE73: 411
A74: 92 | B74: Servicios culturales, deportivos y de esparcimiento | C74: s.d. | D74: s.d. | E74: s.d. | F74: s.d. | G74: s.d. | H74: s.d. | I74: s.d. | J74: 75 | K74: s.d. | L74: s.d. | M74: s.d. | N74: s.d. | O74: s.d. | P74: s.d. | Q74: s.d. | R74: s.d. | S74: s.d. | T74: s.d. | U74: 177 | V74: 177 | W74: 183 | X74: 170 | Y74: 172 | Z74: 166 | AA74: 140 | AB74: 139 | AC74: 157 | AD74: 177 | AE74: 134
A75: 93 | B75: Servicios n.c.p. | C75: 237 | D75: 228 | E75: 227 | F75: 213 | G75: 247 | H75: 217 | I75: 201 | J75: 214 | K75: 246 | L75: 261 | M75: 265 | N75: 269 | O75: 280 | P75: 301 | Q75: 267 | R75: 256 | S75: 260 | T75: 228 | U75: 215 | V75: 214 | W75: 226 | X75: s.d. | Y75: 188 | Z75: 159 | AA75: 138 | AB75: 129 | AC75: 155 | AD75: 235 | AE75: 144
B76: TOTAL | C76: 8548 | D76: 8358 | E76: 8194 | F76: 8128 | G76: 8437 | H76: 7592 | I76: 6725 | J76: 6853 | K76: 7211 | L76: 7495 | M76: 7965 | N76: 8303 | O76: 8887 | P76: 9101 | Q76: 8749 | R76: 9358 | S76: 9534 | T76: 9728 | U76: 9651 | V76: 9701 | W76: 9852 | X76: 9840 | Y76: 9763 | Z76: 9365 | AA76: 9017 | AB76: 9028 | AC76: 9717 | AD76: 10311 | AE76: 9574
A78: Notas:
A79: 1 - Las empresas se encuentran clasificadas por provincia según las zonas donde declaran que trabajan las personas.
A80: 2 - Las firmas con participación accionaria privada y estatal se incluye dentro del sector privado
A81: 3 - s/d : Dato no publicado para resguardar el secreto estadístico de las firmas
A82: Fuente: STEySS - Dirección Nacional de Estudios y Estadísticas Laborales - Observatorio de Empleo y Dinámica Empresarial, en base a SIPA.

Sheet Chubut
D1: Volver al índice
A2: CHUBUT
A3: Empresas del sector privado por rama de actividad - Activas en cada año
B4: Ramas de actividad | C4: 1996 | D4: 1997 | E4: 1998 | F4: 1999 | G4: 2000 | H4: 2001 | I4: 2002 | J4: 2003 | K4: 2004 | L4: 2005 | M4: 2006 | N4: 2007 | O4: 2008 | P4: 2009 | Q4: 2010 | R4: 2011 | S4: 2012 | T4: 2013 | U4: 2014 | V4: 2015 | W4: 2016 | X4: 2017 | Y4: 2018 | Z4: 2019 | AA4: 2020 | AB4: 2021 | AC4: 2022 | AD4: 2023 | AE4: 2024
D5: 2º Trim 1996 | F5: 3º Trim 1996 | H5: 4º Trim 1996 | J5: 1º Trim 1997 | L5: 2º Trim 1997 | N5: 3º Trim 1997 | P5: 4º Trim 1997 | R5: 1º Trim 1998
A6: A | B6: AGRICULTURA, GANADERIA, CAZA Y SILVICULTURA | C6: 668 | D6: 648 | E6: 806 | F6: 868 | G6: 905 | H6: 872 | I6: 853 | J6: 879 | K6: 939 | L6: 970 | M6: 963 | N6: 965 | O6: 963 | P6: 901 | Q6: 928 | R6: 884 | S6: 833 | T6: 783 | U6: 774 | V6: 731 | W6: 733 | X6: 690 | Y6: 700 | Z6: 697 | AA6: 679 | AB6: 661 | AC6: 681 | AD6: 625 | AE6: 596
A7: 1 | B7: Agricultura y ganaderia | C7: 664 | D7: 644 | E7: 800 | F7: 859 | G7: 891 | H7: 860 | I7: 844 | J7: 872 | K7: 931 | L7: 960 | M7: 950 | N7: 952 | O7: 948 | P7: 888 | Q7: 900 | R7: 871 | S7: 822 | T7: 773 | U7: 762 | V7: 721 | W7: 722 | X7: 680 | Y7: 689 | Z7: 685 | AA7: 668 | AB7: 652 | AC7: 672 | AD7: 617 | AE7: 589
A8: 2 | B8: Silvicultura, extracción de madera | C8: 4 | D8: 4 | E8: 6 | F8: 9 | G8: 14 | H8: 12 | I8: 9 | J8: 7 | K8: 8 | L8: 10 | M8: 13 | N8: 13 | O8: 15 | P8: 13 | Q8: 28 | R8: 13 | S8: 11 | T8: 10 | U8: 12 | V8: 10 | W8: 11 | X8: 10 | Y8: 11 | Z8: 12 | AA8: 11 | AB8: 9 | AC8: 9 | AD8: 8 | AE8: 7
